Workbook

Sheet Metadata
A1: cod | B1: Variable | C1: Fuente | D1: Sector económico | E1: Unidad | F1: Agregación trimestre | G1: Comentarios
A2: v_1 | B2: IPC Ecuador | F2: Promedio
A3: v_2 | B3: IPC USA | F3: Promedio
A4: v_3 | B4: Gastos (SPNF) | F4: Suma
A5: v_4 | B5: Ingresos (SPNF) | F5: Suma
A6: v_5 | B6: Resultado global (SPNF) | F6: Suma
A7: v_6 | B7: Exportaciones totales | F7: Suma
A8: v_7 | B8: Importaciones totales | F8: Suma
A9: v_8 | B9: Balanza comercial | F9: Suma
A10: v_9 | B10: Precio petróleo WTI | F10: Promedio
A11: v_10 | B11: Pib nominal (Millones USD)
A12: v_11 | B12: Paridad precios EC-USA
A13: v_12 | B13: Deflactor USA, sa, 100=2018
A14: v_13 | B14: Deflactor PIB EC, sa
A15: v_14 | B15: Deflactor PIB EC, sa, base 2014
A16: v_15 | B16: IPC Ecuador, sa, 100=2014, PPP
A17: v_16 | B17: IPC USA, sa, 100=2014
A18: v_17 | B18: Deflactor PIB EC, sa, 100=dic2018, PPP
A19: v_18 | B19: IPC Ecuador, sa, 100=2019, PPP
A20: v_19 | B20: IPC USA, sa, 100=2019
A21: v_20 | B21: Ingresos petroleros SPNF
A22: v_21 | B22: Deflactor PIB GCFH, sa, 100=dic2018, PPP
... A42: V_41 | B42: PIB REAL ECU (1998=100)

Sheet Data
B1: v_1 | C1: v_2 | D1: v_3 | E1: v_4 | F1: v_5 | G1: v_6 | H1: v_7 | I1: v_8 | J1: v_9 | K1: v_11 | L1: V_38 | M1: V_39 | O1: Total ingresos | P1: Ingresos Petroleros | Q1: Ingresos no petroleros | R1: Ingresos tributarios
A2: 36404
A3: 36434 | B3: 21.558464 | C3: 168.2 | L3: =B3*54.2221/B$137 -> 13.577413 | M3: =C3*100/C$137 -> 76.740929 | N3: =L3/M3 -> 0.17692532
A4: 36465 | B4: 22.934536 | C4: 168.3 | L4: =B4*54.2221/B$137 -> 14.444057 | M4: =C4*100/C$137 -> 76.786553 | N4: =L4/M4 -> 0.18810659
A5: 36495 | B5: 24.213474 | C5: 168.3 | L5: =B5*54.2221/B$137 -> 15.249525 | M5: =C5*100/C$137 -> 76.786553 | N5: =L5/M5 -> 0.1985963
A6: 36526 | B6: 27.684413 | C6: 168.8 | L6: =B6*54.2221/B$137 -> 17.435506 | M6: =C6*100/C$137 -> 77.014678 | N6: =L6/M6 -> 0.22639198
A7: 36557 | B7: 30.46246 | C7: 169.8 | L7: =B7*54.2221/B$137 -> 19.185106 | M7: =C7*100/C$137 -> 77.470926 | N7: =L7/M7 -> 0.24764266
A8: 36586 | B8: 32.766707 | C8: 171.2 | L8: =B8*54.2221/B$137 -> 20.636309 | M8: =C8*100/C$137 -> 78.109673 | N8: =L8/M8 -> 0.26419658
A9: 36617 | B9: 36.112451 | C9: 171.3 | L9: =B9*54.2221/B$137 -> 22.743442 | M9: =C9*100/C$137 -> 78.155298 | N9: =L9/M9 -> 0.2910032
A10: 36647 | B10: 37.968799 | C10: 171.5 | L10: =B10*54.2221/B$137 -> 23.91256 | M10: =C10*100/C$137 -> 78.246547 | N10: =L10/M10 -> 0.30560531
A11: 36678 | B11: 39.987038 | C11: 172.4 | L11: =B11*54.2221/B$137 -> 25.183637 | M11: =C11*100/C$137 -> 78.657171 | N11: =L11/M11 -> 0.32016963
A12: 36708 | B12: 40.935719 | C12: 172.8 | L12: =B12*54.2221/B$137 -> 25.781112 | M12: =C12*100/C$137 -> 78.83967 | N12: =L12/M12 -> 0.32700684
A13: 36739 | B13: 41.492623 | C13: 172.8 | L13: =B13*54.2221/B$137 -> 26.131847 | M13: =C13*100/C$137 -> 78.83967 | N13: =L13/M13 -> 0.33145556
A14: 36770 | B14: 43.019793 | C14: 173.7 | L14: =B14*54.2221/B$137 -> 27.093652 | M14: =C14*100/C$137 -> 79.250293 | N14: =L14/M14 -> 0.34187446
... A29: 37226 | B29: 56.624021 | C29: 176.7 | L29: =B29*54.2221/B$137 -> 35.661526 | M29: =C29*100/C$137 -> 80.619037 | N29: =L29/M29 -> 0.44234621
A30: 37257 | B30: 57.646091 | C30: 177.1 | D30: 390.83 | E30: 502.41 | F30: 111.58 | G30: 350.159 | H30: 502 | I30: =G30-H30 -> -151.841 | J30: 19.687619 | K30: 50 | L30: =B30*54.2221/B$137 -> 36.305221 | M30: =C30*100/C$137 -> 80.801537 | N30: =L30/M30 -> 0.4493135 | O30: 502.4135 | P30: 107.782 | Q30: 373.44646 | R30: 248.86259
A31: 37288 | B31: 58.261277 | C31: 177.8 | D31: 462.87 | E31: 490.39 | F31: 27.52 | G31: 346.297 | H31: 406.7 | I31: =G31-H31 -> -60.403 | J31: 20.723158 | K31: 50.533588 | L31: =B31*54.2221/B$137 -> 36.692662 | M31: =C31*100/C$137 -> 81.12091 | N31: =L31/M31 -> 0.45232064 | O31: 490.38181 | P31: 96.136 | Q31: 371.49855 | R31: 203.27867
A32: 37316 | B32: 58.915316 | C32: 178.8 | D32: 411.84 | E32: 443.49 | F32: 31.65 | G32: 405.99 | H32: 448.3 | I32: =G32-H32 -> -42.31 | J32: 24.377 | K32: 51.100876 | L32: =B32*54.2221/B$137 -> 37.104572 | M32: =C32*100/C$137 -> 81.577158 | N32: =L32/M32 -> 0.45484021 | O32: 443.48845 | P32: 84.473 | Q32: 349.1685 | R32: 223.51667
A33: 37347 | B33: 59.796541 | C33: 179.8 | D33: 517.14 | E33: 640.62 | F33: 123.48 | G33: 447.954 | H33: 586.9 | I33: =G33-H33 -> -138.946 | J33: 26.243182 | K33: 51.865218 | L33: =B33*54.2221/B$137 -> 37.659564 | M33: =C33*100/C$137 -> 82.033406 | N33: =L33/M33 -> 0.45907595 | O33: 640.62465 | P33: 87.933192 | Q33: 541.88227 | R33: 351.80531
A34: 37377 | B34: 60.089024 | C34: 179.8 | D34: 577.29 | E34: 531.48 | F34: -45.81 | G34: 447.788 | H34: 531.8 | I34: =G34-H34 -> -84.012 | J34: 27.044545 | K34: 52.118906 | L34: =B34*54.2221/B$137 -> 37.843768 | M34: =C34*100/C$137 -> 82.033406 | N34: =L34/M34 -> 0.46132143 | O34: 531.47698 | P34: 130.95773 | Q34: 366.77679 | R34: 219.09005
A35: 37408 | B35: 60.31837 | C35: 179.9 | D35: 445.28 | E35: 522.96 | F35: 77.68 | G35: 407.292 | H35: 533.8 | I35: =G35-H35 -> -126.508 | J35: 25.5085 | K35: 52.317831 | L35: =B35*54.2221/B$137 -> 37.988209 | M35: =C35*100/C$137 -> 82.079031 | N35: =L35/M35 -> 0.46282477 | O35: 522.95648 | P35: 103.42 | Q35: 408.87317 | R35: 227.32935
A36: 37438 | B36: 60.278437 | C36: 180.1 | D36: 455.95 | E36: 543.8 | F36: 87.85 | G36: 421.499 | H36: 519.1 | I36: =G36-H36 -> -97.601 | J36: 26.92381 | K36: 52.283195 | L36: =B36*54.2221/B$137 -> 37.963059 | M36: =C36*100/C$137 -> 82.170281 | N36: =L36/M36 -> 0.46200474 | O36: 543.79836 | P36: 107.85223 | Q36: 398.05195 | R36: 248.91106
A37: 37469 | B37: 60.541779 | C37: 180.7 | D37: 549.18 | E37: 482.5 | F37: -66.68 | G37: 443.682 | H37: 571.3 | I37: =G37-H37 -> -127.618 | J37: 28.370455 | K37: 52.511608 | L37: =B37*54.2221/B$137 -> 38.128911 | M37: =C37*100/C$137 -> 82.44403 | N37: =L37/M37 -> 0.46248238 | O37: 482.49788 | P37: 125.19023 | Q37: 346.11475 | R37: 224.48867
A38: 37500 | B38: 60.890924 | C38: 181 | D38: 480.47 | E38: 621.47 | F38: 141 | G38: 447.007 | H38: 510.9 | I38: =G38-H38 -> -63.893 | J38: 29.67 | K38: 52.814442 | L38: =B38*54.2221/B$137 -> 38.3488 | M38: =C38*100/C$137 -> 82.580904 | N38: =L38/M38 -> 0.46437855 | O38: 621.46729 | P38: 148.37023 | Q38: 461.04229 | R38: 251.22467
A39: 37530 | B39: 61.283779 | C39: 181.3 | D39: 505.94 | E39: 607.49 | F39: 101.55 | G39: 428.504 | H39: 589.9 | I39: =G39-H39 -> -161.396 | J39: 28.85087 | K39: 53.15519 | L39: =B39*54.2221/B$137 -> 38.596218 | M39: =C39*100/C$137 -> 82.717779 | N39: =L39/M39 -> 0.46660124 | O39: 607.48556 | P39: 146.19523 | Q39: 449.91365 | R39: 233.85567
A40: 37561 | B40: 61.709552 | C40: 181.3 | D40: 637.7 | E40: 482.82 | F40: -154.88 | G40: 444.137 | H40: 481.5 | I40: =G40-H40 -> -37.363 | J40: 26.283158 | K40: 53.524489 | L40: =B40*54.2221/B$137 -> 38.864368 | M40: =C40*100/C$137 -> 82.717779 | N40: =L40/M40 -> 0.46984299 | O40: 482.82309 | P40: 111.66923 | Q40: 355.07112 | R40: 213.45317
A41: 37591 | B41: 61.921629 | C41: 180.9 | D41: 726.69 | E41: 491.46 | F41: -235.23 | G41: 445.81 | H41: 499.1 | I41: =G41-H41 -> -53.29 | J41: 29.435714 | K41: 53.708436 | L41: =B41*54.2221/B$137 -> 38.997933 | M41: =C41*100/C$137 -> 82.535279 | N41: =L41/M41 -> 0.47250017 | O41: 491.46232 | P41: 142.78223 | Q41: 359.07298 | R41: 260.48667
... A76: 38657 | B76: 68.851363 | C76: 197.6 | D76: 753.48 | E76: 761.15 | F76: 7.67 | G76: 897.14044 | H76: 972.7 | I76: =G76-H76 -> -75.55956 | J76: 58.283 | K76: 59.719021 | L76: =B76*54.2221/B$137 -> 43.362245 | M76: =C76*100/C$137 -> 90.154622 | N76: =L76/M76 -> 0.4809764 | O76: 761.15081 | P76: 195.51212 | Q76: 512.95154 | R76: 315.90876
A77: 38687 | B77: 69.056665 | C77: 196.8 | D77: 1113.64 | E77: 804.53 | F77: -309.11 | G77: 981.39005 | H77: 790.7 | I77: =G77-H77 -> 190.69005 | J77: 59.414286 | K77: 59.897092 | L77: =B77*54.2221/B$137 -> 43.491543 | M77: =C77*100/C$137 -> 89.789624 | N77: =L77/M77 -> 0.4843716 | O77: 804.53002 | P77: 86.789819 | Q77: 696.37014 | R77: 338.03519 | S77: =SUM(O153:O155) -> 0 | T77: =SUM(P153:P155) -> 0 | U77: =SUM(Q153:Q155) -> 0 | V77: =SUM(R153:R155) -> 0
A78: 38718 | B78: 69.386835 | C78: 198.3 | D78: 591.91 | E78: 965.68 | F78: 373.77 | G78: 1023.2616 | H78: 827.8 | I78: =G78-H78 -> 195.4616 | J78: 65.4835 | K78: 60.183469 | L78: =B78*54.2221/B$137 -> 43.699483 | M78: =C78*100/C$137 -> 90.473996 | N78: =L78/M78 -> 0.483006 | O78: 965.68623 | P78: 291.76078 | Q78: 658.03129 | R78: 412.20943
A79: 38749 | B79: 69.87796 | C79: 198.7 | D79: 751.49 | E79: 631.88 | F79: -119.61 | G79: 947.89876 | H79: 710.6 | I79: =G79-H79 -> 237.29876 | J79: 61.615263 | K79: 60.609452 | L79: =B79*54.2221/B$137 -> 44.008791 | M79: =C79*100/C$137 -> 90.656495 | N79: =L79/M79 -> 0.48544554 | O79: 631.88142 | P79: 206.912 | Q79: 425.54179 | R79: 251.86427
A80: 38777 | B80: 70.333289 | C80: 199.8 | D80: 872.49 | E80: 944.38 | F80: 71.89 | G80: 1058.5531 | H80: 989.9 | I80: =G80-H80 -> 68.6531 | J80: 62.889565 | K80: 61.004387 | L80: =B80*54.2221/B$137 -> 44.295555 | M80: =C80*100/C$137 -> 91.158368 | N80: =L80/M80 -> 0.48591869 | O80: 944.37881 | P80: 232.84809 | Q80: 681.41926 | R80: 375.88433 | S80: =SUM(O156:O158) -> 0 | T80: =SUM(P156:P158) -> 0 | U80: =SUM(Q156:Q158) -> 0 | V80: =SUM(R156:R158) -> 0
A81: 38808 | B81: 70.38145 | C81: 201.5 | D81: 727.77 | E81: 1131.54 | F81: 403.77 | G81: 1176.7875 | H81: 852.1 | I81: =G81-H81 -> 324.68752 | J81: 69.412778 | K81: 61.04616 | L81: =B81*54.2221/B$137 -> 44.325887 | M81: =C81*100/C$137 -> 91.93399 | N81: =L81/M81 -> 0.48214906 | O81: 1131.5403 | P81: 223.011 | Q81: 994.34731 | R81: 757.62769
A82: 38838 | B82: 70.284315 | C82: 202.5 | D82: 793.5 | E82: 1100.05 | F82: 306.55 | G82: 1086.7671 | H82: 1015.5 | I82: =G82-H82 -> 71.26712 | J82: 70.933182 | K82: 60.961909 | L82: =B82*54.2221/B$137 -> 44.264711 | M82: =C82*100/C$137 -> 92.390238 | N82: =L82/M82 -> 0.47910594 | O82: 1100.0516 | P82: 365.32689 | Q82: 712.2577 | R82: 408.51326
A83: 38869 | B83: 70.122692 | C83: 202.9 | D83: 822.22 | E83: 867.05 | F83: 44.83 | G83: 1059.5297 | H83: 874.2 | I83: =G83-H83 -> 185.32967 | J83: 70.931818 | K83: 60.821723 | L83: =B83*54.2221/B$137 -> 44.162922 | M83: =C83*100/C$137 -> 92.572737 | N83: =L83/M83 -> 0.47706186 | O83: 867.04725 | P83: 239.01207 | Q83: 680.00231 | R83: 358.80179 | S83: =SUM(O159:O161) -> 0 | T83: =SUM(P159:P161) -> 0 | U83: =SUM(Q159:Q161) -> 0 | V83: =SUM(R159:R161) -> 0
A84: 38899 | B84: 70.143546 | C84: 203.5 | D84: 723.49 | E84: 902.16 | F84: 178.67 | G84: 1041.9202 | H84: 971 | I84: =G84-H84 -> 70.9202 | J84: 74.404211 | K84: 60.839811 | L84: =B84*54.2221/B$137 -> 44.176056 | M84: =C84*100/C$137 -> 92.846486 | N84: =L84/M84 -> 0.47579675 | O84: 902.1569 | P84: 277.40278 | Q84: 655.70928 | R84: 448.18765
A85: 38930 | B85: 70.294099 | C85: 203.9 | D85: 873.06 | E85: 758.16 | F85: -114.9 | G85: 1127.6715 | H85: 998.2 | I85: =G85-H85 -> 129.47152 | J85: 73.041739 | K85: 60.970394 | L85: =B85*54.2221/B$137 -> 44.270873 | M85: =C85*100/C$137 -> 93.028985 | N85: =L85/M85 -> 0.47588257 | O85: 758.16661 | P85: 197.26423 | Q85: 594.32739 | R85: 374.30821
A86: 38961 | B86: 70.696813 | C86: 202.9 | D86: 796.16 | E86: 794.35 | F86: -1.81 | G86: 1096.9109 | H86: 1048 | I86: =G86-H86 -> 48.91086 | J86: 63.819 | K86: 61.319693 | L86: =B86*54.2221/B$137 -> 44.524501 | M86: =C86*100/C$137 -> 92.572737 | N86: =L86/M86 -> 0.48096774 | O86: 794.35046 | P86: 72.342065 | Q86: 764.03796 | R86: 446.20029 | S86: =SUM(O162:O164) -> 0 | T86: =SUM(P162:P164) -> 0 | U86: =SUM(Q162:Q164) -> 0 | V86: =SUM(R162:R164) -> 0
A87: 38991 | B87: 70.943382 | C87: 201.8 | D87: 811.2 | E87: 1318.26 | F87: 507.06 | G87: 1051.8995 | H87: 1084.1 | I87: =G87-H87 -> -32.20052 | J87: 58.850455 | K87: 61.533558 | L87: =B87*54.2221/B$137 -> 44.679788 | M87: =C87*100/C$137 -> 92.070864 | N87: =L87/M87 -> 0.48527608 | O87: 1318.2641 | P87: 638.04295 | Q87: 681.3346 | R87: 358.81112
A88: 39022 | B88: 71.060782 | C88: 201.5 | D88: 897.86 | E88: 993.08 | F88: 95.22 | G88: 1044.3057 | H88: 988.1 | I88: =G88-H88 -> 56.20567 | J88: 59.1305 | K88: 61.635386 | L88: =B88*54.2221/B$137 -> 44.753726 | M88: =C88*100/C$137 -> 91.93399 | N88: =L88/M88 -> 0.48680283 | O88: 993.08067 | P88: 332.80702 | Q88: 672.04322 | R88: 384.60876
A89: 39052 | B89: 71.038173 | C89: 201.8 | D89: 1266.83 | E89: 856.12 | F89: -410.71 | G89: 1012.7375 | H89: 919.8 | I89: =G89-H89 -> 92.93753 | J89: 61.999 | K89: 61.615776 | L89: =B89*54.2221/B$137 -> 44.739488 | M89: =C89*100/C$137 -> 92.070864 | N89: =L89/M89 -> 0.48592449 | O89: 856.11426 | P89: 158.27674 | Q89: 814.16017 | R89: 375.75388 | S89: =SUM(O165:O167) -> 0 | T89: =SUM(P165:P167) -> 0 | U89: =SUM(Q165:Q167) -> 0 | V89: =SUM(R165:R167) -> 0
A90: 39083 | B90: 71.249075 | C90: 202.416 | D90: 611.04 | E90: 1019.24 | F90: 408.2 | G90: 904.45829 | H90: 1002 | I90: =G90-H90 -> -97.54171 | J90: 54.24 | K90: 61.798704 | L90: =B90*54.2221/B$137 -> 44.872312 | M90: =C90*100/C$137 -> 92.351913 | N90: =L90/M90 -> 0.48588395 | O90: 1019.2328 | P90: 226.5842 | Q90: 710.14874 | R90: 465.83711
A91: 39114 | B91: 71.297216 | C91: 203.499 | D91: 813.76 | E91: 831.52 | F91: 17.76 | G91: 927.57138 | H91: 795.9 | I91: =G91-H91 -> 131.67138 | J91: 59.25 | K91: 61.84046 | L91: =B91*54.2221/B$137 -> 44.902632 | M91: =C91*100/C$137 -> 92.84603 | N91: =L91/M91 -> 0.48362468 | O91: 831.52408 | P91: 175.22393 | Q91: 552.67778 | R91: 323.48742
A92: 39142 | B92: 71.365551 | C92: 205.352 | D92: 847.58 | E92: 878 | F92: 30.42 | G92: 1046.3581 | H92: 1068.8 | I92: =G92-H92 -> -22.44195 | J92: 60.601818 | K92: 61.899731 | L92: =B92*54.2221/B$137 -> 44.945669 | M92: =C92*100/C$137 -> 93.691458 | N92: =L92/M92 -> 0.47972003 | O92: 877.99765 | P92: 171.15802 | Q92: 656.96391 | R92: 367.4177 | S92: =SUM(O168:O170) -> 0 | T92: =SUM(P168:P170) -> 0 | U92: =SUM(Q168:Q170) -> 0 | V92: =SUM(R168:R170) -> 0
A93: 39173 | B93: 71.358784 | C93: 206.686 | D93: 856.49 | E93: 1375.99 | F93: 519.5 | G93: 1100.6165 | H93: 898.1 | I93: =G93-H93 -> 202.51652 | J93: 63.9365 | K93: 61.893862 | L93: =B93*54.2221/B$137 -> 44.941407 | M93: =C93*100/C$137 -> 94.300093 | N93: =L93/M93 -> 0.47657861 | O93: 1375.9956 | P93: 255.56315 | Q93: 1107.7111 | R93: 751.20343
A94: 39203 | B94: 71.380284 | C94: 207.949 | D94: 869.64 | E94: 986.98 | F94: 117.34 | G94: 1066.3344 | H94: 1091.6 | I94: =G94-H94 -> -25.26557 | J94: 63.450909 | K94: 61.91251 | L94: =B94*54.2221/B$137 -> 44.954947 | M94: =C94*100/C$137 -> 94.876334 | N94: =L94/M94 -> 0.47382678 | O94: 986.9742 | P94: 197.24108 | Q94: 674.24119 | R94: 410.89906
A95: 39234 | B95: 71.656888 | C95: 208.352 | D95: 889.37 | E95: 937.98 | F95: 48.61 | G95: 1185.9394 | H95: 957.2 | I95: =G95-H95 -> 228.73944 | J95: 67.491905 | K95: 62.152425 | L95: =B95*54.2221/B$137 -> 45.129151 | M95: =C95*100/C$137 -> 95.060202 | N95: =L95/M95 -> 0.47474285 | O95: 937.97586 | P95: 238.83587 | Q95: 698.84978 | R95: 364.03247 | S95: =SUM(O171:O173) -> 0 | T95: =SUM(P171:P173) -> 0 | U95: =SUM(Q171:Q173) -> 0 | V95: =SUM(R171:R173) -> 0
A96: 39264 | B96: 71.956441 | C96: 208.299 | D96: 954.92 | E96: 1238.14 | F96: 283.22 | G96: 1362.3092 | H96: 1102.9 | I96: =G96-H96 -> 259.4092 | J96: 74.141905 | K96: 62.412246 | L96: =B96*54.2221/B$137 -> 45.317808 | M96: =C96*100/C$137 -> 95.036021 | N96: =L96/M96 -> 0.47684875 | O96: 1238.1443 | P96: 392.98832 | Q96: 760.2422 | R96: 499.95395
A97: 39295 | B97: 72.008932 | C97: 207.917 | D97: 1355.09 | E97: 1317.8 | F97: -37.29 | G97: 1184.0149 | H97: 1067.7 | I97: =G97-H97 -> 116.31492 | J97: 72.378261 | K97: 62.457775 | L97: =B97*54.2221/B$137 -> 45.350866 | M97: =C97*100/C$137 -> 94.861734 | N97: =L97/M97 -> 0.47807334 | O97: 1317.7953 | P97: 225.6662 | Q97: 791.91168 | R97: 440.43783
A98: 39326 | B98: 72.520302 | C98: 208.49 | D98: 1050.94 | E98: 1258.88 | F98: 207.94 | G98: 1279.9574 | H98: 1125.9 | I98: =G98-H98 -> 154.05741 | J98: 79.906316 | K98: 62.901317 | L98: =B98*54.2221/B$137 -> 45.672925 | M98: =C98*100/C$137 -> 95.123164 | N98: =L98/M98 -> 0.48014514 | O98: 1258.8738 | P98: 350.05521 | Q98: 927.11899 | R98: 541.13617 | S98: =SUM(O174:O176) -> 0 | T98: =SUM(P174:P176) -> 0 | U98: =SUM(Q174:Q176) -> 0 | V98: =SUM(R174:R176) -> 0
A99: 39356 | B99: 72.617999 | C99: 208.936 | D99: 1210.48 | E99: 1233.69 | F99: 23.21 | G99: 1426.4442 | H99: 1304 | I99: =G99-H99 -> 122.44416 | J99: 85.903913 | K99: 62.986056 | L99: =B99*54.2221/B$137 -> 45.734454 | M99: =C99*100/C$137 -> 95.326651 | N99: =L99/M99 -> 0.47976566 | O99: 1233.6912 | P99: 320.03272 | Q99: 829.5587 | R99: 434.61761
A100: 39387 | B100: 72.979256 | C100: 210.177 | D100: 1172.19 | E100: 1268.59 | F100: 96.4 | G100: 1372.5757 | H100: 1303.8 | I100: =G100-H100 -> 68.77568 | J100: 94.755238 | K100: 63.299396 | L100: =B100*54.2221/B$137 -> 45.961972 | M100: =C100*100/C$137 -> 95.892855 | N100: =L100/M100 -> 0.47930549 | O100: 1268.5912 | P100: 352.47204 | Q100: 850.95389 | R100: 468.60104
A101: 39417 | B101: 73.396432 | C101: 210.036 | D101: 1673.96 | E101: 1283.8 | F101: -390.16 | G101: 1464.736 | H101: 1189.3 | I101: =G101-H101 -> 275.43596 | J101: 91.356667 | K101: 63.661239 | L101: =B101*54.2221/B$137 -> 46.224707 | M101: =C101*100/C$137 -> 95.828524 | N101: =L101/M101 -> 0.48236898 | O101: 1283.7966 | P101: 412.23911 | Q101: 902.44239 | R101: 497.65195 | S101: =SUM(O177:O179) -> 0 | T101: =SUM(P177:P179) -> 0 | U101: =SUM(Q177:Q179) -> 0 | V101: =SUM(R177:R179) -> 0
A102: 39448 | B102: 74.234712 | C102: 211.08 | D102: 1016.57 | E102: 1432.38 | F102: 415.81 | G102: 1574.3096 | H102: 1318 | I102: =G102-H102 -> 256.30958 | J102: 92.975714 | K102: 64.388331 | L102: =B102*54.2221/B$137 -> 46.752652 | M102: =C102*100/C$137 -> 96.304847 | N102: =L102/M102 -> 0.4854652 | O102: 1432.3735 | P102: 432.19861 | Q102: 953.79694 | R102: 622.20126
A103: 39479 | B103: 74.935165 | C103: 211.693 | D103: 1204.92 | E103: 1771.47 | F103: 566.55 | G103: 1613.8749 | H103: 1055.9 | I103: =G103-H103 -> 557.97489 | J103: 95.384 | K103: 64.995877 | L103: =B103*54.2221/B$137 -> 47.193794 | M103: =C103*100/C$137 -> 96.584527 | N103: =L103/M103 -> 0.48862686 | O103: 1771.4709 | P103: 964.12493 | Q103: 737.65128 | R103: 381.20475
A104: 39508 | B104: 76.04391 | C104: 213.528 | D104: 1442.19 | E104: 1717.35 | F104: 275.16 | G104: 1434.4892 | H104: 1248.9 | I104: =G104-H104 -> 185.58917 | J104: 105.4725 | K104: 65.957559 | L104: =B104*54.2221/B$137 -> 47.892075 | M104: =C104*100/C$137 -> 97.421742 | N104: =L104/M104 -> 0.49159535 | O104: 1717.3492 | P104: 676.67948 | Q104: 954.42442 | R104: 488.69491 | S104: =SUM(O180:O182) -> 0 | T104: =SUM(P180:P182) -> 0 | U104: =SUM(Q180:Q182) -> 0 | V104: =SUM(R180:R182) -> 0
A105: 39539 | B105: 77.198497 | C105: 214.823 | D105: 1684.08 | E105: 2052.93 | F105: 368.85 | G105: 1631.0525 | H105: 1397.8 | I105: =G105-H105 -> 233.25246 | J105: 112.61818 | K105: 66.959003 | L105: =B105*54.2221/B$137 -> 48.619229 | M105: =C105*100/C$137 -> 98.012583 | N105: =L105/M105 -> 0.49605088 | O105: 2052.9382 | P105: 732.61388 | Q105: 1284.1184 | R105: 856.1707
A106: 39569 | B106: 78.008168 | C106: 216.632 | D106: 1647.44 | E106: 2049.72 | F106: 402.28 | G106: 1967.7328 | H106: 1289.8 | I106: =G106-H106 -> 677.93281 | J106: 125.013 | K106: 67.661281 | L106: =B106*54.2221/B$137 -> 49.129156 | M106: =C106*100/C$137 -> 98.837936 | N106: =L106/M106 -> 0.4970678 | O106: 2049.7223 | P106: 1086.4721 | Q106: 873.87804 | R106: 516.69095
A107: 39600 | B107: 78.598522 | C107: 218.815 | D107: 1648.56 | E107: 1781.34 | F107: 132.78 | G107: 1897.9908 | H107: 1594.2 | I107: =G107-H107 -> 303.79076 | J107: 133.92714 | K107: 68.173331 | L107: =B107*54.2221/B$137 -> 49.500957 | M107: =C107*100/C$137 -> 99.833926 | N107: =L107/M107 -> 0.49583303 | O107: 1781.3367 | P107: 928.85431 | Q107: 803.25596 | R107: 456.33025 | S107: =SUM(O183:O185) -> 0 | T107: =SUM(P183:P185) -> 0 | U107: =SUM(Q183:Q185) -> 0 | V107: =SUM(R183:R185) -> 0
A108: 39630 | B108: 79.05926 | C108: 219.964 | D108: 2074.53 | E108: 2146.48 | F108: 71.95 | G108: 1828.069 | H108: 1722 | I108: =G108-H108 -> 106.06904 | J108: 133.37773 | K108: 68.572958 | L108: =B108*54.2221/B$137 -> 49.791128 | M108: =C108*100/C$137 -> 100.35815 | N108: =L108/M108 -> 0.49613435 | O108: 2146.4793 | P108: 910.81243 | Q108: 1106.0607 | R108: 665.77181
A109: 39661 | B109: 79.225183 | C109: 219.086 | D109: 2125.98 | E109: 2319.53 | F109: 193.55 | G109: 1819.3781 | H109: 1764.4 | I109: =G109-H109 -> 54.97805 | J109: 116.64048 | K109: 68.716873 | L109: =B109*54.2221/B$137 -> 49.895626 | M109: =C109*100/C$137 -> 99.957569 | N109: =L109/M109 -> 0.49916806 | O109: 2319.5286 | P109: 1078.9132 | Q109: 1202.5041 | R109: 528.37338
A110: 39692 | B110: 79.747573 | C110: 218.783 | D110: 1795.8 | E110: 1789.66 | F110: -6.14 | G110: 1530.5549 | H110: 1679.6 | I110: =G110-H110 -> -149.0451 | J110: 103.93667 | K110: 69.169974 | L110: =B110*54.2221/B$137 -> 50.224624 | M110: =C110*100/C$137 -> 99.819326 | N110: =L110/M110 -> 0.50315532 | O110: 1789.6549 | P110: 535.33104 | Q110: 1171.6117 | R110: 697.50541 | S110: =SUM(O186:O188) -> 0 | T110: =SUM(P186:P188) -> 0 | U110: =SUM(Q186:Q188) -> 0 | V110: =SUM(R186:R188) -> 0
A111: 39722 | B111: 79.772782 | C111: 216.573 | D111: 2136.67 | E111: 2058.71 | F111: -77.96 | G111: 1268.4164 | H111: 1804.6 | I111: =G111-H111 -> -536.1836 | J111: 76.614783 | K111: 69.19184 | L111: =B111*54.2221/B$137 -> 50.240501 | M111: =C111*100/C$137 -> 98.811017 | N111: =L111/M111 -> 0.50845039 | O111: 2058.7098 | P111: 681.34909 | Q111: 1233.9422 | R111: 604.5433
A112: 39753 | B112: 79.644603 | C112: 212.425 | D112: 1891.58 | E112: 1507.96 | F112: -383.62 | G112: 1044.178 | H112: 1488.8 | I112: =G112-H112 -> -444.62203 | J112: 57.293684 | K112: 69.080662 | L112: =B112*54.2221/B$137 -> 50.159774 | M112: =C112*100/C$137 -> 96.9185 | N112: =L112/M112 -> 0.51754592 | O112: 1507.9556 | P112: 363.24154 | Q112: 1082.9714 | R112: 557.85255
A113: 39783 | B113: 79.877734 | C113: 210.228 | D113: 3092.75 | E113: 1480.86 | F113: -1611.89 | G113: 900.55185 | H113: 1373.2 | I113: =G113-H113 -> -472.64815 | J113: 41.439048 | K113: 69.282871 | L113: =B113*54.2221/B$137 -> 50.306599 | M113: =C113*100/C$137 -> 95.916123 | N113: =L113/M113 -> 0.52448532 | O113: 1480.8561 | P113: 284.68126 | Q113: 1136.2368 | R113: 543.87028 | S113: =SUM(O189:O191) -> 0 | T113: =SUM(P189:P191) -> 0 | U113: =SUM(Q189:Q191) -> 0 | V113: =SUM(R189:R191) -> 0
A114: 39814 | B114: 80.442804 | C114: 211.143 | D114: 1137.6 | E114: 1214.02 | F114: 76.42 | G114: 873.69332 | H114: 1224.9 | I114: =G114-H114 -> -351.20668 | J114: 41.7385 | K114: 69.77299 | L114: =B114*54.2221/B$137 -> 50.662477 | M114: =C114*100/C$137 -> 96.33359 | N114: =L114/M114 -> 0.52590666 | O114: 1214.0228 | P114: 203.75662 | Q114: 953.594 | R114: 631.40107
A115: 39845 | B115: 80.817792 | C115: 212.193 | D115: 1360.63 | E115: 989.84 | F115: -370.79 | G115: 800.79863 | H115: 1031.1 | I115: =G115-H115 -> -230.30137 | J115: 39.150526 | K115: 70.098241 | L115: =B115*54.2221/B$137 -> 50.898643 | M115: =C115*100/C$137 -> 96.812651 | N115: =L115/M115 -> 0.52574371 | O115: 989.83274 | P115: 136.94016 | Q115: 724.5349 | R115: 424.89829
A116: 39873 | B116: 81.699662 | C116: 212.709 | D116: 1761.28 | E116: 1242.31 | F116: -518.97 | G116: 993.82567 | H116: 1125.8 | I116: =G116-H116 -> -131.97433 | J116: 47.520909 | K116: 70.863141 | L116: =B116*54.2221/B$137 -> 51.45404 | M116: =C116*100/C$137 -> 97.048075 | N116: =L116/M116 -> 0.53019125 | O116: 1242.3095 | P116: 311.65983 | Q116: 889.22326 | R116: 573.10359 | S116: =SUM(O192:O194) -> 0 | T116: =SUM(P192:P194) -> 0 | U116: =SUM(Q192:Q194) -> 0 | V116: =SUM(R192:R194) -> 0
A117: 39904 | B117: 82.23477 | C117: 213.24 | D117: 1798.02 | E117: 1934.04 | F117: 136.02 | G117: 1018.1491 | H117: 1021 | I117: =G117-H117 -> -2.85094 | J117: 49.809048 | K117: 71.327273 | L117: =B117*54.2221/B$137 -> 51.791048 | M117: =C117*100/C$137 -> 97.290343 | N117: =L117/M117 -> 0.53233494 | O117: 1934.0359 | P117: 367.55834 | Q117: 1486.5988 | R117: 1074.7948
A118: 39934 | B118: 82.227597 | C118: 213.856 | D118: 1370.07 | E118: 1415.31 | F118: 45.24 | G118: 1113.4417 | H118: 1121.6 | I118: =G118-H118 -> -8.15833 | J118: 59.125 | K118: 71.321051 | L118: =B118*54.2221/B$137 -> 51.786531 | M118: =C118*100/C$137 -> 97.571391 | N118: =L118/M118 -> 0.53075528 | O118: 1415.3083 | P118: 389.01589 | Q118: 940.56002 | R118: 541.51808
A119: 39965 | B119: 82.165439 | C119: 215.693 | D119: 1514.85 | E119: 1432.59 | F119: -82.26 | G119: 1167.337 | H119: 1091 | I119: =G119-H119 -> 76.33698 | J119: 69.621364 | K119: 71.267138 | L119: =B119*54.2221/B$137 -> 51.747384 | M119: =C119*100/C$137 -> 98.409519 | N119: =L119/M119 -> 0.52583718 | O119: 1432.591 | P119: 459.15527 | Q119: 874.0806 | R119: 520.05482 | S119: =SUM(O195:O197) -> 0 | T119: =SUM(P195:P197) -> 0 | U119: =SUM(Q195:Q197) -> 0 | V119: =SUM(R195:R197) -> 0
A120: 39995 | B120: 82.105065 | C120: 215.351 | D120: 1535.26 | E120: 1518.02 | F120: -17.24 | G120: 1237.4324 | H120: 1154.3 | I120: =G120-H120 -> 83.13236 | J120: 64.120455 | K120: 71.214772 | L120: =B120*54.2221/B$137 -> 51.709361 | M120: =C120*100/C$137 -> 98.253482 | N120: =L120/M120 -> 0.52628527 | O120: 1518.0217 | P120: 520.54144 | Q120: 1013.0692 | R120: 711.44172
A121: 40026 | B121: 81.860631 | C121: 215.834 | D121: 1572.44 | E121: 1314.26 | F121: -258.18 | G121: 1359.2343 | H121: 1082.5 | I121: =G121-H121 -> 276.73426 | J121: 71.06 | K121: 71.00276 | L121: =B121*54.2221/B$137 -> 51.555418 | M121: =C121*100/C$137 -> 98.47385 | N121: =L121/M121 -> 0.52354425 | O121: 1314.2621 | P121: 402.09624 | Q121: 831.52977 | R121: 524.44572
A122: 40057 | B122: 82.372647 | C122: 215.969 | D122: 1637.47 | E122: 1989.22 | F122: 351.75 | G122: 1212.6906 | H122: 1266.8 | I122: =G122-H122 -> -54.10941 | J122: 69.443333 | K122: 71.446863 | L122: =B122*54.2221/B$137 -> 51.877883 | M122: =C122*100/C$137 -> 98.535444 | N122: =L122/M122 -> 0.52648957 | O122: 1989.2162 | P122: 655.21807 | Q122: 1268.3617 | R122: 709.04556 | S122: =SUM(O198:O200) -> 0 | T122: =SUM(P198:P200) -> 0 | U122: =SUM(Q198:Q200) -> 0 | V122: =SUM(R198:R200) -> 0
A123: 40087 | B123: 82.567888 | C123: 216.177 | D123: 2052.45 | E123: 1679.89 | F123: -372.56 | G123: 1369.4901 | H123: 1285.8 | I123: =G123-H123 -> 83.69012 | J123: 75.772273 | K123: 71.616206 | L123: =B123*54.2221/B$137 -> 52.000844 | M123: =C123*100/C$137 -> 98.630343 | N123: =L123/M123 -> 0.52722968 | O123: 1679.8888 | P123: 646.43227 | Q123: 963.37819 | R123: 568.11955
A124: 40118 | B124: 82.84512 | C124: 216.33 | D124: 1885.1 | E124: 2068.69 | F124: 183.59 | G124: 1249.4477 | H124: 1274.1 | I124: =G124-H124 -> -24.65235 | J124: 77.995 | K124: 71.856667 | L124: =B124*54.2221/B$137 -> 52.175444 | M124: =C124*100/C$137 -> 98.700149 | N124: =L124/M124 -> 0.52862578 | O124: 2068.69 | P124: 591.07133 | Q124: 1385.3033 | R124: 634.35872
A125: 40148 | B125: 83.321857 | C125: 215.949 | D125: 2985.2 | E125: 1580.23 | F125: -1404.97 | G125: 1467.5175 | H125: 1418.1 | I125: =G125-H125 -> 49.41754 | J125: 74.487273 | K125: 72.270171 | L125: =B125*54.2221/B$137 -> 52.475691 | M125: =C125*100/C$137 -> 98.526319 | N125: =L125/M125 -> 0.53260582 | O125: 1580.2339 | P125: 528.05569 | Q125: 1042.43 | R125: 640.25243 | S125: =SUM(O201:O203) -> 0 | T125: =SUM(P201:P203) -> 0 | U125: =SUM(Q201:Q203) -> 0 | V125: =SUM(R201:R203) -> 0
A126: 40179 | B126: 84.01399 | C126: 216.687 | D126: 1392.48 | E126: 1974.9 | F126: 582.42 | G126: 1334.449 | H126: 1392.7 | I126: =G126-H126 -> -58.25104 | J126: 78.355263 | K126: 72.8705 | L126: =B126*54.2221/B$137 -> 52.911593 | M126: =C126*100/C$137 -> 98.86303 | N126: =L126/M126 -> 0.535201 | O126: 1974.9008 | P126: 751.38674 | Q126: 1117.9945 | R126: 752.49703
A127: 40210 | B127: 84.300315 | C127: 216.741 | D127: 1594.91 | E127: 1576.76 | F127: -18.15 | G127: 1286.1334 | H127: 1204 | I127: =G127-H127 -> 82.13341 | J127: 76.413158 | K127: 73.118848 | L127: =B127*54.2221/B$137 -> 53.091919 | M127: =C127*100/C$137 -> 98.887667 | N127: =L127/M127 -> 0.5368912 | O127: 1576.7587 | P127: 515.60063 | Q127: 956.19833 | R127: 587.33143
A128: 40238 | B128: 84.437662 | C128: 217.631 | D128: 1910.11 | E128: 2257 | F128: 346.89 | G128: 1514.7725 | H128: 1435.8 | I128: =G128-H128 -> 78.97253 | J128: 81.250435 | K128: 73.237977 | L128: =B128*54.2221/B$137 -> 53.178419 | M128: =C128*100/C$137 -> 99.293728 | N128: =L128/M128 -> 0.53556675 | O128: 2257.0031 | P128: 657.125 | Q128: 1469.1035 | R128: 768.28175 | S128: =SUM(O204:O206) -> 0 | T128: =SUM(P204:P206) -> 0 | U128: =SUM(Q204:Q206) -> 0 | V128: =SUM(R204:R206) -> 0
A129: 40269 | B129: 84.874474 | C129: 218.009 | D129: 2113.22 | E129: 2200.74 | F129: 87.52 | G129: 1576.83 | H129: 1677.2 | I129: =G129-H129 -> -100.36999 | J129: 84.477619 | K129: 73.616851 | L129: =B129*54.2221/B$137 -> 53.453521 | M129: =C129*100/C$137 -> 99.46619 | N129: =L129/M129 -> 0.53740393 | O129: 2200.742 | P129: 732.33735 | Q129: 1385.0679 | R129: 1024.3518
A130: 40299 | B130: 84.888697 | C130: 218.178 | D130: 1900.39 | E130: 1991.41 | F130: 91.02 | G130: 1360.0625 | H130: 1531.5 | I130: =G130-H130 -> -171.43751 | J130: 73.73 | K130: 73.629187 | L130: =B130*54.2221/B$137 -> 53.462479 | M130: =C130*100/C$137 -> 99.543296 | N130: =L130/M130 -> 0.53707764 | O130: 1991.4034 | P130: 730.31073 | Q130: 1147.0038 | R130: 670.08838
A131: 40330 | B131: 84.880883 | C131: 217.965 | D131: 1883.58 | E131: 1682.51 | F131: -201.07 | G131: 1469.9697 | H131: 1556.6 | I131: =G131-H131 -> -86.63032 | J131: 75.353636 | K131: 73.62241 | L131: =B131*54.2221/B$137 -> 53.457557 | M131: =C131*100/C$137 -> 99.446115 | N131: =L131/M131 -> 0.537553 | O131: 1682.5124 | P131: 549.31657 | Q131: 1077.8721 | R131: 659.92565 | S131: =SUM(O207:O209) -> 0 | T131: =SUM(P207:P209) -> 0 | U131: =SUM(Q207:Q209) -> 0 | V131: =SUM(R207:R209) -> 0
A132: 40360 | B132: 84.897489 | C132: 218.011 | D132: 1944.64 | E132: 1953.34 | F132: 8.7 | G132: 1397.9194 | H132: 1710.3 | I132: =G132-H132 -> -312.38059 | J132: 76.350476 | K132: 73.636813 | L132: =B132*54.2221/B$137 -> 53.468015 | M132: =C132*100/C$137 -> 99.467102 | N132: =L132/M132 -> 0.53754472 | O132: 1953.3373 | P132: 730.48507 | Q132: 1143.7745 | R132: 749.08191
A133: 40391 | B133: 84.987929 | C133: 218.312 | D133: 1974.62 | E133: 1754.75 | F133: -219.87 | G133: 1328.4313 | H133: 1916.4 | I133: =G133-H133 -> -587.96869 | J133: 76.601818 | K133: 73.715257 | L133: =B133*54.2221/B$137 -> 53.524974 | M133: =C133*100/C$137 -> 99.604433 | N133: =L133/M133 -> 0.53737542 | O133: 1754.7547 | P133: 519.86296 | Q133: 1018.9334 | R133: 633.08187
A134: 40422 | B134: 85.206307 | C134: 218.439 | D134: 1915.5 | E134: 1772.56 | F134: -142.94 | G134: 1392.2585 | H134: 1568.3 | I134: =G134-H134 -> -176.04153 | J134: 75.291429 | K134: 73.904669 | L134: =B134*54.2221/B$137 -> 53.662507 | M134: =C134*100/C$137 -> 99.662376 | N134: =L134/M134 -> 0.53844298 | O134: 1772.5639 | P134: 633.87623 | Q134: 1158.2801 | R134: 758.36667 | S134: =SUM(O210:O212) -> 0 | T134: =SUM(P210:P212) -> 0 | U134: =SUM(Q210:Q212) -> 0 | V134: =SUM(R210:R212) -> 0
A135: 40452 | B135: 85.423004 | C135: 218.711 | D135: 2080.77 | E135: 1981.4 | F135: -99.37 | G135: 1613.4366 | H135: 1752 | I135: =G135-H135 -> -138.5634 | J135: 81.899524 | K135: 74.092625 | L135: =B135*54.2221/B$137 -> 53.798982 | M135: =C135*100/C$137 -> 99.786476 | N135: =L135/M135 -> 0.53914102 | O135: 1981.4012 | P135: 703.06009 | Q135: 1127.1628 | R135: 652.69597
A136: 40483 | B136: 85.65426 | C136: 218.803 | D136: 2159.58 | E136: 1909.52 | F136: -250.06 | G136: 1489.3818 | H136: 1903.7 | I136: =G136-H136 -> -414.31819 | J136: 84.23619 | K136: 74.293207 | L136: =B136*54.2221/B$137 -> 53.944626 | M136: =C136*100/C$137 -> 99.828451 | N136: =L136/M136 -> 0.54037327 | O136: 1909.5161 | P136: 585.18833 | Q136: 1086.7801 | R136: 687.04775
A137: 40513 | B137: 86.094838 | C137: 219.179 | D137: 3252.75 | E137: 2123.51 | F137: -1129.24 | G137: 1726.2828 | H137: 1849.8 | I137: =G137-H137 -> -123.5172 | J137: 89.146818 | K137: 74.675347 | L137: =B137*54.2221/B$137 -> 54.2221 | M137: =C137*100/C$137 -> 100 | N137: =L137/M137 -> 0.542221 | O137: 2123.5082 | P137: 736.47075 | Q137: 1298.8805 | R137: 724.71225 | S137: =SUM(O213:O215) -> 0 | T137: =SUM(P213:P215) -> 0 | U137: =SUM(Q213:Q215) -> 0 | V137: =SUM(R213:R215) -> 0
A138: 40544 | B138: 86.679584 | C138: 220.223 | D138: 1862.16 | E138: 2353.23 | F138: 491.07 | G138: 1621.544 | H138: 1575.8 | I138: =G138-H138 -> 45.744 | J138: 89.4085 | K138: 75.182533 | L138: =B138*54.2221/B$137 -> 54.59037 | M138: =C138*100/C$137 -> 100.47632 | N138: =L138/M138 -> 0.54331576 | O138: 2353.2268 | P138: 937.06377 | Q138: 1202.6397 | R138: 827.24573
A139: 40575 | B139: 87.160621 | C139: 221.309 | D139: 2012.2 | E139: 2139.86 | F139: 127.66 | G139: 1690.4771 | H139: 1525.5 | I139: =G139-H139 -> 164.97711 | J139: 89.532632 | K139: 75.599767 | L139: =B139*54.2221/B$137 -> 54.893325 | M139: =C139*100/C$137 -> 100.97181 | N139: =L139/M139 -> 0.54365001 | O139: 2139.8585 | P139: 899.20782 | Q139: 1107.4301 | R139: 594.43597
A140: 40603 | B140: 87.454201 | C140: 223.467 | D140: 2664.92 | E140: 2497.65 | F140: -167.27 | G140: 2032.0055 | H140: 1899.9 | I140: =G140-H140 -> 132.10552 | J140: 102.91609 | K140: 75.854407 | L140: =B140*54.2221/B$137 -> 55.07822 | M140: =C140*100/C$137 -> 101.95639 | N140: =L140/M140 -> 0.54021351 | O140: 2497.6567 | P140: 1080.9271 | Q140: 1318.2572 | R140: 791.86486 | S140: =SUM(O216:O218) -> 0 | T140: =SUM(P216:P218) -> 0 | U140: =SUM(Q216:Q218) -> 0 | V140: =SUM(R216:R218) -> 0
A141: 40634 | B141: 88.171396 | C141: 224.906 | D141: 2413.15 | E141: 2906.63 | F141: 493.48 | G141: 1831.3041 | H141: 1869.6 | I141: =G141-H141 -> -38.29592 | J141: 109.9595 | K141: 76.476474 | L141: =B141*54.2221/B$137 -> 55.529906 | M141: =C141*100/C$137 -> 102.61293 | N141: =L141/M141 -> 0.54115894 | O141: 2906.6329 | P141: 1099.1979 | Q141: 1689.8113 | R141: 1147.916
A142: 40664 | B142: 88.476337 | C142: 225.964 | D142: 2571 | E142: 2370.78 | F142: -200.22 | G142: 2009.4841 | H142: 1950.2 | I142: =G142-H142 -> 59.28405 | J142: 101.28286 | K142: 76.740968 | L142: =B142*54.2221/B$137 -> 55.721956 | M142: =C142*100/C$137 -> 103.09564 | N142: =L142/M142 -> 0.54048798 | O142: 2370.7732 | P142: 875.52452 | Q142: 1342.4557 | R142: 781.60364
A143: 40695 | B143: 88.511526 | C143: 225.722 | D143: 2448.76 | E143: 2933.59 | F143: 484.83 | G143: 1863.1895 | H143: 1993 | I143: =G143-H143 -> -129.81052 | J143: 96.254091 | K143: 76.771489 | L143: =B143*54.2221/B$137 -> 55.744118 | M143: =C143*100/C$137 -> 102.98523 | N143: =L143/M143 -> 0.54128264 | O143: 2933.5933 | P143: 1518.0536 | Q143: 1302.7305 | R143: 747.85953 | S143: =SUM(O219:O221) -> 0 | T143: =SUM(P219:P221) -> 0 | U143: =SUM(Q219:Q221) -> 0 | V143: =SUM(R219:R221) -> 0
A144: 40725 | B144: 88.667149 | C144: 225.922 | D144: 2456.96 | E144: 2528.68 | F144: 71.72 | G144: 1974.0108 | H144: 1822.6 | I144: =G144-H144 -> 151.4108 | J144: 97.3065 | K144: 76.90647 | L144: =B144*54.2221/B$137 -> 55.842128 | M144: =C144*100/C$137 -> 103.07648 | N144: =L144/M144 -> 0.54175432 | O144: 2528.679 | P144: 1045.9545 | Q144: 1330.1016 | R144: 779.11546
A145: 40756 | B145: 89.098049 | C145: 226.545 | D145: 2601.36 | E145: 2578.94 | F145: -22.42 | G145: 1772.2588 | H145: 2025.3 | I145: =G145-H145 -> -253.04121 | J145: 86.321304 | K145: 77.280217 | L145: =B145*54.2221/B$137 -> 56.113507 | M145: =C145*100/C$137 -> 103.36072 | N145: =L145/M145 -> 0.54289004 | O145: 2578.9366 | P145: 1138.3581 | Q145: 1242.0099 | R145: 715.61217
A146: 40787 | B146: 89.802691 | C146: 226.889 | D146: 2539.17 | E146: 2784.12 | F146: 244.95 | G146: 1856.0822 | H146: 2091.4 | I146: =G146-H146 -> -235.3178 | J146: 85.577143 | K146: 77.891396 | L146: =B146*54.2221/B$137 -> 56.557287 | M146: =C146*100/C$137 -> 103.51767 | N146: =L146/M146 -> 0.54635393 | O146: 2784.1152 | P146: 1117.1748 | Q146: 1556.0551 | R146: 880.43734 | S146: =SUM(O222:O224) -> 0 | T146: =SUM(P222:P224) -> 0 | U146: =SUM(Q222:Q224) -> 0 | V146: =SUM(R222:R224) -> 0
A147: 40817 | B147: 90.11894 | C147: 226.421 | D147: 2772.17 | E147: 2505.72 | F147: -266.45 | G147: 1827.8605 | H147: 2054.9 | I147: =G147-H147 -> -227.03951 | J147: 86.40619 | K147: 78.165698 | L147: =B147*54.2221/B$137 -> 56.756459 | M147: =C147*100/C$137 -> 103.30415 | N147: =L147/M147 -> 0.54941123 | O147: 2505.7208 | P147: 1042.3752 | Q147: 1323.1451 | R147: 788.87731
A148: 40848 | B148: 90.392332 | C148: 226.23 | D148: 2917.38 | E148: 2346.17 | F148: -571.21 | G148: 1868.9732 | H148: 2166.1 | I148: =G148-H148 -> -297.12678 | J148: 97.123333 | K148: 78.402828 | L148: =B148*54.2221/B$137 -> 56.92864 | M148: =C148*100/C$137 -> 103.21701 | N148: =L148/M148 -> 0.55154323 | O148: 2346.1658 | P148: 722.48646 | Q148: 1409.4847 | R148: 808.22841
...

Sheet Data sa
A1: date | B1: año | C1: mes | D1: v_1 | E1: v_2 | F1: v_3 | G1: v_4 | H1: v_5 | I1: v_6 | J1: v_7 | K1: v_8 | L1: v_9 | M1: v_11
A2: 37257 | B2: =YEAR(A2) -> 2002 | C2: =MONTH(A2) -> 1 | D2: 57.756016 | E2: 177.99343 | F2: 502.7649 | G2: 500.00698 | H2: -34.234354 | I2: 356.96195 | J2: 467.56369 | K2: -59.432794 | L2: 19.54338 | M2: 50.095344 | O2: 37257
A3: 37288 | B3: =YEAR(A3) -> 2002 | C3: =MONTH(A3) -> 2 | D3: 58.174537 | E3: 178.06952 | F3: 463.28569 | G3: 563.74048 | H3: 97.56345 | I3: 372.88136 | J3: 468.72476 | K3: -102.09906 | L3: 22.03949 | M3: 50.458353 | O3: 37288
A4: 37316 | B4: =YEAR(A4) -> 2002 | C4: =MONTH(A4) -> 3 | D4: 58.676633 | E4: 178.4295 | F4: 448.1338 | G4: 484.8317 | H4: -13.871439 | I4: 399.93916 | J4: 472.38134 | K4: -87.420008 | L4: 22.923641 | M4: 50.893852 | O4: 37316
A5: 37347 | B5: =YEAR(A5) -> 2002 | C5: =MONTH(A5) -> 4 | D5: 59.250983 | E5: 179.15807 | F5: 536.63638 | G5: 521.50959 | H5: -53.616519 | I5: 418.38742 | J5: 614.98407 | K5: -139.74049 | L5: 26.702077 | M5: 51.392021 | O5: 37347
A6: 37377 | B6: =YEAR(A6) -> 2002 | C6: =MONTH(A6) -> 5 | D6: 59.716022 | E6: 179.31168 | F6: 541.13084 | G6: 513.69375 | H6: 2.3176279 | I6: 441.92805 | J6: 489.69887 | K6: -30.24629 | L6: 26.786171 | M6: 51.795378 | O6: 37377
A7: 37408 | B7: =YEAR(A7) -> 2002 | C7: =MONTH(A7) -> 6 | D7: 60.205417 | E7: 179.51769 | F7: 487.64222 | G7: 565.86846 | H7: 32.125814 | I7: 407.5848 | J7: 548.33678 | K7: -200.9749 | L7: 26.005562 | M7: 52.219861 | O7: 37408
A8: 37438 | B8: =YEAR(A8) -> 2002 | C8: =MONTH(A8) -> 7 | D8: 60.501357 | E8: 179.95772 | F8: 499.63712 | G8: 497.00187 | H8: 4.900056 | I8: 427.8449 | J8: 500.99663 | K8: -60.527602 | L8: 26.560429 | M8: 52.476547 | O8: 37438
A9: 37469 | B9: =YEAR(A9) -> 2002 | C9: =MONTH(A9) -> 8 | D9: 60.875758 | E9: 180.45407 | F9: 509.08438 | G9: 508.96355 | H9: -6.8369928 | I9: 429.14876 | J9: 557.9492 | K9: -142.64449 | L9: 25.983801 | M9: 52.801288 | O9: 37469
A10: 37500 | B10: =YEAR(A10) -> 2002 | C10: =MONTH(A10) -> 9 | D10: 61.079506 | E10: 180.58474 | F10: 504.31117 | G10: 579.736 | H10: 80.841258 | I10: 438.01722 | J10: 546.70736 | K10: -144.87208 | L10: 28.316634 | M10: 52.978011 | O10: 37500
A11: 37530 | B11: =YEAR(A11) -> 2002 | C11: =MONTH(A11) -> 10 | D11: 61.463923 | E11: 180.99426 | F11: 532.05552 | G11: 593.22535 | H11: 38.905535 | I11: 424.70509 | J11: 515.40079 | K11: -83.360329 | L11: 28.654307 | M11: 53.31144 | O11: 37530
A12: 37561 | B12: =YEAR(A12) -> 2002 | C12: =MONTH(A12) -> 11 | D12: 61.808325 | E12: 181.73576 | F12: 617.08961 | G12: 531.14899 | H12: -46.484336 | I12: 459.71339 | J12: 483.43281 | K12: -9.6782097 | L12: 27.518206 | M12: 53.610161 | O12: 37561
A13: 37591 | B13: =YEAR(A13) -> 2002 | C13: =MONTH(A13) -> 12 | D13: 62.141134 | E13: 182.23688 | F13: 507.98642 | G13: 532.27912 | H13: 102.00672 | I13: 456.39376 | J13: 505.87798 | K13: -57.323054 | L13: 31.85431 | M13: 53.898827 | O13: 37591
... A231: 44228 | B231: =YEAR(A231) -> 2021 | C231: =MONTH(A231) -> 2 | D231: 104.49261 | E231: 263.66785 | F231: 2925.8166 | G231: 2979.5982 | H231: -190.59036 | I231: 2022.5131 | J231: 1719.4039 | K231: 293.75954 | L231: 57.866584 | M231: 90.632865 | O231: 44228
A232: 44256 | B232: =YEAR(A232) -> 2021 | C232: =MONTH(A232) -> 3 | D232: 104.70458 | E232: 264.8226 | F232: 3612.2328 | I232: 2016.4714 | J232: 1951.3071 | K232: 161.84995 | L232: 62.848589 | M232: 90.816719 | O232: 44256
A233: 44287 | B233: =YEAR(A233) -> 2021 | C233: =MONTH(A233) -> 4 | D233: 104.85604 | E233: 266.77606 | F233: 3215.4568 | I233: 2181.7315 | J233: 1776.6011 | K233: 401.49525 | L233: 60.55542 | M233: 90.948091 | O233: 44287
A234: 44317 | B234: =YEAR(A234) -> 2021 | C234: =MONTH(A234) -> 5 | D234: 104.91954 | E234: 268.41067 | F234: 3566.8181 | I234: 2128.4977 | J234: 1845.5121 | K234: 315.81859 | L234: 64.236454 | M234: 91.003172 | O234: 44317
A235: 44348 | B235: =YEAR(A235) -> 2021 | C235: =MONTH(A235) -> 6 | D235: 104.88605 | E235: 270.62988 | F235: 3409.4438 | I235: 2228.2992 | J235: 1934.2751 | K235: 285.81637 | L235: 68.705994 | M235: 90.974121 | O235: 44348
A236: 44378 | B236: =YEAR(A236) -> 2021 | C236: =MONTH(A236) -> 7 | D236: 105.32015 | E236: 272.05819 | F236: 3429.8384 | I236: 2264.1238 | J236: 2125.0654 | K236: 115.89963 | L236: 69.944723 | M236: 91.350639 | O236: 44378
A237: 44409 | B237: =YEAR(A237) -> 2021 | C237: =MONTH(A237) -> 8 | D237: 105.5211 | E237: 272.98778 | F237: 3424.5052 | I237: 2247.8702 | J237: 2150.1698 | K237: 85.512184 | L237: 67.642343 | M237: 91.524942 | O237: 44409
A238: 44440 | B238: =YEAR(A238) -> 2021 | C238: =MONTH(A238) -> 9 | D238: 105.49511 | E238: 273.99862 | F238: 3205.2138 | I238: 2364.164 | J238: 2022.8764 | K238: 292.87733 | L238: 73.106886 | M238: 91.502394 | O238: 44440
A239: 44470 | B239: =YEAR(A239) -> 2021 | C239: =MONTH(A239) -> 10 | D239: 105.80317 | E239: 276.45088 | F239: 3241.2414 | I239: 2562.7463 | J239: 2093.3298 | K239: 497.03555 | L239: 80.572058 | M239: 91.769592 | O239: 44470
A240: 44501 | B240: =YEAR(A240) -> 2021 | C240: =MONTH(A240) -> 11 | D240: 106.30996 | E240: 278.75689 | F240: 3330.7261 | I240: 2617.4277 | J240: 2194.9542 | K240: 398.12326 | L240: 80.531835 | M240: 92.209163 | O240: 44501
A241: 44531 | B241: =YEAR(A241) -> 2021 | C241: =MONTH(A241) -> 12 | D241: 106.4348 | E241: 280.46875 | F241: 3572.6048 | I241: 2132.5733 | J241: 2285.5038 | K241: -170.85872 | L241: 75.987808 | M241: 92.317444 | O241: 44531
A242: 44562 | B242: =YEAR(A242) -> 2022 | C242: =MONTH(A242) -> 1 | D242: 107.06388 | E242: 282.37778 | F242: 3456.5112 | I242: 2625.2576 | J242: 2469.3634 | K242: 104.61216 | L242: 85.232867 | M242: 92.863085 | O242: 44562
A243: 44593 | B243: =YEAR(A243) -> 2022 | C243: =MONTH(A243) -> 2 | D243: 107.38148 | E243: 284.39898 | F243: 3661.655 | I243: 2738.577 | J243: 2457.7017 | K243: 347.59582 | L243: 90.978022 | M243: 93.138559 | O243: 44593
... A263: 45200 | B263: =YEAR(A263) -> 2023 | C263: =MONTH(A263) -> 10 | D263: 112.08635 | E263: 307.60709 | F263: 4147.435 | I263: 2609.7386 | J263: 2496.9978 | K263: 65.104756 | L263: 83.612444 | M263: 97.219385 | O263: 45200
A264: 45231 | B264: =YEAR(A264) -> 2023 | C264: =MONTH(A264) -> 11 | D264: 111.85196 | E264: 308.05403 | F264: 4302.7387 | J264: 2425.5391 | K264: -2423.8203 | L264: 78.719847 | M264: 97.016083 | O264: 45231
A265: 45261 | B265: =YEAR(A265) -> 2023 | C265: =MONTH(A265) -> 12 | D265: 111.91455 | E265: 308.67235 | F265: 3568.481 | J265: 2355.4135 | K265: -2306.205 | L265: 77.242455 | M265: 97.070371 | O265: 45261
A266: 45292 | B266: =YEAR(A266) -> 2024 | C266: =MONTH(A266) -> 1 | D266: 111.95551 | E266: 309.82308 | F266: 4108.0622 | J266: 2195.4605 | K266: -2080.0784 | L266: 76.860814 | M266: 97.105896 | O266: 45292
A267: 45323 | B267: =YEAR(A267) -> 2024 | C267: =MONTH(A267) -> 2 | D267: 112.13649 | E267: 310.97504 | J267: 2173.0038 | K267: -2153.8055 | L267: 77.497739 | M267: 97.262873 | O267: 45323

Sheet Data trim
A1: fecha | B1: v_1 | C1: v_2 | D1: v_3 | E1: V_3 (P) | F1: V_4(P) | G1: V_3/V_4 | H1: V_3/V_10 | I1: v_4 | J1: v_5 | K1: v_6 | L1: v_7 | M1: v_8 | N1: v_9 | O1: v_10 | P1: v_11 | Q1: V_38 | R1: V_39 | T1: V_40 | U1: V_41 | V1: V_42 | W1: Cuenta Corriente | X1: Exportaciones (bienes) | Y1: Importaciones (bienes) | Z1: Exportaciones (servicios) | AA1: Importaciones (servicios) | AB1: Exportaciones (bienes + servicios) | AC1: Importaciones (bienes + servicios) | AD1: Balanza Comercial | AE1: Crédito (Renta recibida) | AF1: Débito (Renta pagada) | AG1: Crédito (transf. recibida) | AH1: Débito (transf. pagada) | AI1: Crédito (Transferencias de capital recibidas) | AJ1: Debito (Transferencias de capital enviadas) | AK1: Total ingresos | AL1: Ingresos Petroleros | AM1: Ingresos no petroleros | AN1: Ingresos tributarios | AQ1: ingres sec
A2: 36495 | Q2: =AVERAGE(Data!L3:L5) -> 14.423665 | R2: =AVERAGE(Data!M3:M5) -> 76.771345
A3: 36586 | Q3: =AVERAGE(Data!L6:L8) -> 19.08564 | R3: =AVERAGE(Data!M6:M8) -> 77.531759 | T3: 11973785
A4: 36678 | Q4: =AVERAGE(Data!L9:L11) -> 23.946546 | R4: =AVERAGE(Data!M9:M11) -> 78.353005 | T4: 12435932
A5: 36770 | Q5: =AVERAGE(Data!L12:L14) -> 26.335537 | R5: =AVERAGE(Data!M12:M14) -> 78.976544 | T5: 13192816
A6: 36861 | Q6: =AVERAGE(Data!L15:L17) -> 28.458756 | R6: =AVERAGE(Data!M15:M17) -> 79.402376 | T6: 14555506
A7: 36951 | Q7: =AVERAGE(Data!L18:L20) -> 31.994435 | R7: =AVERAGE(Data!M18:M20) -> 80.162789 | T7: 12757885
A8: 37043 | Q8: =AVERAGE(Data!L21:L23) -> 33.419582 | R8: =AVERAGE(Data!M21:M23) -> 80.999244 | T8: 13167471
A9: 37135 | Q9: =AVERAGE(Data!L24:L26) -> 33.953162 | R9: =AVERAGE(Data!M24:M26) -> 81.105702 | T9: 13455244
A10: 37226 | Q10: =AVERAGE(Data!L27:L29) -> 35.317134 | R10: =AVERAGE(Data!M27:M29) -> 80.877578 | T10: 14971349
A11: 37316 | B11: 58.202395 | C11: 178.16415 | D11: =SUM(Data!C30:C32) -> 533.7 | E11: =SUM(Data!D30:D32) -> 1265.54 | F11: =SUM(Data!E30:E32) -> 1436.29 | G11: =E11/F11 -> 0.88111732 | H11: =E11/O11 -> 0.20897244 | I11: 1548.5792 | J11: 49.457657 | K11: 1129.7825 | L11: 1408.6698 | M11: -248.95186 | N11: 21.502171 | O11: 6056.014 | P11: 50.482517 | Q11: =AVERAGE(Data!L30:L32) -> 36.700818 | R11: =AVERAGE(Data!M30:M32) -> 81.166535 | T11: 13314495 | U11: =AB11+AE11+AG11 -> 1774.3934 | V11: =AC11+AF11+AH11 -> 2065.3866 | W11: =U11/V11 -> 0.85910958 | X11: 1151.5991 | Y11: 1370.6946 | Z11: 211.39039 | AA11: 380.463 | AB11: =X11+Z11 -> 1362.9895 | AC11: =Y11+AA11 -> 1751.1576 | AD11: =AB11/AC11 -> 0.77833632 | AE11: 23.482903 | AF11: 300.206 | AG11: 387.92101 | AH11: 14.023082 | AI11: 7.023 | AJ11: 2 | AK11: 1436.2838 | AL11: 288.391 | AM11: 1094.1135 | AN11: 675.65792 | AQ11: =AG11-AH11 -> 373.89793
A12: 37408 | B12: 59.724141 | C12: 179.32914 | D12: =SUM(Data!C33:C35) -> 539.5 | E12: =SUM(Data!D33:D35) -> 1539.71 | F12: =SUM(Data!E33:E35) -> 1695.06 | G12: =E12/F12 -> 0.90835133 | H12: =E12/O12 -> 0.23939528 | I12: 1601.0718 | J12: -19.173077 | K12: 1267.9003 | L12: 1653.0197 | M12: -370.96169 | N12: 26.497936 | O12: 6431.664 | P12: 51.80242 | Q12: =AVERAGE(Data!L33:L35) -> 37.830514 | R12: =AVERAGE(Data!M33:M35) -> 82.048615 | T12: 13815664 | U12: =AB12+AE12+AG12 -> 2009.0829 | V12: =AC12+AF12+AH12 -> 2417.206 | W12: =U12/V12 -> 0.83115912 | X12: 1355.4692 | Y12: 1670.2517 | Z12: 222.88434 | AA12: 406.129 | AB12: =X12+Z12 -> 1578.3535 | AC12: =Y12+AA12 -> 2076.3807 | AD12: =AB12/AC12 -> 0.76014651 | AE12: 23.08355 | AF12: 326.39902 | AG12: 407.6458 | AH12: 14.426365 | AI12: 11.68 | AJ12: 2 | AK12: 1695.0581 | AL12: 322.31092 | AM12: 1317.5322 | AN12: 798.22471 | AQ12: =AG12-AH12 -> 393.21943
A13: 37500 | B13: 60.818873 | C13: 180.33218 | D13: =SUM(Data!C36:C38) -> 541.8 | E13: =SUM(Data!D36:D38) -> 1485.6 | F13: =SUM(Data!E36:E38) -> 1647.77 | G13: =E13/F13 -> 0.90158214 | H13: =E13/O13 -> 0.21710646 | I13: 1585.7014 | J13: 78.904321 | K13: 1295.0109 | L13: 1605.6532 | M13: -348.04417 | N13: 26.953621 | O13: 6842.726 | P13: 52.751949 | Q13: =AVERAGE(Data!L36:L38) -> 38.146923 | R13: =AVERAGE(Data!M36:M38) -> 82.398405 | T13: 14177884 | U13: =AB13+AE13+AG13 -> 2050.245 | V13: =AC13+AF13+AH13 -> 2380.413 | W13: =U13/V13 -> 0.86129801 | X13: 1370.7106 | Y13: 1605.0032 | Z13: 228.02734 | AA13: 409.50801 | AB13: =X13+Z13 -> 1598.7379 | AC13: =Y13+AA13 -> 2014.5112 | AD13: =AB13/AC13 -> 0.79361085 | AE13: 18.803823 | AF13: 351.17758 | AG13: 432.7032 | AH13: 14.72421 | AI13: 7.9061 | AJ13: 2 | AK13: 1647.7635 | AL13: 381.41268 | AM13: 1205.209 | AN13: 724.62439 | AQ13: =AG13-AH13 -> 417.97899
A14: 37591 | B14: 61.804461 | C14: 181.65563 | D14: =SUM(Data!C39:C41) -> 543.5 | E14: =SUM(Data!D39:D41) -> 1870.33 | F14: =SUM(Data!E39:E41) -> 1581.77 | G14: =E14/F14 -> 1.1824285 | H14: =E14/O14 -> 0.24215172 | I14: 1656.6535 | J14: 94.427915 | K14: 1340.8122 | L14: 1504.7116 | M14: -150.36159 | N14: 29.342274 | O14: 7723.794 | P14: 53.606809 | Q14: =AVERAGE(Data!L39:L41) -> 38.819507 | R14: =AVERAGE(Data!M39:M41) -> 82.656946 | T14: 15722423 | U14: =AB14+AE14+AG14 -> 2100.0964 | V14: =AC14+AF14+AH14 -> 2289.8368 | W14: =U14/V14 -> 0.91713799 | X14: 1379.9038 | Y14: 1513.7339 | Z14: 221.62015 | AA14: 403.75953 | AB14: =X14+Z14 -> 1601.5239 | AC14: =Y14+AA14 -> 1917.4934 | AD14: =AB14/AC14 -> 0.83521743 | AE14: 17.345296 | AF14: 357.69517 | AG14: 481.22717 | AH14: 14.648272 | AI14: 8.0124 | AJ14: 2 | AK14: 1581.771 | AL14: 400.64668 | AM14: 1164.0577 | AN14: 707.79551 | AQ14: =AG14-AH14 -> 466.57889
A15: 37681 | B15: 63.828736 | C15: 183.32684 | D15: =SUM(Data!C42:C44) -> 549 | E15: =SUM(Data!D42:D44) -> 1371.55 | F15: =SUM(Data!E42:E44) -> 1605.61 | G15: =E15/F15 -> 0.85422363 | H15: =E15/O15 -> 0.18876884 | I15: 1660.0542 | J15: 129.03939 | K15: 1578.2739 | L15: 1558.141 | M15: 23.470858 | N15: 34.220287 | O15: 7265.765 | P15: 55.362587 | Q15: =AVERAGE(Data!L42:L44) -> 40.246919 | R15: =AVERAGE(Data!M42:M44) -> 83.4934 | S15: =Q15/R15 -> 0.48203713 | T15: 13903569 | U15: =AB15+AE15+AG15 -> 2245.7663 | V15: =AC15+AF15+AH15 -> 2311.1223 | W15: =U15/V15 -> 0.9717211 | X15: 1595.3812 | Y15: 1522.2151 | Z15: 214.01448 | AA15: 414.20099 | AB15: =X15+Z15 -> 1809.3957 | AC15: =Y15+AA15 -> 1936.4161 | AD15: =AB15/AC15 -> 0.93440435 | AE15: 14.834026 | AF15: 373.97457 | AG15: 421.53665 | AH15: 0.73162719 | AI15: 38.481306 | AJ15: 2.25 | AK15: 1605.601 | AL15: 433.8 | AM15: 1170.6882 | AN15: 742.47423 | AQ15: =AG15-AH15 -> 420.80502
A16: 37773 | B16: 64.633307 | C16: 183.12823 | D16: =SUM(Data!C45:C47) -> 551 | E16: =SUM(Data!D45:D47) -> 1543.38 | F16: =SUM(Data!E45:E47) -> 1729.48 | G16: =E16/F16 -> 0.8923954 | H16: =E16/O16 -> 0.2130273 | I16: 1629.4442 | J16: -22.178987 | K16: 1398.0534 | L16: 1518.0399 | M16: -124.02211 | N16: 29.11772 | O16: 7244.987 | P16: 56.060442 | Q16: =AVERAGE(Data!L45:L47) -> 40.913838 | R16: =AVERAGE(Data!M45:M47) -> 83.797566 | S16: =Q16/R16 -> 0.48824614 | T16: 13983215 | U16: =AB16+AE16+AG16 -> 2153.8545 | V16: =AC16+AF16+AH16 -> 2388.6216 | W16: =U16/V16 -> 0.9017144 | X16: 1491.9231 | Y16: 1549.9584 | Z16: 222.951 | AA16: 408.24909 | AB16: =X16+Z16 -> 1714.8741 | AC16: =Y16+AA16 -> 1958.2075 | AD16: =AB16/AC16 -> 0.87573668 | AE16: 14.806015 | AF16: 429.18659 | AG16: 424.17435 | AH16: 1.227534 | AI16: 17.331481 | AJ16: 2.25 | AK16: 1729.4724 | AL16: 313.17 | AM16: 1345.1343 | AN16: 857.61781 | AQ16: =AG16-AH16 -> 422.94682
A17: 37865 | B17: 65.371558 | C17: 184.23369 | D17: =SUM(Data!C48:C50) -> 553.7 | E17: =SUM(Data!D48:D50) -> 1769.94 | F17: =SUM(Data!E48:E50) -> 1821.85 | G17: =E17/F17 -> 0.97150698 | H17: =E17/O17 -> 0.23022529 | I17: 1823.3319 | J17: -15.561742 | K17: 1518.8011 | L17: 1563.724 | M17: -69.908429 | N17: 28.445305 | O17: 7687.861 | P17: 56.700773 | Q17: =AVERAGE(Data!L48:L50) -> 41.019308 | R17: =AVERAGE(Data!M48:M50) -> 84.208189 | S17: =Q17/R17 -> 0.4871178 | T17: 14456706 | U17: =AB17+AE17+AG17 -> 2278.91 | V17: =AC17+AF17+AH17 -> 2404.3784 | W17: =U17/V17 -> 0.94781669 | X17: 1592.6364 | Y17: 1615.864 | Z17: 224.56463 | AA17: 401.94556 | AB17: =X17+Z17 -> 1817.201 | AC17: =Y17+AA17 -> 2017.8095 | AD17: =AB17/AC17 -> 0.90058106 | AE17: 15.090307 | AF17: 367.70298 | AG17: 446.61867 | AH17: 18.865925 | AI17: 6.0976031 | AJ17: 2.25 | AK17: 1821.8473 | AL17: 460.2 | AM17: 1315.3455 | AN17: 793.84303 | AQ17: =AG17-AH17 -> 427.75274
A18: 37956 | B18: 65.786431 | C18: 185.11683 | D18: =SUM(Data!C51:C53) -> 553.8 | E18: =SUM(Data!D51:D53) -> 1901.69 | F18: =SUM(Data!E51:E53) -> 1753.32 | G18: =E18/F18 -> 1.0846223 | H18: =E18/O18 -> 0.21692456 | I18: 1772.9298 | J18: 250.49875 | K18: 1741.3533 | L18: 1603.9148 | M18: 180.88873 | N18: 32.500919 | O18: 8766.596 | P18: 57.060617 | Q18: =AVERAGE(Data!L51:L53) -> 41.330507 | R18: =AVERAGE(Data!M51:M53) -> 84.223397 | S18: =Q18/R18 -> 0.49072476 | T18: 16332020 | U18: =AB18+AE18+AG18 -> 2502.2959 | V18: =AC18+AF18+AH18 -> 2463.5228 | W18: =U18/V18 -> 1.0157389 | X18: 1765.8862 | Y18: 1678.2892 | Z18: 219.62189 | AA18: 400.08281 | AB18: =X18+Z18 -> 1985.5081 | AC18: =Y18+AA18 -> 2078.372 | AD18: =AB18/AC18 -> 0.95531892 | AE18: 17.840147 | AF18: 384.12446 | AG18: 498.94762 | AH18: 1.0263901 | AI18: 7.6914874 | AJ18: 2.25 | AK18: 1753.3222 | AL18: 456.48274 | AM18: 1324.7047 | AN18: 769.58142 | AQ18: =AG18-AH18 -> 497.92123
A19: 38047 | B19: 66.326534 | C19: 186.71285 | D19: =SUM(Data!C54:C56) -> 558.8 | E19: =SUM(Data!D54:D56) -> 1632.95 | F19: =SUM(Data!E54:E56) -> 1842.54 | G19: =E19/F19 -> 0.88624942 | H19: =E19/O19 -> 0.20202629 | I19: 1918.7608 | J19: 118.21221 | K19: 1739.4882 | L19: 1660.7248 | M19: 67.673952 | N19: 36.038825 | O19: 8082.859 | P19: 57.529081 | Q19: =AVERAGE(Data!L54:L56) -> 41.821944 | R19: =AVERAGE(Data!M54:M56) -> 84.983811 | S19: =Q19/R19 -> 0.49211661 | T19: 14557303 | U19: =AB19+AE19+AG19 -> 2467.8755 | V19: =AC19+AF19+AH19 -> 2495.7873 | W19: =U19/V19 -> 0.98881643 | X19: 1743.6109 | Y19: 1600.8622 | Z19: 238.21343 | AA19: 465.94281 | AB19: =X19+Z19 -> 1981.8244 | AC19: =Y19+AA19 -> 2066.805 | AD19: =AB19/AC19 -> 0.9588831 | AE19: 17.030222 | AF19: 427.86045 | AG19: 469.02095 | AH19: 1.1218982 | AI19: 5.3967888 | AJ19: 2.5 | AK19: 1842.5486 | AL19: 429.85925 | AM19: 1315.7296 | AN19: 806.25362 | AQ19: =AG19-AH19 -> 467.89905
A20: 38139 | B20: 66.716009 | C20: 188.31622 | D20: =SUM(Data!C57:C59) -> 566.8 | E20: =SUM(Data!D57:D59) -> 1861.73 | F20: =SUM(Data!E57:E59) -> 2046.84 | G20: =E20/F20 -> 0.90956303 | H20: =E20/O20 -> 0.22364093 | I20: 1936.3442 | J20: -74.062393 | K20: 1932.1572 | L20: 1832.0244 | M20: 93.511676 | N20: 38.115748 | O20: 8324.639 | P20: 57.866897 | Q20: =AVERAGE(Data!L57:L59) -> 42.209045 | R20: =AVERAGE(Data!M57:M59) -> 86.200472 | S20: =Q20/R20 -> 0.48966141 | T20: 15036628 | U20: =AB20+AE20+AG20 -> 2814.7435 | V20: =AC20+AF20+AH20 -> 2819.2682 | W20: =U20/V20 -> 0.99839508 | X20: 2040.8013 | Y20: 1825.2247 | Z20: 261.15232 | AA20: 482.25715 | AB20: =X20+Z20 -> 2301.9536 | AC20: =Y20+AA20 -> 2307.4818 | AD20: =AB20/AC20 -> 0.99760422 | AE20: 22.132583 | AF20: 509.01548 | AG20: 490.65734 | AH20: 2.7709221 | AI20: 5.6165501 | AJ20: 2.5 | AK20: 2046.8497 | AL20: 500.9802 | AM20: 1486.8394 | AN20: 974.15578 | AQ20: =AG20-AH20 -> 487.88642
A21: 38231 | B21: 66.640867 | C21: 189.16226 | D21: =SUM(Data!C60:C62) -> 568.8 | E21: =SUM(Data!D60:D62) -> 1835.44 | F21: =SUM(Data!E60:E62) -> 2167.83 | G21: =E21/F21 -> 0.84667156 | H21: =E21/O21 -> 0.20818239 | I21: 2135.4849 | J21: 282.15273 | K21: 2002.3963 | L21: 1896.6952 | M21: 92.091342 | N21: 41.482443 | O21: 8816.5 | P21: 57.801722 | Q21: =AVERAGE(Data!L60:L62) -> 41.835765 | R21: =AVERAGE(Data!M60:M62) -> 86.504638 | S21: =Q21/R21 -> 0.48362454 | T21: 15584558 | U21: =AB21+AE21+AG21 -> 2894.67 | V21: =AC21+AF21+AH21 -> 2903.6371 | W21: =U21/V21 -> 0.99691176 | X21: 2092.6662 | Y21: 1963.3582 | Z21: 262.83016 | AA21: 499.05077 | AB21: =X21+Z21 -> 2355.4964 | AC21: =Y21+AA21 -> 2462.409 | AD21: =AB21/AC21 -> 0.9565821 | AE21: 26.454552 | AF21: 427.34881 | AG21: 512.71903 | AH21: 13.879282 | AI21: 6.0145196 | AJ21: 2.5 | AK21: 2167.8269 | AL21: 610.85421 | AM21: 1499.185 | AN21: 911.10149 | AQ21: =AG21-AH21 -> 498.83975
A22: 38322 | B22: 67.057985 | C22: 191.29958 | D22: =SUM(Data!C63:C65) -> 572.2 | E22: =SUM(Data!D63:D65) -> 2163.01 | F22: =SUM(Data!E63:E65) -> 2119.25 | G22: =E22/F22 -> 1.0206488 | H22: =E22/O22 -> 0.21693119 | I22: 2197.4753 | J22: 399.84056 | K22: 2071.6994 | L22: 2113.538 | M22: -14.101187 | N22: 49.827548 | O22: 9970.95 | P22: 58.163514 | Q22: =AVERAGE(Data!L63:L65) -> 42.129291 | R22: =AVERAGE(Data!M63:M65) -> 87.021719 | S22: =Q22/R22 -> 0.48412387 | T22: 17505965 | U22: =AB22+AE22+AG22 -> 2953.236 | V22: =AC22+AF22+AH22 -> 3391.2551 | W22: =U22/V22 -> 0.87083865 | X22: 2090.6752 | Y22: 2294.3024 | Z22: 251.75398 | AA22: 520.31557 | AB22: =X22+Z22 -> 2342.4292 | AC22: =Y22+AA22 -> 2814.618 | AD22: =AB22/AC22 -> 0.83223699 | AE22: 34.506774 | AF22: 575.93199 | AG22: 576.30008 | AH22: 0.70515148 | AI22: 6.8226907 | AJ22: 2.5 | AK22: 2119.2513 | AL22: 573.692 | AM22: 1522.9986 | AN22: 903.35789 | AQ22: =AG22-AH22 -> 575.59493
A23: 38412 | B23: 67.227554 | C23: 192.55143 | D23: =SUM(Data!C66:C68) -> 575.8 | E23: =SUM(Data!D66:D68) -> 1959.28 | F23: =SUM(Data!E66:E68) -> 2012.59 | G23: =E23/F23 -> 0.97351174 | H23: =E23/O23 -> 0.21634557 | I23: 2129.9248 | J23: -53.038595 | K23: 2294.5318 | L23: 2297.2978 | M23: 43.667283 | N23: 51.688897 | O23: 9056.252 | P23: 58.310592 | Q23: =AVERAGE(Data!L66:L68) -> 42.386969 | R23: =AVERAGE(Data!M66:M68) -> 87.569217 | S23: =Q23/R23 -> 0.4840396 | T23: 15482339 | U23: =AB23+AE23+AG23 -> 3275.0175 | V23: =AC23+AF23+AH23 -> 3257.4868 | W23: =U23/V23 -> 1.0053817 | X23: 2305.3176 | Y23: 2218.2729 | Z23: 261.55188 | AA23: 522.82351 | AB23: =X23+Z23 -> 2566.8695 | AC23: =Y23+AA23 -> 2741.0964 | AD23: =AB23/AC23 -> 0.93643897 | AE23: 39.897875 | AF23: 497.16086 | AG23: 668.25012 | AH23: 19.22956 | AI23: 7.029 | AJ23: 2.5 | AK23: 2012.5914 | AL23: 431.945 | AM23: 1494.0055 | AN23: 926.91939 | AQ23: =AG23-AH23 -> 649.02056
A24: 38504 | B24: 67.859768 | C24: 193.77654 | D24: =SUM(Data!C69:C71) -> 583.5 | E24: =SUM(Data!D69:D71) -> 1926.2 | F24: =SUM(Data!E69:E71) -> 2428.08 | G24: =E24/F24 -> 0.7933017 | H24: =E24/O24 -> 0.20206235 | I24: 2259.4192 | J24: 181.54509 | K24: 2394.7355 | L24: 2369.6788 | M24: -0.83945918 | N24: 52.030356 | O24: 9532.701 | P24: 58.85895 | Q24: =AVERAGE(Data!L69:L71) -> 42.915838 | R24: =AVERAGE(Data!M69:M71) -> 88.740253 | S24: =Q24/R24 -> 0.48361185 | T24: 15996968 | U24: =AB24+AE24+AG24 -> 3561.0108 | V24: =AC24+AF24+AH24 -> 3483.3491 | W24: =U24/V24 -> 1.0222951 | X24: 2562.3005 | Y24: 2390.5956 | Z24: 252.44723 | AA24: 527.72848 | AB24: =X24+Z24 -> 2814.7478 | AC24: =Y24+AA24 -> 2918.324 | AD24: =AB24/AC24 -> 0.9645083 | AE24: 46.263114 | AF24: 537.3423 | AG24: 699.99995 | AH24: 27.68273 | AI24: 8.476 | AJ24: 2.5 | AK24: 2428.0777 | AL24: 599.69354 | AM24: 1807.5348 | AN24: 1252.9403 | AQ24: =AG24-AH24 -> 672.31722
A25: 38596 | B25: 68.377844 | C25: 196.27552 | D25: =SUM(Data!C72:C74) -> 590.6 | E25: =SUM(Data!D72:D74) -> 2408.64 | F25: =SUM(Data!E72:E74) -> 2379.06 | G25: =E25/F25 -> 1.0124335 | H25: =E25/O25 -> 0.23337077 | I25: 2346.3052 | J25: -60.396773 | K25: 2618.7441 | L25: 2321.9019 | M25: 275.79059 | N25: 59.669853 | O25: 10321.087 | P25: 59.308309 | Q25: =AVERAGE(Data!L72:L74) -> 42.95478 | R25: =AVERAGE(Data!M72:M74) -> 89.820041 | S25: =Q25/R25 -> 0.47823158 | T25: 16340891 | U25: =AB25+AE25+AG25 -> 3795.1921 | V25: =AC25+AF25+AH25 -> 3405.7618 | W25: =U25/V25 -> 1.1143446 | X25: 2782.9461 | Y25: 2374.9804 | Z25: 254.67597 | AA25: 518.93459 | AB25: =X25+Z25 -> 3037.6221 | AC25: =Y25+AA25 -> 2893.915 | AD25: =AB25/AC25 -> 1.0496584 | AE25: 55.848027 | AF25: 470.56384 | AG25: 701.72195 | AH25: 41.282903 | AI25: 8.218 | AJ25: 2.5 | AK25: 2379.0575 | AL25: 640.202 | AM25: 1763.0157 | AN25: 1113.0331 | AQ25: =AG25-AH25 -> 660.43905
A26: 38687 | B26: 69.064973 | C26: 198.51557 | D26: =SUM(Data!C75:C77) -> 593.6 | E26: =SUM(Data!D75:D77) -> 2585.43 | F26: =SUM(Data!E75:E77) -> 2326.01 | G26: =E26/F26 -> 1.11153 | H26: =E26/O26 -> 0.2274143 | I26: 2442.2246 | J26: 273.97038 | K26: 2789.4784 | L26: 2593.8248 | M26: 197.57133 | N26: 62.022528 | O26: 11368.81 | P26: 59.904298 | Q26: =AVERAGE(Data!L75:L77) -> 43.38108 | R26: =AVERAGE(Data!M75:M77) -> 90.276289 | S26: =Q26/R26 -> 0.48053681 | T26: 18248352 | U26: =AB26+AE26+AG26 -> 3843.1009 | V26: =AC26+AF26+AH26 -> 3853.7982 | W26: =U26/V26 -> 0.99722422 | X26: 2817.1266 | Y26: 2725.5013 | Z26: 243.44627 | AA26: 572.4683 | AB26: =X26+Z26 -> 3060.5729 | AC26: =Y26+AA26 -> 3297.9696 | AD26: =AB26/AC26 -> 0.92801731 | AE26: 71.149946 | AF26: 523.61313 | AG26: 711.37805 | AH26: 32.215447 | AI26: 59.249 | AJ26: 2.5 | AK26: 2326.0169 | AL26: 539.75705 | AM26: 1805.9625 | AN26: 990.38824 | AQ26: =AG26-AH26 -> 679.1626
A27: 38777 | B27: 69.80051 | C27: 199.72929 | D27: =SUM(Data!C78:C80) -> 596.8 | E27: =SUM(Data!D78:D80) -> 2215.89 | F27: =SUM(Data!E78:E80) -> 2541.94 | G27: =E27/F27 -> 0.87173183 | H27: =E27/O27 -> 0.21083243 | I27: 2630.4753 | J27: 177.26274 | K27: 3154.6413 | L27: 2638.8477 | M27: 537.09925 | N27: 66.794543 | O27: 10510.195 | P27: 60.542274 | Q27: =AVERAGE(Data!L78:L80) -> 44.001276 | R27: =AVERAGE(Data!M78:M80) -> 90.762953 | S27: =Q27/R27 -> 0.48479335 | T27: 16174029 | U27: =AB27+AE27+AG27 -> 4150.9331 | V27: =AC27+AF27+AH27 -> 3666.8375 | W27: =U27/V27 -> 1.1320199 | X27: 3139.0276 | Y27: 2562.4727 | Z27: 250.86802 | AA27: 565.04754 | AB27: =X27+Z27 -> 3389.8956 | AC27: =Y27+AA27 -> 3127.5202 | AD27: =AB27/AC27 -> 1.0838925 | AE27: 67.803746 | AF27: 521.0035 | AG27: 693.23382 | AH27: 18.313748 | AI27: 4.727 | AJ27: 2.6 | AK27: 2541.9465 | AL27: 731.52087 | AM27: 1764.9923 | AN27: 1039.958 | AQ27: =AG27-AH27 -> 674.92007
A28: 38869 | B28: 69.984833 | C28: 201.47771 | D28: =SUM(Data!C81:C83) -> 606.9 | E28: =SUM(Data!D81:D83) -> 2343.49 | F28: =SUM(Data!E81:E83) -> 3098.64 | G28: =E28/F28 -> 0.75629631 | H28: =E28/O28 -> 0.21101512 | I28: 2887.4216 | J28: 364.31395 | K28: 3201.347 | L28: 2755.2851 | M28: 432.52728 | N28: 68.294545 | O28: 11105.792 | P28: 60.702149 | Q28: =AVERAGE(Data!L81:L83) -> 44.251173 | R28: =AVERAGE(Data!M81:M83) -> 92.298988 | S28: =Q28/R28 -> 0.47943292 | T28: 16669237 | U28: =AB28+AE28+AG28 -> 4522.2718 | V28: =AC28+AF28+AH28 -> 3922.5145 | W28: =U28/V28 -> 1.1529012 | X28: 3434.7551 | Y28: 2774.5544 | Z28: 257.15776 | AA28: 574.50399 | AB28: =X28+Z28 -> 3691.9129 | AC28: =Y28+AA28 -> 3349.0584 | AD28: =AB28/AC28 -> 1.1023734 | AE28: 71.77974 | AF28: 543.52232 | AG28: 758.5792 | AH28: 29.933773 | AI28: 6.084 | AJ28: 2.6 | AK28: 3098.6391 | AL28: 827.34996 | AM28: 2386.6073 | AN28: 1524.9427 | AQ28: =AG28-AH28 -> 728.64543
A29: 38961 | B29: 70.50975 | C29: 202.68732 | D29: =SUM(Data!C84:C86) -> 610.3 | E29: =SUM(Data!D84:D86) -> 2392.71 | F29: =SUM(Data!E84:E86) -> 2454.67 | G29: =E29/F29 -> 0.97475832 | H29: =E29/O29 -> 0.20545156 | I29: 2442.1426 | J29: 19.300756 | K29: 3164.3868 | L29: 3011.0361 | M29: 123.71207 | N29: 66.321646 | O29: 11646.103 | P29: 61.157442 | Q29: =AVERAGE(Data!L84:L86) -> 44.32381 | R29: =AVERAGE(Data!M84:M86) -> 92.81607 | S29: =Q29/R29 -> 0.47754457 | T29: 17236054 | U29: =AB29+AE29+AG29 -> 4546.4152 | V29: =AC29+AF29+AH29 -> 4213.8619 | W29: =U29/V29 -> 1.0789189 | X29: 3383.3222 | Y29: 3048.5813 | Z29: 268.76751 | AA29: 578.53947 | AB29: =X29+Z29 -> 3652.0898 | AC29: =Y29+AA29 -> 3627.1208 | AD29: =AB29/AC29 -> 1.006884 | AE29: 75.541664 | AF29: 535.58164 | AG29: 818.7838 | AH29: 51.159427 | AI29: 6.28 | AJ29: 2.6 | AK29: 2454.674 | AL29: 547.00908 | AM29: 2014.0746 | AN29: 1268.6961 | AQ29: =AG29-AH29 -> 767.62438
A30: 39052 | B30: 71.236893 | C30: 202.44265 | D30: =SUM(Data!C87:C89) -> 605.1 | E30: =SUM(Data!D87:D89) -> 2975.89 | F30: =SUM(Data!E87:E89) -> 3167.46 | G30: =E30/F30 -> 0.93951936 | H30: =E30/O30 -> 0.23943749 | I30: 3323.6636 | J30: 896.59606 | K30: 3202.6509 | L30: 2855.8046 | M30: 381.29365 | N30: 62.557473 | O30: 12428.672 | P30: 61.788138 | Q30: =AVERAGE(Data!L87:L89) -> 44.724334 | R30: =AVERAGE(Data!M87:M89) -> 92.02524 | S30: =Q30/R30 -> 0.48600074 | T30: 18857354 | U30: =AB30+AE30+AG30 -> 4513.3708 | V30: =AC30+AF30+AH30 -> 4189.8503 | W30: =U30/V30 -> 1.0772153 | X30: 3218.9868 | Y30: 3022.0771 | Z30: 259.73753 | AA30: 623.17919 | AB30: =X30+Z30 -> 3478.7243 | AC30: =Y30+AA30 -> 3645.2563 | AD30: =AB30/AC30 -> 0.95431541 | AE30: 71.442927 | AF30: 514.065 | AG30: 963.20356 | AH30: 30.528935 | AI30: 19.421 | AJ30: 2.6 | AK30: 3167.4591 | AL30: 1129.1267 | AM30: 2167.538 | AN30: 1119.1738 | AQ30: =AG30-AH30 -> 932.67462
A31: 39142 | B31: 71.240798 | C31: 204.6774 | D31: =SUM(Data!C90:C92) -> 611.267 | E31: =SUM(Data!D90:D92) -> 2272.38 | F31: =SUM(Data!E90:E92) -> 2728.76 | G31: =E31/F31 -> 0.83275187 | H31: =E31/O31 -> 0.20750959 | I31: 2822.2983 | J31: 200.37217 | K31: 3016.8122 | L31: 3038.3683 | M31: -15.453257 | N31: 62.652366 | O31: 10950.723 | P31: 61.791525 | Q31: =AVERAGE(Data!L90:L92) -> 44.906871 | R31: =AVERAGE(Data!M90:M92) -> 92.963134 | S31: =Q31/R31 -> 0.48306107 | T31: 16460616 | U31: =AB31+AE31+AG31 -> 4163.0114 | V31: =AC31+AF31+AH31 -> 4098.7001 | W31: =U31/V31 -> 1.0156907 | X31: 2999.8047 | Y31: 2902.183 | Z31: 273.33095 | AA31: 612.78766 | AB31: =X31+Z31 -> 3273.1356 | AC31: =Y31+AA31 -> 3514.9706 | AD31: =AB31/AC31 -> 0.93119856 | AE31: 79.343964 | AF31: 551.1426 | AG31: 810.5318 | AH31: 32.586853 | AI31: 60.8966 | AJ31: 2.5 | AK31: 2728.7546 | AL31: 572.96615 | AM31: 1919.7904 | AN31: 1156.7422 | AQ31: =AG31-AH31 -> 777.94495
A32: 39234 | B32: 71.176109 | C32: 206.77243 | D32: =SUM(Data!C93:C95) -> 622.987 | E32: =SUM(Data!D93:D95) -> 2615.5 | F32: =SUM(Data!E93:E95) -> 3300.95 | G32: =E32/F32 -> 0.79234766 | H32: =E32/O32 -> 0.22348239 | I32: 3045.5394 | J32: 236.1932 | K32: 3214.052 | L32: 2959.893 | M32: 227.34762 | N32: 61.630985 | O32: 11703.383 | P32: 61.735416 | Q32: =AVERAGE(Data!L93:L95) -> 45.008502 | R32: =AVERAGE(Data!M93:M95) -> 94.745543 | S32: =Q32/R32 -> 0.47504611 | T32: 16855707 | U32: =AB32+AE32+AG32 -> 4752.0242 | V32: =AC32+AF32+AH32 -> 4206.7555 | W32: =U32/V32 -> 1.1296174 | X32: 3480.896 | Y32: 2981.6206 | Z32: 301.92297 | AA32: 623.37685 | AB32: =X32+Z32 -> 3782.819 | AC32: =Y32+AA32 -> 3604.9975 | AD32: =AB32/AC32 -> 1.0493264 | AE32: 80.242146 | AF32: 562.51687 | AG32: 888.96306 | AH32: 39.241132 | AI32: 19.4922 | AJ32: 2.5 | AK32: 3300.9456 | AL32: 691.64011 | AM32: 2480.8021 | AN32: 1526.135 | AQ32: =AG32-AH32 -> 849.72192
A33: 39326 | B33: 72.268273 | C33: 207.36874 | D33: =SUM(Data!C96:C98) -> 624.706 | E33: =SUM(Data!D96:D98) -> 3360.95 | F33: =SUM(Data!E96:E98) -> 3814.82 | G33: =E33/F33 -> 0.88102453 | H33: =E33/O33 -> 0.26718281 | I33: 3826.5083 | J33: 404.34698 | K33: 3700.1941 | L33: 3249.2279 | M33: 439.42705 | N33: 71.197255 | O33: 12579.215 | P33: 62.682718 | Q33: =AVERAGE(Data!L96:L98) -> 45.4472 | R33: =AVERAGE(Data!M96:M98) -> 95.006973 | S33: =Q33/R33 -> 0.47835646 | T33: 17498795 | U33: =AB33+AE33+AG33 -> 5299.4952 | V33: =AC33+AF33+AH33 -> 4625.2364 | W33: =U33/V33 -> 1.1457782 | X33: 3970.0201 | Y33: 3329.7637 | Z33: 316.70418 | AA33: 654.82369 | AB33: =X33+Z33 -> 4286.7243 | AC33: =Y33+AA33 -> 3984.5874 | AD33: =AB33/AC33 -> 1.0758264 | AE33: 85.458678 | AF33: 598.81598 | AG33: 927.31226 | AH33: 41.833038 | AI33: 14.3488 | AJ33: 2.5 | AK33: 3814.8134 | AL33: 968.70973 | AM33: 2479.2729 | AN33: 1481.528 | AQ33: =AG33-AH33 -> 885.47922
A34: 39417 | B34: 73.262135 | C34: 210.54983 | D34: =SUM(Data!C99:C101) -> 629.149 | E34: =SUM(Data!D99:D101) -> 4056.63 | F34: =SUM(Data!E99:E101) -> 3786.08 | G34: =E34/F34 -> 1.0714591 | H34: =E34/O34 -> 0.27755851 | I34: 3913.7917 | J34: 626.9968 | K34: 4404.7421 | L34: 3621.7782 | M34: 796.37548 | N34: 93.695847 | O34: 14615.405 | P34: 63.544755 | Q34: =AVERAGE(Data!L99:L101) -> 45.973711 | R34: =AVERAGE(Data!M99:M101) -> 95.682676 | S34: =Q34/R34 -> 0.48048103 | T34: 19433027 | U34: =AB34+AE34+AG34 -> 5745.5463 | V34: =AC34+AF34+AH34 -> 5142.8963 | W34: =U34/V34 -> 1.1171811 | X34: 4419.4347 | Y34: 3833.5631 | Z34: 308.13183 | AA34: 680.57473 | AB34: =X34+Z34 -> 4727.5665 | AC34: =Y34+AA34 -> 4514.1378 | AD34: =AB34/AC34 -> 1.0472801 | AE34: 92.397631 | AF34: 593.0822 | AG34: 925.58217 | AH34: 35.676281 | AI34: 10.707337 | AJ34: 2.5 | AK34: 3786.079 | AL34: 1084.7439 | AM34: 2582.955 | AN34: 1400.8706 | AQ34: =AG34-AH34 -> 889.90589
A35: 39508 | B35: 74.99912 | C35: 213.05212 | D35: =SUM(Data!C102:C104) -> 636.301 | E35: =SUM(Data!D102:D104) -> 3663.68 | F35: =SUM(Data!E102:E104) -> 4921.2 | G35: =E35/F35 -> 0.74446883 | H35: =E35/O35 -> 0.26606182 | I35: 5084.1936 | J35: 871.96596 | K35: 4879.9117 | L35: 3854.4873 | M35: 868.09979 | N35: 102.81011 | O35: 13770.033 | P35: 65.051349 | Q35: =AVERAGE(Data!L102:L104) -> 47.279507 | R35: =AVERAGE(Data!M102:M104) -> 96.770372 | S35: =Q35/R35 -> 0.4885742 | T35: 17414431 | U35: =AB35+AE35+AG35 -> 6137.4308 | V35: =AC35+AF35+AH35 -> 4817.7035 | W35: =U35/V35 -> 1.2739329 | X35: 4803.6524 | Y35: 3665.4247 | Z35: 330.11935 | AA35: 668.3594 | AB35: =X35+Z35 -> 5133.7718 | AC35: =Y35+AA35 -> 4333.7841 | AD35: =AB35/AC35 -> 1.1845933 | AE35: 80.305507 | AF35: 457.32206 | AG35: 923.35354 | AH35: 26.597315 | AI35: 37.441 | AJ35: 2.6 | AK35: 4921.1936 | AL35: 2073.003 | AM35: 2645.8726 | AN35: 1492.1009 | AQ35: =AG35-AH35 -> 896.75622
A36: 39600 | B36: 77.630993 | C36: 215.84133 | D36: =SUM(Data!C105:C107) -> 650.27 | E36: =SUM(Data!D105:D107) -> 4980.08 | F36: =SUM(Data!E105:E107) -> 5883.99 | G36: =E36/F36 -> 0.84637805 | H36: =E36/O36 -> 0.32405128 | I36: 5495.7946 | J36: 413.17426 | K36: 5263.1428 | L36: 4328.3068 | M36: 1032.8703 | N36: 119.79716 | O36: 15368.185 | P36: 67.334134 | Q36: =AVERAGE(Data!L105:L107) -> 49.083114 | R36: =AVERAGE(Data!M105:M107) -> 98.894815 | S36: =Q36/R36 -> 0.49631635 | T36: 17990328 | U36: =AB36+AE36+AG36 -> 7118.6601 | V36: =AC36+AF36+AH36 -> 5570.4306 | W36: =U36/V36 -> 1.2779371 | X36: 5813.9316 | Y36: 4325.2773 | Z36: 365.59706 | AA36: 759.21482 | AB36: =X36+Z36 -> 6179.5287 | AC36: =Y36+AA36 -> 5084.4921 | AD36: =AB36/AC36 -> 1.2153679 | AE36: 81.711739 | AF36: 453.70069 | AG36: 857.4197 | AH36: 32.237812 | AI36: 27.52 | AJ36: 2.6 | AK36: 5883.9972 | AL36: 2747.9403 | AM36: 2961.2524 | AN36: 1829.1919 | AQ36: =AG36-AH36 -> 825.18189
A37: 39692 | B37: 79.445947 | C37: 218.38724 | D37: =SUM(Data!C108:C110) -> 657.833 | E37: =SUM(Data!D108:D110) -> 5996.31 | F37: =SUM(Data!E108:E110) -> 6255.67 | G37: =E37/F37 -> 0.95854001 | H37: =E37/O37 -> 0.3732452 | I37: 6391.7741 | J37: 154.63111 | K37: 5011.4009 | L37: 5013.7192 | M37: -4.228794 | N37: 114.37771 | O37: 16065.337 | P37: 68.908356 | Q37: =AVERAGE(Data!L108:L110) -> 49.970459 | R37: =AVERAGE(Data!M108:M110) -> 100.04502 | S37: =Q37/R37 -> 0.49947974 | T37: 18677591 | U37: =AB37+AE37+AG37 -> 6726.3621 | V37: =AC37+AF37+AH37 -> 6491.9494 | W37: =U37/V37 -> 1.0361082 | X37: 5420.3056 | Y37: 5210.428 | Z37: 377.99761 | AA37: 782.3657 | AB37: =X37+Z37 -> 5798.3032 | AC37: =Y37+AA37 -> 5992.7937 | AD37: =AB37/AC37 -> 0.96754594 | AE37: 90.933225 | AF37: 454.4236 | AG37: 837.1257 | AH37: 44.732056 | AI37: 19.7654 | AJ37: 2.6 | AK37: 6255.6628 | AL37: 2525.0566 | AM37: 3480.1765 | AN37: 1891.6506 | AQ37: =AG37-AH37 -> 792.39365
A38: 39783 | B38: 80.058203 | C38: 213.95845 | D38: =SUM(Data!C111:C113) -> 639.226 | E38: =SUM(Data!D111:D113) -> 7121 | F38: =SUM(Data!E111:E113) -> 5047.53 | G38: =E38/F38 -> 1.410789 | H38: =E38/O38 -> 0.44685321 | I38: 5216.0752 | J38: -913.66973 | K38: 3313.0654 | L38: 4413.0724 | M38: -1055.0617 | N38: 61.579263 | O38: 15935.882 | P38: 69.439402 | Q38: =AVERAGE(Data!L111:L113) -> 50.235625 | R38: =AVERAGE(Data!M111:M113) -> 97.215214 | S38: =Q38/R38 -> 0.51674653 | T38: 20777530 | U38: =AB38+AE38+AG38 -> 4636.1733 | V38: =AC38+AF38+AH38 -> 5969.1263 | W38: =U38/V38 -> 0.77669211 | X38: 3422.8778 | Y38: 4710.9728 | Z38: 367.90218 | AA38: 803.07954 | AB38: =X38+Z38 -> 3790.78 | AC38: =Y38+AA38 -> 5514.0523 | AD38: =AB38/AC38 -> 0.68747624 | AE38: 80.557688 | AF38: 396.88098 | AG38: 764.83567 | AH38: 58.193002 | AI38: 31.278148 | AJ38: 2.6 | AK38: 5047.5215 | AL38: 1329.2719 | AM38: 3453.1504 | AN38: 1706.2661 | AQ38: =AG38-AH38 -> 706.64266
A39: 39873 | B39: 80.892076 | C39: 212.89739 | D39: =SUM(Data!C114:C116) -> 636.045 | E39: =SUM(Data!D114:D116) -> 4259.51 | F39: =SUM(Data!E114:E116) -> 3446.17 | G39: =E39/F39 -> 1.2360127 | H39: =E39/O39 -> 0.31531104 | I39: 3611.0634 | J39: -1375.2474 | K39: 2779.4519 | L39: 3670.4289 | M39: -931.18604 | N39: 46.984913 | O39: 13508.915 | P39: 70.162672 | Q39: =AVERAGE(Data!L114:L116) -> 51.005053 | R39: =AVERAGE(Data!M114:M116) -> 96.731439 | S39: =Q39/R39 -> 0.52728517 | T39: 18181890 | U39: =AB39+AE39+AG39 -> 3879.6686 | V39: =AC39+AF39+AH39 -> 4533.7553 | W39: =U39/V39 -> 0.8557296 | X39: 2789.1636 | Y39: 3430.8795 | Z39: 320.24496 | AA39: 695.95676 | AB39: =X39+Z39 -> 3109.4085 | AC39: =Y39+AA39 -> 4126.8363 | AD39: =AB39/AC39 -> 0.75346059 | AE39: 65.872545 | AF39: 333.98522 | AG39: 704.38751 | AH39: 72.933737 | AI39: 30.529 | AJ39: 2.8 | AK39: 3446.165 | AL39: 652.35661 | AM39: 2567.3522 | AN39: 1629.4029 | AQ39: =AG39-AH39 -> 631.45377
A40: 39965 | B40: 81.899378 | C40: 213.37468 | D40: =SUM(Data!C117:C119) -> 642.789 | E40: =SUM(Data!D117:D119) -> 4682.94 | F40: =SUM(Data!E117:E119) -> 4781.94 | G40: =E40/F40 -> 0.97929711 | H40: =E40/O40 -> 0.32544142 | I40: 4397.1759 | J40: -424.65302 | K40: 3163.9533 | L40: 3252.3192 | M40: -93.580487 | N40: 55.366635 | O40: 14389.502 | P40: 71.036367 | Q40: =AVERAGE(Data!L117:L119) -> 51.774988 | R40: =AVERAGE(Data!M117:M119) -> 97.757084 | S40: =Q40/R40 -> 0.52962901 | T40: 18425949 | U40: =AB40+AE40+AG40 -> 4548.167 | V40: =AC40+AF40+AH40 -> 4397.9713 | W40: =U40/V40 -> 1.0341512 | X40: 3428.6511 | Y40: 3277.1209 | Z40: 326.05295 | AA40: 640.8013 | AB40: =X40+Z40 -> 3754.704 | AC40: =Y40+AA40 -> 3917.9222 | AD40: =AB40/AC40 -> 0.95834063 | AE40: 49.609691 | AF40: 412.42954 | AG40: 743.85331 | AH40: 67.619514 | AI40: 1939.46 | AJ40: 2.8 | AK40: 4781.9353 | AL40: 1215.7295 | AM40: 3301.2394 | AN40: 2136.3677 | AQ40: =AG40-AH40 -> 676.23379
A41: 40057 | B41: 82.237685 | C41: 214.87106 | D41: =SUM(Data!C120:C122) -> 647.154 | E41: =SUM(Data!D120:D122) -> 4745.17 | F41: =SUM(Data!E120:E122) -> 4821.5 | G41: =E41/F41 -> 0.98416883 | H41: =E41/O41 -> 0.31312042 | I41: 4781.651 | J41: -73.691801 | K41: 3708.1664 | L41: 3397.6488 | M41: 339.45945 | N41: 65.508033 | O41: 15154.457 | P41: 71.329801 | Q41: =AVERAGE(Data!L120:L122) -> 51.714221 | R41: =AVERAGE(Data!M120:M122) -> 98.420925 | S41: =Q41/R41 -> 0.52543928 | T41: 18709674 | U41: =AB41+AE41+AG41 -> 5139.0435 | V41: =AC41+AF41+AH41 -> 4502.6158 | W41: =U41/V41 -> 1.1413462 | X41: 3955.8937 | Y41: 3542.2414 | Z41: 345.35275 | AA41: 614.81155 | AB41: =X41+Z41 -> 4301.2465 | AC41: =Y41+AA41 -> 4157.0529 | AD41: =AB41/AC41 -> 1.0346865 | AE41: 43.305821 | AF41: 292.36886 | AG41: 794.49118 | AH41: 53.194048 | AI41: 19.8486 | AJ41: 2.8 | AK41: 4821.4999 | AL41: 1577.8558 | AM41: 3112.9607 | AN41: 1944.933 | AQ41: =AG41-AH41 -> 741.29714
A42: 40148 | B42: 83.200761 | C42: 217.04857 | D42: =SUM(Data!C123:C125) -> 648.456 | E42: =SUM(Data!D123:D125) -> 6922.75 | F42: =SUM(Data!E123:E125) -> 5328.81 | G42: =E42/F42 -> 1.2991174 | H42: =E42/O42 -> 0.40621456 | I42: 5604.0652 | J42: -178.45596 | K42: 4213.9612 | L42: 3761.3484 | M42: 510.10442 | N42: 79.290754 | O42: 17042.102 | P42: 72.165137 | Q42: =AVERAGE(Data!L123:L125) -> 52.217326 | R42: =AVERAGE(Data!M123:M125) -> 98.618937 | S42: =Q42/R42 -> 0.52948579 | T42: 20359099 | U42: =AB42+AE42+AG42 -> 5413.8807 | V42: =AC42+AF42+AH42 -> 5233.6371 | W42: =U42/V42 -> 1.0344395 | X42: 4238.3176 | Y42: 4018.2038 | Z42: 344.8734 | AA42: 666.74132 | AB42: =X42+Z42 -> 4583.191 | AC42: =Y42+AA42 -> 4684.9451 | AD42: =AB42/AC42 -> 0.97828062 | AE42: 40.278946 | AF42: 430.93327 | AG42: 790.41076 | AH42: 117.75872 | AI42: 67.651152 | AJ42: 2.8 | AK42: 5328.8127 | AL42: 1765.5593 | AM42: 3391.1115 | AN42: 1842.7307 | AQ42: =AG42-AH42 -> 672.65204
A43: 40238 | B43: 84.126852 | C43: 217.78 | D43: =SUM(Data!C126:C128) -> 651.059 | E43: =SUM(Data!D126:D128) -> 4897.5 | F43: =SUM(Data!E126:E128) -> 5808.66 | G43: =E43/F43 -> 0.84313766 | H43: =E43/O43 -> 0.31265515 | I43: 5967.1567 | J43: 215.38819 | K43: 4259.4893 | L43: 4403.6657 | M43: -186.79893 | N43: 81.433039 | O43: 15664.223 | P43: 72.968392 | Q43: =AVERAGE(Data!L126:L128) -> 53.060643 | R43: =AVERAGE(Data!M126:M128) -> 99.014808 | S43: =Q43/R43 -> 0.53588594 | T43: 18184931 | U43: =AB43+AE43+AG43 -> 5350.7999 | V43: =AC43+AF43+AH43 -> 5143.9111 | W43: =U43/V43 -> 1.0402201 | X43: 4292.3502 | Y43: 4113.271 | Z43: 350.20249 | AA43: 690.64971 | AB43: =X43+Z43 -> 4642.5527 | AC43: =Y43+AA43 -> 4803.9207 | AD43: =AB43/AC43 -> 0.9664091 | AE43: 19.830188 | AF43: 234.84915 | AG43: 688.41709 | AH43: 105.1413 | AI43: 25.8336 | AJ43: 2.9 | AK43: 5808.6627 | AL43: 1924.1124 | AM43: 3543.2964 | AN43: 2108.1102 | AQ43: =AG43-AH43 -> 583.27579
A44: 40330 | B44: 84.584742 | C44: 217.2153 | D44: =SUM(Data!C129:C131) -> 654.152 | E44: =SUM(Data!D129:D131) -> 5897.19 | F44: =SUM(Data!E129:E131) -> 5874.66 | G44: =E44/F44 -> 1.0038351 | H44: =E44/O44 -> 0.36549888 | I44: 5419.6274 | J44: -603.13561 | K44: 4258.705 | L44: 4777.4268 | M44: -477.91382 | N44: 74.367489 | O44: 16134.632 | P44: 73.365548 | Q44: =AVERAGE(Data!L129:L131) -> 53.457852 | R44: =AVERAGE(Data!M129:M131) -> 99.4852 | S44: =Q44/R44 -> 0.53734477 | T44: 18793111 | U44: =AB44+AE44+AG44 -> 5637.3753 | V44: =AC44+AF44+AH44 -> 5980.0014 | W44: =U44/V44 -> 0.94270468 | X44: 4563.6456 | Y44: 4824.1588 | Z44: 365.29766 | AA44: 754.69641 | AB44: =X44+Z44 -> 4928.9433 | AC44: =Y44+AA44 -> 5578.8553 | AD44: =AB44/AC44 -> 0.88350442 | AE44: 22.32369 | AF44: 297.55443 | AG44: 686.10837 | AH44: 103.59174 | AI44: 27.33436 | AJ44: 2.6 | AK44: 5874.6577 | AL44: 2011.9647 | AM44: 3609.9439 | AN44: 2354.3658 | AQ44: =AG44-AH44 -> 582.51664
A45: 40422 | B45: 85.19496 | C45: 217.49406 | D45: =SUM(Data!C132:C134) -> 654.762 | E45: =SUM(Data!D132:D134) -> 5834.76 | F45: =SUM(Data!E132:E134) -> 5480.65 | G45: =E45/F45 -> 1.0646109 | H45: =E45/O45 -> 0.34576067 | I45: 5504.154 | J45: -596.18551 | K45: 4039.4778 | L45: 5023.8147 | M45: -1004.9206 | N45: 74.138647 | O45: 16875.141 | P45: 73.894828 | Q45: =AVERAGE(Data!L132:L134) -> 53.551832 | R45: =AVERAGE(Data!M132:M134) -> 99.577971 | S45: =Q45/R45 -> 0.53778795 | T45: 19572313 | U45: =AB45+AE45+AG45 -> 5428.9098 | V45: =AC45+AF45+AH45 -> 6320.9835 | W45: =U45/V45 -> 0.85887106 | X45: 4277.876 | Y45: 5230.6102 | Z45: 374.89571 | AA45: 763.29385 | AB45: =X45+Z45 -> 4652.7717 | AC45: =Y45+AA45 -> 5993.9041 | AD45: =AB45/AC45 -> 0.77625062 | AE45: 18.422747 | AF45: 218.37014 | AG45: 757.71533 | AH45: 108.70928 | AI45: 25.654057 | AJ45: 2.6 | AK45: 5480.6559 | AL45: 1884.2243 | AM45: 3320.988 | AN45: 2140.5305 | AQ45: =AG45-AH45 -> 649.00605
A46: 40513 | B46: 85.978509 | C46: 219.77653 | D46: =SUM(Data!C135:C137) -> 656.693 | E46: =SUM(Data!D135:D137) -> 7493.1 | F46: =SUM(Data!E135:E137) -> 6014.43 | G46: =E46/F46 -> 1.2458537 | H46: =E46/O46 -> 0.38470873 | I46: 6324.4146 | J46: 243.45072 | K46: 4979.2967 | L46: 5261.2611 | M46: -328.36799 | N46: 88.281579 | O46: 19477.333 | P46: 74.574448 | Q46: =AVERAGE(Data!L135:L137) -> 53.98857 | R46: =AVERAGE(Data!M135:M137) -> 99.871642 | S46: =Q46/R46 -> 0.54057957 | T46: 22175372 | U46: =AB46+AE46+AG46 -> 6197.6423 | V46: =AC46+AF46+AH46 -> 6752.2399 | W46: =U46/V46 -> 0.91786465 | X46: 5003.2203 | Y46: 5473.0337 | Z46: 381.82578 | AA46: 786.03141 | AB46: =X46+Z46 -> 5385.046 | AC46: =Y46+AA46 -> 6259.0651 | AD46: =AB46/AC46 -> 0.86035949 | AE46: 17.142071 | AF46: 363.91655 | AG46: 795.45419 | AH46: 129.25824 | AI46: 37.258694 | AJ46: 2.6 | AK46: 6014.4255 | AL46: 2024.7192 | AM46: 3512.8234 | AN46: 2064.456 | AQ46: =AG46-AH46 -> 666.19594
A47: 40603 | B47: 86.943418 | C47: 222.31134 | D47: =SUM(Data!C138:C140) -> 664.999 | E47: =SUM(Data!D138:D140) -> 6539.28 | F47: =SUM(Data!E138:E140) -> 6990.74 | G47: =E47/F47 -> 0.93542028 | H47: =E47/O47 -> 0.365845 | I47: 7251.2018 | J47: -377.14675 | K47: 5420.5293 | L47: 5387.2686 | M47: 37.012995 | N47: 95.300621 | O47: 17874.455 | P47: 75.411373 | Q47: =AVERAGE(Data!L138:L140) -> 54.853972 | R47: =AVERAGE(Data!M138:M140) -> 101.13484 | S47: =Q47/R47 -> 0.54238451 | T47: 19701481 | U47: =AB47+AE47+AG47 -> 6689.0578 | V47: =AC47+AF47+AH47 -> 6228.4334 | W47: =U47/V47 -> 1.0739551 | X47: 5531.0274 | Y47: 5131.4468 | Z47: 374.66278 | AA47: 773.51722 | AB47: =X47+Z47 -> 5905.6902 | AC47: =Y47+AA47 -> 5904.964 | AD47: =AB47/AC47 -> 1.000123 | AE47: 19.727297 | AF47: 267.40186 | AG47: 763.64037 | AH47: 56.067591 | AI47: 35.641 | AJ47: 2.6 | AK47: 6990.742 | AL47: 2917.1987 | AM47: 3628.3269 | AN47: 2213.5466 | AQ47: =AG47-AH47 -> 707.57278
A48: 40695 | B48: 88.129961 | C48: 224.74712 | D48: =SUM(Data!C141:C143) -> 676.592 | E48: =SUM(Data!D141:D143) -> 7432.91 | F48: =SUM(Data!E141:E143) -> 8211 | G48: =E48/F48 -> 0.9052381 | H48: =E48/O48 -> 0.39071057 | I48: 7588.0149 | J48: 81.691799 | K48: 5542.1107 | L48: 5814.5087 | M48: -197.58027 | N48: 100.03598 | O48: 19024.082 | P48: 76.440535 | Q48: =AVERAGE(Data!L141:L143) -> 55.665327 | R48: =AVERAGE(Data!M141:M143) -> 102.89794 | S48: =Q48/R48 -> 0.54097613 | T48: 20583919 | U48: =AB48+AE48+AG48 -> 7072.4599 | V48: =AC48+AF48+AH48 -> 7100.1184 | W48: =U48/V48 -> 0.9961045 | X48: 5889.6957 | Y48: 5872.2138 | Z48: 384.79142 | AA48: 786.53673 | AB48: =X48+Z48 -> 6274.4871 | AC48: =Y48+AA48 -> 6658.7505 | AD48: =AB48/AC48 -> 0.94229197 | AE48: 18.901448 | AF48: 378.91911 | AG48: 779.07133 | AH48: 62.448815 | AI48: 30.45 | AJ48: 2.6 | AK48: 8210.9995 | AL48: 3492.776 | AM48: 4334.9975 | AN48: 2677.3791 | AQ48: =AG48-AH48 -> 716.62251
A49: 40787 | B49: 89.3811 | C49: 225.75776 | D49: =SUM(Data!C144:C146) -> 679.356 | E49: =SUM(Data!D144:D146) -> 7597.49 | F49: =SUM(Data!E144:E146) -> 7891.74 | G49: =E49/F49 -> 0.96271418 | H49: =E49/O49 -> 0.38632196 | I49: 7924.4647 | J49: 32.442442 | K49: 5525.0098 | L49: 5781.0564 | M49: -262.91128 | N49: 87.968774 | O49: 19666.213 | P49: 77.525724 | Q49: =AVERAGE(Data!L144:L146) -> 56.170974 | R49: =AVERAGE(Data!M144:M146) -> 103.31829 | S49: =Q49/R49 -> 0.54366921 | T49: 21361932 | U49: =AB49+AE49+AG49 -> 6956.6474 | V49: =AC49+AF49+AH49 -> 7123.9395 | W49: =U49/V49 -> 0.97651691 | X49: 5795.4846 | Y49: 5986.9523 | Z49: 404.0369 | AA49: 791.90196 | AB49: =X49+Z49 -> 6199.5215 | AC49: =Y49+AA49 -> 6778.8543 | AD49: =AB49/AC49 -> 0.91453824 | AE49: 20.057616 | AF49: 275.27693 | AG49: 737.06833 | AH49: 69.808312 | AI49: 22.422 | AJ49: 2.6 | AK49: 7891.7308 | AL49: 3301.4875 | AM49: 4128.1665 | AN49: 2375.165 | AQ49: =AG49-AH49 -> 667.26002
A50: 40878 | B50: 90.625336 | C50: 226.96056 | D50: =SUM(Data!C147:C149) -> 678.323 | E50: =SUM(Data!D147:D149) -> 9720.57 | F50: =SUM(Data!E147:E149) -> 8096.31 | G50: =E50/F50 -> 1.2006173 | H50: =E50/O50 -> 0.4335302 | I50: 8600.8229 | J50: 330.89367 | K50: 5842.7195 | L50: 6147.2152 | M50: -406.61436 | N50: 97.085138 | O50: 22421.898 | P50: 78.604927 | Q50: =AVERAGE(Data!L147:L149) -> 56.94676 | R50: =AVERAGE(Data!M147:M149) -> 103.16119 | S50: =Q50/R50 -> 0.55201728 | T50: 23755499 | U50: =AB50+AE50+AG50 -> 7020.866 | V50: =AC50+AF50+AH50 -> 7686.221 | W50: =U50/V50 -> 0.91343536 | X50: 5866.1154 | Y50: 6394.3244 | Z50: 423.97899 | AA50: 798.21539 | AB50: =X50+Z50 -> 6290.0944 | AC50: =Y50+AA50 -> 7192.5397 | AD50: =AB50/AC50 -> 0.87453036 | AE50: 25.7785 | AF50: 419.62846 | AG50: 704.99315 | AH50: 74.05274 | AI50: 20.668547 | AJ50: 2.6 | AK50: 8096.3008 | AL50: 3223.1396 | AM50: 4397.4161 | AN50: 2498.8878 | AQ50: =AG50-AH50 -> 630.94041
A51: 40969 | B51: 91.850408 | C51: 228.49762 | D51: =SUM(Data!C150:C152) -> 683.72 | E51: =SUM(Data!D150:D152) -> 8126.412 | F51: =SUM(Data!E150:E152) -> 9173.692 | G51: =E51/F51 -> 0.88583877 | H51: =E51/O51 -> 0.39468687 | I51: 9411.3895 | J51: 153.40068 | K51: 6284.5909 | L51: 6103.3399 | M51: 111.72184 | N51: 103.58711 | O51: 20589.517 | P51: 79.667508 | Q51: =AVERAGE(Data!L150:L152) -> 57.951223 | R51: =AVERAGE(Data!M150:M152) -> 103.98198 | S51: =Q51/R51 -> 0.55731986 | T51: 21097535 | U51: =AB51+AE51+AG51 -> 7586.0522 | V51: =AC51+AF51+AH51 -> 6986.9552 | W51: =U51/V51 -> 1.0857451 | X51: 6414.6285 | Y51: 5818.3257 | Z51: 434.60729 | AA51: 785.87968 | AB51: =X51+Z51 -> 6849.2358 | AC51: =Y51+AA51 -> 6604.2054 | AD51: =AB51/AC51 -> 1.0371022 | AE51: 25.234039 | AF51: 319.69249 | AG51: 711.58235 | AH51: 63.057308 | AI51: 36.547 | AJ51: 2.7 | AK51: 9019.2587 | AL51: 4246.3678 | AM51: 4772.8908 | AN51: 2830.3177 | AQ51: =AG51-AH51 -> 648.52504
A52: 41061 | B52: 92.674622 | C52: 229.02298 | D52: =SUM(Data!C153:C155) -> 689.378 | E52: =SUM(Data!D153:D155) -> 8949.305 | F52: =SUM(Data!E153:E155) -> 9859.405 | G52: =E52/F52 -> 0.9076922 | H52: =E52/O52 -> 0.42521183 | I52: 9058.0983 | J52: 93.631265 | K52: 5909.4331 | L52: 6084.6098 | M52: -118.93256 | N52: 91.796453 | O52: 21046.698 | P52: 80.382399 | Q52: =AVERAGE(Data!L153:L155) -> 58.498812 | R52: =AVERAGE(Data!M153:M155) -> 104.84247 | S52: =Q52/R52 -> 0.55796868 | T52: 21753840 | U52: =AB52+AE52+AG52 -> 7434.3337 | V52: =AC52+AF52+AH52 -> 7424.1311 | W52: =U52/V52 -> 1.0013743 | X52: 6247.4174 | Y52: 6159.0616 | Z52: 448.41212 | AA52: 814.30798 | AB52: =X52+Z52 -> 6695.8295 | AC52: =Y52+AA52 -> 6973.3696 | AD52: =AB52/AC52 -> 0.96020001 | AE52: 26.808486 | AF52: 378.46926 | AG52: 711.69568 | AH52: 72.292247 | AI52: 29.538 | AJ52: 2.7 | AK52: 9665.6654 | AL52: 4223.8459 | AM52: 5441.8195 | AN52: 3361.5305 | AQ52: =AG52-AH52 -> 639.40343
A53: 41153 | B53: 93.894779 | C53: 229.653 | D53: =SUM(Data!C156:C158) -> 690.89 | E53: =SUM(Data!D156:D158) -> 9241.077 | F53: =SUM(Data!E156:E158) -> 9157.247 | G53: =E53/F53 -> 1.0091545 | H53: =E53/O53 -> 0.42185728 | I53: 9281.2757 | J53: -404.50712 | K53: 5850.4068 | L53: 6233.7954 | M53: -363.89327 | N53: 90.19678 | O53: 21905.695 | P53: 81.440716 | Q53: =AVERAGE(Data!L156:L158) -> 59.015058 | R53: =AVERAGE(Data!M156:M158) -> 105.07241 | S53: =Q53/R53 -> 0.56166082 | T53: 22538013 | U53: =AB53+AE53+AG53 -> 7256.4838 | V53: =AC53+AF53+AH53 -> 7566.529 | W53: =U53/V53 -> 0.95902412 | X53: 6109.6997 | Y53: 6413.5162 | Z53: 455.15936 | AA53: 796.91176 | AB53: =X53+Z53 -> 6564.8591 | AC53: =Y53+AA53 -> 7210.4279 | AD53: =AB53/AC53 -> 0.91046733 | AE53: 24.894274 | AF53: 288.98137 | AG53: 666.73043 | AH53: 67.119688 | AI53: 19.512 | AJ53: 2.7 | AK53: 8578.3475 | AL53: 3461.8698 | AM53: 5116.4777 | AN53: 3016.8325 | AQ53: =AG53-AH53 -> 599.61074
A54: 41244 | B54: 94.77018 | C54: 231.19506 | D54: =SUM(Data!C159:C161) -> 691.139 | E54: =SUM(Data!D159:D161) -> 11648.31 | F54: =SUM(Data!E159:E161) -> 8950.74 | G54: =E54/F54 -> 1.3013796 | H54: =E54/O54 -> 0.48147165 | I54: 9247.579 | J54: -521.65824 | K54: 5731.5079 | L54: 5790.9932 | M54: -132.52794 | N54: 90.790325 | O54: 24193.138 | P54: 82.200005 | Q54: =AVERAGE(Data!L159:L161) -> 59.581279 | R54: =AVERAGE(Data!M159:M161) -> 105.11028 | S54: =Q54/R54 -> 0.56684538 | T54: 24952468 | U54: =AB54+AE54+AG54 -> 6957.5392 | V54: =AC54+AF54+AH54 -> 7400.4198 | W54: =U54/V54 -> 0.94015466 | X54: 5797.1527 | Y54: 6128.0454 | Z54: 465.83387 | AA54: 801.25266 | AB54: =X54+Z54 -> 6262.9865 | AC54: =Y54+AA54 -> 6929.2981 | AD54: =AB54/AC54 -> 0.90384141 | AE54: 27.988721 | AF54: 397.19962 | AG54: 666.56397 | AH54: 73.922122 | AI54: 63.10864 | AJ54: 2.7 | AK54: 8067.4033 | AL54: 3075.9621 | AM54: 4991.4413 | AN54: 2962.2995 | AQ54: =AG54-AH54 -> 592.64185
A55: 41334 | B55: 95.109464 | C55: 232.33447 | D55: =SUM(Data!C162:C164) -> 695.219 | E55: =SUM(Data!D162:D164) -> 9341.585 | F55: =SUM(Data!E162:E164) -> 9318.245 | G55: =E55/F55 -> 1.0025048 | H55: =E55/O55 -> 0.42336728 | I55: 9781.3321 | J55: -979.90261 | K55: 6254.4999 | L55: 6648.5752 | M55: -317.09263 | N55: 95.369949 | O55: 22064.967 | P55: 82.494287 | Q55: =AVERAGE(Data!L162:L164) -> 59.995697 | R55: =AVERAGE(Data!M162:M164) -> 105.73078 | S55: =Q55/R55 -> 0.56743833 | T55: 22232257 | U55: =AB55+AE55+AG55 -> 7542.0947 | V55: =AC55+AF55+AH55 -> 7608.6837 | W55: =U55/V55 -> 0.99124829 | X55: 6380.0272 | Y55: 6379.2806 | Z55: 486.1609 | AA55: 846.63337 | AB55: =X55+Z55 -> 6866.1881 | AC55: =Y55+AA55 -> 7225.914 | AD55: =AB55/AC55 -> 0.95021724 | AE55: 28.523614 | AF55: 325.23153 | AG55: 647.38303 | AH55: 57.538148 | AI55: 31.8252 | AJ55: 2.7 | AK55: 8815.1185 | AL55: 3442.5152 | AM55: 5372.6033 | AN55: 3238.0714 | AQ55: =AG55-AH55 -> 589.84489
A56: 41426 | B56: 95.408489 | C56: 232.22025 | D56: =SUM(Data!C165:C167) -> 698.98 | E56: =SUM(Data!D165:D167) -> 10313.705 | F56: =SUM(Data!E165:E167) -> 10296.155 | G56: =E56/F56 -> 1.0017045 | H56: =E56/O56 -> 0.45137894 | I56: 9430.6178 | J56: -950.90153 | K56: 5815.3691 | L56: 6655.9651 | M56: -784.16292 | N56: 92.746275 | O56: 22849.327 | P56: 82.75365 | Q56: =AVERAGE(Data!L165:L167) -> 60.198838 | R56: =AVERAGE(Data!M165:M167) -> 106.30276 | S56: =Q56/R56 -> 0.56629608 | T56: 23313980 | U56: =AB56+AE56+AG56 -> 7309.2819 | V56: =AC56+AF56+AH56 -> 7995.1204 | W56: =U56/V56 -> 0.91421787 | X56: 6112.2953 | Y56: 6681.7232 | Z56: 481.9322 | AA56: 850.88751 | AB56: =X56+Z56 -> 6594.2275 | AC56: =Y56+AA56 -> 7532.6107 | AD56: =AB56/AC56 -> 0.87542391 | AE56: 28.054986 | AF56: 383.27032 | AG56: 686.9994 | AH56: 79.239373 | AI56: 27.863 | AJ56: 2.7 | AK56: 9654.8602 | AL56: 3357.0175 | AM56: 6297.8427 | AN56: 3788.4424 | AQ56: =AG56-AH56 -> 607.76003
A57: 41518 | B57: 95.853023 | C57: 233.25068 | D57: =SUM(Data!C168:C170) -> 701.622 | E57: =SUM(Data!D168:D170) -> 10971.614 | F57: =SUM(Data!E168:E170) -> 10540.644 | G57: =E57/F57 -> 1.0408865 | H57: =E57/O57 -> 0.44757901 | I57: 10403.118 | J57: -733.10553 | K57: 6358.4941 | L57: 6498.2122 | M57: -108.76904 | N57: 103.50745 | O57: 24513.245 | P57: 83.139221 | Q57: =AVERAGE(Data!L168:L170) -> 60.269193 | R57: =AVERAGE(Data!M168:M170) -> 106.70457 | S57: =Q57/R57 -> 0.564823 | T57: 24369093 | U57: =AB57+AE57+AG57 -> 7842.4561 | V57: =AC57+AF57+AH57 -> 7899.5486 | W57: =U57/V57 -> 0.99277269 | X57: 6605.2577 | Y57: 6640.8575 | Z57: 521.96181 | AA57: 850.81447 | AB57: =X57+Z57 -> 7127.2195 | AC57: =Y57+AA57 -> 7491.6719 | AD57: =AB57/AC57 -> 0.95135232 | AE57: 27.205568 | AF57: 320.43941 | AG57: 688.03106 | AH57: 87.437265 | AI57: 18.582 | AJ57: 2.7 | AK57: 9316.029 | AL57: 3695.7633 | AM57: 5620.2657 | AN57: 3420.9584 | AQ57: =AG57-AH57 -> 600.5938
A58: 41609 | B58: 96.977249 | C58: 234.00483 | D58: =SUM(Data!C171:C173) -> 699.664 | E58: =SUM(Data!D171:D173) -> 14592.105 | F58: =SUM(Data!E171:E173) -> 10716.445 | G58: =E58/F58 -> 1.3616554 | H58: =E58/O58 -> 0.53760508 | I58: 11431.494 | J58: -1611.3284 | K58: 6417.6544 | L58: 6028.1215 | M58: 230.50055 | N58: 99.743949 | O58: 27142.796 | P58: 84.114332 | Q58: =AVERAGE(Data!L171:L173) -> 60.98008 | R58: =AVERAGE(Data!M171:M173) -> 106.40679 | S58: =Q58/R58 -> 0.57308449 | T58: 26941292 | U58: =AB58+AE58+AG58 -> 7749.4823 | V58: =AC58+AF58+AH58 -> 7873.0133 | W58: =U58/V58 -> 0.98430956 | X58: 6489.1949 | Y58: 6413.4678 | Z58: 551.31311 | AA58: 912.60012 | AB58: =X58+Z58 -> 7040.508 | AC58: =Y58+AA58 -> 7326.0679 | AD58: =AB58/AC58 -> 0.96102139 | AE58: 28.842329 | AF58: 444.5293 | AG58: 680.13199 | AH58: 102.41611 | AI58: 17.444399 | AJ58: 2.7 | AK58: 9513.6467 | AL58: 3890.8446 | AM58: 5622.802 | AN58: 3220.0819 | AQ58: =AG58-AH58 -> 577.71588
A59: 41699 | B59: 97.963578 | C59: 235.61578 | D59: =SUM(Data!C174:C176) -> 704.99 | E59: =SUM(Data!D174:D176) -> 9920.952 | F59: =SUM(Data!E174:E176) -> 9909.342 | G59: =E59/F59 -> 1.0011716 | H59: =E59/O59 -> 0.41477584 | I59: 10023.632 | J59: -965.56663 | K59: 6745.8263 | L59: 6535.5065 | M59: 286.66348 | N59: 100.52994 | O59: 23918.828 | P59: 84.969836 | Q59: =AVERAGE(Data!L174:L176) -> 61.772206 | R59: =AVERAGE(Data!M174:M176) -> 107.21678 | S59: =Q59/R59 -> 0.57614308 | T59: 23411663 | U59: =AB59+AE59+AG59 -> 8170.6977 | V59: =AC59+AF59+AH59 -> 7660.0348 | W59: =U59/V59 -> 1.0666659 | X59: 6880.0707 | Y59: 6221.6378 | Z59: 558.46202 | AA59: 883.62788 | AB59: =X59+Z59 -> 7438.5327 | AC59: =Y59+AA59 -> 7105.2656 | AD59: =AB59/AC59 -> 1.0469042 | AE59: 30.103642 | AF59: 410.0327 | AG59: 702.06137 | AH59: 144.73647 | AI59: 35.0736 | AJ59: 2.7 | AK59: 9459.0459 | AL59: 3629.0448 | AM59: 5830.0012 | AN59: 3358.8353 | AQ59: =AG59-AH59 -> 557.32491
A60: 41791 | B60: 98.703415 | C60: 236.98945 | D60: =SUM(Data!C177:C179) -> 713.315 | E60: =SUM(Data!D177:D179) -> 11117.589 | F60: =SUM(Data!E177:E179) -> 11920.849 | G60: =E60/F60 -> 0.93261722 | H60: =E60/O60 -> 0.44419499 | I60: 11006.365 | J60: -187.28018 | K60: 6590.9195 | L60: 6635.5497 | M60: 70.975111 | N60: 101.43838 | O60: 25028.623 | P60: 85.611542 | Q60: =AVERAGE(Data!L177:L179) -> 62.268899 | R60: =AVERAGE(Data!M177:M179) -> 108.48287 | S60: =Q60/R60 -> 0.57399754 | T60: 24463512 | U60: =AB60+AE60+AG60 -> 8299.173 | V60: =AC60+AF60+AH60 -> 7999.6162 | W60: =U60/V60 -> 1.0374464 | X60: 7002.0905 | Y60: 6627.4795 | Z60: 564.56102 | AA60: 845.18448 | AB60: =X60+Z60 -> 7566.6515 | AC60: =Y60+AA60 -> 7472.664 | AD60: =AB60/AC60 -> 1.0125775 | AE60: 31.020962 | AF60: 401.79508 | AG60: 701.50055 | AH60: 125.15717 | AI60: 26.436 | AJ60: 2.7 | AK60: 10484.149 | AL60: 3816.0941 | AM60: 6668.0544 | AN60: 3941.1838 | AQ60: =AG60-AH60 -> 576.34338
A61: 41883 | B61: 99.782648 | C61: 237.4447 | D61: =SUM(Data!C180:C182) -> 714.133 | E61: =SUM(Data!D180:D182) -> 11465.028 | F61: =SUM(Data!E180:E182) -> 10107.948 | G61: =E61/F61 -> 1.1342587 | H61: =E61/O61 -> 0.4412263 | I61: 10352.404 | J61: -1680.3627 | K61: 6489.104 | L61: 6533.0023 | M61: -36.930715 | N61: 95.079707 | O61: 25984.462 | P61: 86.547627 | Q61: =AVERAGE(Data!L180:L182) -> 62.770222 | R61: =AVERAGE(Data!M180:M182) -> 108.60727 | S61: =Q61/R61 -> 0.57795597 | T61: 25293840 | U61: =AB61+AE61+AG61 -> 8057.0837 | V61: =AC61+AF61+AH61 -> 8137.1832 | W61: =U61/V61 -> 0.99015636 | X61: 6748.5614 | Y61: 6724.0704 | Z61: 597.42469 | AA61: 883.45297 | AB61: =X61+Z61 -> 7345.986 | AC61: =Y61+AA61 -> 7607.5234 | AD61: =AB61/AC61 -> 0.96562122 | AE61: 34.415388 | AF61: 331.50973 | AG61: 676.6823 | AH61: 198.15013 | AI61: 18.7252 | AJ61: 2.7 | AK61: 9263.8503 | AL61: 3205.3396 | AM61: 6058.5107 | AN61: 3625.2171 | AQ61: =AG61-AH61 -> 478.53217
A62: 41974 | B62: 100.66683 | C62: 236.88391 | D62: =SUM(Data!C183:C185) -> 708.396 | E62: =SUM(Data!D183:D185) -> 14778.703 | F62: =SUM(Data!E183:E185) -> 10029.943 | G62: =E62/F62 -> 1.4734583 | H62: =E62/O62 -> 0.53187817 | I62: 10330.11 | J62: -2452.2043 | K62: 5844.2515 | L62: 6735.8924 | M62: -1024.0911 | N62: 75.027241 | O62: 27785.88 | P62: 87.314534 | Q62: =AVERAGE(Data!L183:L185) -> 63.29843 | R62: =AVERAGE(Data!M183:M185) -> 107.73477 | S62: =Q62/R62 -> 0.58753945 | T62: 27780832 | U62: =AB62+AE62+AG62 -> 7263.5081 | V62: =AC62+AF62+AH62 -> 8662.3705 | W62: =U62/V62 -> 0.83851275 | X62: 5965.7588 | Y62: 7086.7867 | Z62: 625.84029 | AA62: 904.69979 | AB62: =X62+Z62 -> 6591.599 | AC62: =Y62+AA62 -> 7991.4865 | AD62: =AB62/AC62 -> 0.82482765 | AE62: 25.172571 | AF62: 520.41921 | AG62: 646.73653 | AH62: 150.46483 | AI62: 17.351849 | AJ62: 2.7 | AK62: 9692.9986 | AL62: 3326.0234 | AM62: 6366.9752 | AN62: 3534.7446 | AQ62: =AG62-AH62 -> 496.27169
A63: 42064 | B63: 101.70185 | C63: 235.47183 | D63: =SUM(Data!C186:C188) -> 704.548 | E63: =SUM(Data!D186:D188) -> 9291.276 | F63: =SUM(Data!E186:E188) -> 8756.516 | G63: =E63/F63 -> 1.06107 | H63: =E63/O63 -> 0.40166417 | I63: 9223.7952 | J63: -1487.857 | K63: 4986.8083 | L63: 6073.1301 | M63: -1063.7265 | N63: 50.982295 | O63: 23131.951 | P63: 88.212267 | Q63: =AVERAGE(Data!L186:L188) -> 64.108117 | R63: =AVERAGE(Data!M186:M188) -> 107.14956 | S63: =Q63/R63 -> 0.598305 | T63: 24251725 | U63: =AB63+AE63+AG63 -> 6322.9727 | V63: =AC63+AF63+AH63 -> 7251.3981 | W63: =U63/V63 -> 0.87196602 | X63: 5063.5359 | Y63: 5838.9417 | Z63: 625.40902 | AA63: 871.75561 | AB63: =X63+Z63 -> 5688.9449 | AC63: =Y63+AA63 -> 6710.6973 | AD63: =AB63/AC63 -> 0.84774274 | AE63: 32.406164 | AF63: 411.55307 | AG63: 601.62164 | AH63: 129.14771 | AI63: 24.749 | AJ63: 2.8 | AK63: 8983.3969 | AL63: 2114.0028 | AM63: 6869.3941 | AN63: 3872.6729 | AQ63: =AG63-AH63 -> 472.47393
A64: 42156 | B64: 103.2312 | C64: 236.90169 | D64: =SUM(Data!C189:C191) -> 713.042 | E64: =SUM(Data!D189:D191) -> 10648.087 | F64: =SUM(Data!E189:E191) -> 10226.527 | G64: =E64/F64 -> 1.0412222 | H64: =E64/O64 -> 0.44534307 | I64: 9529.5267 | J64: -1441.328 | K64: 4791.8819 | L64: 5327.7555 | M64: -490.12989 | N64: 55.972265 | O64: 23909.852 | P64: 89.538771 | Q64: =AVERAGE(Data!L189:L191) -> 65.119768 | R64: =AVERAGE(Data!M189:M191) -> 108.44135 | S64: =Q64/R64 -> 0.6005068 | T64: 24364088 | U64: =AB64+AE64+AG64 -> 6372.351 | V64: =AC64+AF64+AH64 -> 6656.8784 | W64: =U64/V64 -> 0.95725814 | X64: 5116.6058 | Y64: 5309.1528 | Z64: 561.28592 | AA64: 772.85435 | AB64: =X64+Z64 -> 5677.8917 | AC64: =Y64+AA64 -> 6082.0072 | AD64: =AB64/AC64 -> 0.93355558 | AE64: 35.362588 | AF64: 446.00894 | AG64: 659.0967 | AH64: 128.86225 | AI64: 25.313 | AJ64: 2.8 | AK64: 10026.374 | AL64: 2491.3065 | AM64: 7535.0676 | AN64: 4386.7359 | AQ64: =AG64-AH64 -> 530.23445
A65: 42248 | B65: 103.82077 | C65: 237.75806 | D65: =SUM(Data!C192:C194) -> 714.915 | E65: =SUM(Data!D192:D194) -> 10220.551 | F65: =SUM(Data!E192:E194) -> 9657.961 | G65: =E65/F65 -> 1.0582514 | H65: =E65/O65 -> 0.42680987 | I65: 9489.1794 | J65: -825.12365 | K65: 4431.6907 | L65: 4831.7227 | M65: -352.53235 | N65: 44.21378 | O65: 23946.379 | P65: 90.050141 | Q65: =AVERAGE(Data!L192:L194) -> 65.33992 | R65: =AVERAGE(Data!M192:M194) -> 108.7262 | S65: =Q65/R65 -> 0.60095837 | T65: 25156152 | U65: =AB65+AE65+AG65 -> 5943.3813 | V65: =AC65+AF65+AH65 -> 6456.9445 | W65: =U65/V65 -> 0.92046344 | X65: 4614.1549 | Y65: 4977.2862 | Z65: 617.47523 | AA65: 760.83005 | AB65: =X65+Z65 -> 5231.6302 | AC65: =Y65+AA65 -> 5738.1163 | AD65: =AB65/AC65 -> 0.91173303 | AE65: 32.648829 | AF65: 482.90363 | AG65: 679.10233 | AH65: 235.92455 | AI65: 21.7222 | AJ65: 2.8 | AK65: 9283.4268 | AL65: 2198.5498 | AM65: 7084.877 | AN65: 4431.7914 | AQ65: =AG65-AH65 -> 443.17778
A66: 42339 | B66: 104.11916 | C66: 237.93382 | D66: =SUM(Data!C195:C197) -> 711.699 | E66: =SUM(Data!D195:D197) -> 12760.991 | F66: =SUM(Data!E195:E197) -> 8339.911 | G66: =E66/F66 -> 1.5301112 | H66: =E66/O66 -> 0.48666369 | I66: 8659.4544 | J66: -2229.5254 | K66: 4110.8332 | L66: 4271.3261 | M66: -174.3863 | N66: 43.537558 | O66: 26221.375 | P66: 90.308948 | Q66: =AVERAGE(Data!L195:L197) -> 65.462921 | R66: =AVERAGE(Data!M195:M197) -> 108.2371 | S66: =Q66/R66 -> 0.60481036 | T66: 27298710 | U66: =AB66+AE66+AG66 -> 5585.3363 | V66: =AC66+AF66+AH66 -> 6079.9072 | W66: =U66/V66 -> 0.91865485 | X66: 4254.4511 | Y66: 4573.161 | Z66: 587.14258 | AA66: 791.11897 | AB66: =X66+Z66 -> 4841.5937 | AC66: =Y66+AA66 -> 5364.2799 | AD66: =AB66/AC66 -> 0.90256171 | AE66: 39.914583 | AF66: 528.43806 | AG66: 703.82799 | AH66: 187.18921 | AI66: 26.928076 | AJ66: 275.32627 | AK66: 7899.0238 | AL66: 1824.0724 | AM66: 6074.9514 | AN66: 3269.6811 | AQ66: =AG66-AH66 -> 516.63878
A67: 42430 | B67: 104.44574 | C67: 237.98369 | D67: =SUM(Data!C198:C200) -> 712.159 | E67: =SUM(Data!D198:D200) -> 9452.97 | F67: =SUM(Data!E198:E200) -> 8570.03 | G67: =E67/F67 -> 1.1030265 | H67: =E67/O67 -> 0.42657181 | I67: 8852.6439 | J67: -1789.3019 | K67: 3728.7578 | L67: 3853.1019 | M67: -203.59392 | N67: 35.81535 | O67: 22160.325 | P67: 90.592213 | Q67: =AVERAGE(Data!L198:L200) -> 65.820016 | R67: =AVERAGE(Data!M198:M200) -> 108.30706 | S67: =Q67/R67 -> 0.60771676 | T67: 23282572 | U67: =AB67+AE67+AG67 -> 5196.6852 | V67: =AC67+AF67+AH67 -> 5274.7213 | W67: =U67/V67 -> 0.98520563 | X67: 3783.364 | Y67: 3765.7231 | Z67: 668.75839 | AA67: 849.68375 | AB67: =X67+Z67 -> 4452.1224 | AC67: =Y67+AA67 -> 4615.4069 | AD67: =AB67/AC67 -> 0.96462188 | AE67: 38.933813 | AF67: 505.52579 | AG67: 705.62891 | AH67: 153.78868 | AI67: 21.929 | AJ67: 553.43553 | AK67: 7711.2326 | AL67: 1453.5799 | AM67: 6257.6527 | AN67: 3308.2266 | AQ67: =AG67-AH67 -> 551.84023
A68: 42522 | B68: 104.94936 | C68: 239.41061 | D68: =SUM(Data!C201:C203) -> 720.508 | E68: =SUM(Data!D201:D203) -> 9671.865 | F68: =SUM(Data!E201:E203) -> 8721.015 | G68: =E68/F68 -> 1.1090297 | H68: =E68/O68 -> 0.41098829 | I68: 8096.5039 | J68: -1939.2515 | K68: 4171.6148 | L68: 3611.4192 | M68: 563.49748 | N68: 43.458137 | O68: 23533.189 | P68: 91.029035 | Q68: =AVERAGE(Data!L201:L203) -> 66.205573 | R68: =AVERAGE(Data!M201:M203) -> 109.5768 | S68: =Q68/R68 -> 0.60419335 | T68: 24272826 | U68: =AB68+AE68+AG68 -> 5946.365 | V68: =AC68+AF68+AH68 -> 5098.0065 | W68: =U68/V68 -> 1.1664098 | X68: 4457.287 | Y68: 3621.7851 | Z68: 618.71834 | AA68: 843.98144 | AB68: =X68+Z68 -> 5076.0053 | AC68: =Y68+AA68 -> 4465.7665 | AD68: =AB68/AC68 -> 1.1366482 | AE68: 39.276051 | AF68: 490.17417 | AG68: 831.08364 | AH68: 142.06585 | AI68: 152.91386 | AJ68: 333.92704 | AK68: 8255.9119 | AL68: 1748.7335 | AM68: 6507.1784 | AN68: 3787.5465 | AQ68: =AG68-AH68 -> 689.01779
A69: 42614 | B69: 105.27788 | C69: 240.4946 | D69: =SUM(Data!C204:C206) -> 722.905 | E69: =SUM(Data!D204:D206) -> 10318.218 | F69: =SUM(Data!E204:E206) -> 8572.258 | G69: =E69/F69 -> 1.2036756 | H69: =E69/O69 -> 0.42880986 | I69: 8587.7231 | J69: -1986.263 | K69: 4243.6504 | L69: 3868.3157 | M69: 388.07014 | N69: 43.268646 | O69: 24062.455 | P69: 91.313981 | Q69: =AVERAGE(Data!L204:L206) -> 66.275805 | R69: =AVERAGE(Data!M204:M206) -> 109.94134 | S69: =Q69/R69 -> 0.60282878 | T69: 24617173 | U69: =AB69+AE69+AG69 -> 5913.5155 | V69: =AC69+AF69+AH69 -> 5790.2533 | W69: =U69/V69 -> 1.0212879 | X69: 4396.5644 | Y69: 4029.9731 | Z69: 680.81003 | AA69: 961.25502 | AB69: =X69+Z69 -> 5077.3744 | AC69: =Y69+AA69 -> 4991.2281 | AD69: =AB69/AC69 -> 1.0172595 | AE69: 42.669911 | AF69: 477.8521 | AG69: 793.4712 | AH69: 321.17306 | AI69: 171.08323 | AJ69: 2.8 | AK69: 8317.3043 | AL69: 1973.0725 | AM69: 6344.2318 | AN69: 3766.3914 | AQ69: =AG69-AH69 -> 472.29814
A70: 42705 | B70: 105.33936 | C70: 242.15002 | D70: =SUM(Data!C207:C209) -> 724.514 | E70: =SUM(Data!D207:D209) -> 13736.147 | F70: =SUM(Data!E207:E209) -> 10002.347 | G70: =E70/F70 -> 1.3732924 | H70: =E70/O70 -> 0.4920623 | I70: 10378.258 | J70: -1646.6993 | K70: 4632.6241 | L70: 4227.4491 | M70: 415.88418 | N70: 50.271773 | O70: 27915.463 | P70: 91.367301 | Q70: =AVERAGE(Data!L207:L209) -> 66.223351 | R70: =AVERAGE(Data!M207:M209) -> 110.18604 | S70: =Q70/R70 -> 0.60101397 | T70: 28202783 | U70: =AB70+AE70+AG70 -> 6335.7558 | V70: =AC70+AF70+AH70 -> 6136.2889 | W70: =U70/V70 -> 1.0325061 | X70: 4776.1601 | Y70: 4443.0825 | Z70: 707.23333 | AA70: 998.50679 | AB70: =X70+Z70 -> 5483.3934 | AC70: =Y70+AA70 -> 5441.5892 | AD70: =AB70/AC70 -> 1.0076823 | AE70: 42.208653 | AF70: 504.42872 | AG70: 810.15374 | AH70: 190.2709 | AI70: 73.646696 | AJ70: 2.8 | AK70: 8785.4833 | AL70: 2161.3367 | AM70: 6624.1466 | AN70: 3391.2016 | AQ70: =AG70-AH70 -> 619.88284
A71: 42795 | B71: 105.44005 | C71: 243.9455 | D71: =SUM(Data!C210:C212) -> 730.243 | E71: =SUM(Data!D210:D212) -> 9546.054 | F71: =SUM(Data!E210:E212) -> 8988.104 | G71: =E71/F71 -> 1.0620765 | H71: =E71/O71 -> 0.38637932 | I71: 9340.9688 | J71: -1454.3896 | K71: 4845.2769 | L71: 4423.2318 | M71: 382.87669 | N71: 53.978018 | O71: 24706.431 | P71: 91.454641 | Q71: =AVERAGE(Data!L210:L212) -> 66.437635 | R71: =AVERAGE(Data!M210:M212) -> 111.05732 | S71: =Q71/R71 -> 0.59822831 | T71: 24966378 | U71: =AB71+AE71+AG71 -> 6319.0521 | V71: =AC71+AF71+AH71 -> 5930.2255 | W71: =U71/V71 -> 1.0655669 | X71: 4831.5961 | Y71: 4316.9043 | Z71: 701.20072 | AA71: 827.27907 | AB71: =X71+Z71 -> 5532.7968 | AC71: =Y71+AA71 -> 5144.1834 | AD71: =AB71/AC71 -> 1.0755443 | AE71: 44.364707 | AF71: 642.19723 | AG71: 741.89054 | AH71: 143.84488 | AI71: 21.542 | AJ71: 2.8 | AK71: 8739.9401 | AL71: 2308.1094 | AM71: 6431.8307 | AN71: 3483.4065 | AQ71: =AG71-AH71 -> 598.04566
A72: 42887 | B72: 105.76833 | C72: 244.04505 | D72: =SUM(Data!C213:C215) -> 734.212 | E72: =SUM(Data!D213:D215) -> 9934.307 | F72: =SUM(Data!E213:E215) -> 9507.257 | G72: =E72/F72 -> 1.0449183 | H72: =E72/O72 -> 0.38712027 | I72: 8853.6033 | J72: -1392.4094 | K72: 4528.4935 | L72: 4611.5545 | M72: -60.571981 | N72: 46.450963 | O72: 25662.069 | P72: 91.739376 | Q72: =AVERAGE(Data!L213:L215) -> 66.723573 | R72: =AVERAGE(Data!M213:M215) -> 111.66094 | S72: =Q72/R72 -> 0.59755517 | T72: 26282122 | U72: =AB72+AE72+AG72 -> 6349.6255 | V72: =AC72+AF72+AH72 -> 6249.1116 | W72: =U72/V72 -> 1.0160845 | X72: 4776.6485 | Y72: 4624.3469 | Z72: 710.96943 | AA72: 882.01295 | AB72: =X72+Z72 -> 5487.618 | AC72: =Y72+AA72 -> 5506.3599 | AD72: =AB72/AC72 -> 0.99659631 | AE72: 43.550737 | AF72: 595.48071 | AG72: 818.45684 | AH72: 147.27095 | AI72: 25.316 | AJ72: 2.8 | AK72: 9203.8321 | AL72: 2219.4239 | AM72: 6984.4082 | AN72: 3949.5566 | AQ72: =AG72-AH72 -> 671.18589
A73: 42979 | B73: 105.39144 | C73: 245.27853 | D73: =SUM(Data!C216:C218) -> 737.124 | E73: =SUM(Data!D216:D218) -> 9601.519 | F73: =SUM(Data!E216:E218) -> 8849.389 | G73: =E73/F73 -> 1.0849923 | H73: =E73/O73 -> 0.37806107 | I73: 8909.4328 | J73: -902.32263 | K73: 4649.7718 | L73: 4921.9515 | M73: -292.56023 | N73: 47.004839 | O73: 25396.741 | P73: 91.412481 | Q73: =AVERAGE(Data!L216:L218) -> 66.35454 | R73: =AVERAGE(Data!M216:M218) -> 112.10381 | S73: =Q73/R73 -> 0.59190265 | T73: 26026697 | U73: =AB73+AE73+AG73 -> 6386.0095 | V73: =AC73+AF73+AH73 -> 6820.8172 | W73: =U73/V73 -> 0.93625284 | X73: 4731.65 | Y73: 5045.2835 | Z73: 748.00319 | AA73: 943.56708 | AB73: =X73+Z73 -> 5479.6532 | AC73: =Y73+AA73 -> 5988.8506 | AD73: =AB73/AC73 -> 0.91497577 | AE73: 44.534013 | AF73: 635.43606 | AG73: 861.82228 | AH73: 196.53052 | AI73: 61.940725 | AJ73: 2.8 | AK73: 9000.4366 | AL73: 2291.3045 | AM73: 6709.132 | AN73: 3506.6451 | AQ73: =AG73-AH73 -> 665.29176
A74: 43070 | B74: 105.16097 | C74: 247.21681 | D74: =SUM(Data!C219:C221) -> 739.856 | E74: =SUM(Data!D219:D221) -> 13302.514 | F74: =SUM(Data!E219:E221) -> 10386.654 | G74: =E74/F74 -> 1.2807314 | H74: =E74/O74 -> 0.46346598 | I74: 10772.685 | J74: -957.80443 | K74: 5105.2969 | L74: 5084.3471 | M74: 10.123868 | N74: 56.568162 | O74: 28702.245 | P74: 91.212577 | Q74: =AVERAGE(Data!L219:L221) -> 66.112378 | R74: =AVERAGE(Data!M219:M221) -> 112.5193 | S74: =Q74/R74 -> 0.58756481 | T74: 29092967 | U74: =AB74+AE74+AG74 -> 6980.5388 | V74: =AC74+AF74+AH74 -> 7219.3623 | W74: =U74/V74 -> 0.96691902 | X74: 5209.1744 | Y74: 5308.6563 | Z74: 821.07154 | AA74: 1073.76 | AB74: =X74+Z74 -> 6030.2459 | AC74: =Y74+AA74 -> 6382.4163 | AD74: =AB74/AC74 -> 0.94482177 | AE74: 52.582071 | AF74: 631.64999 | AG74: 897.7108 | AH74: 205.29599 | AI74: 27.582875 | AJ74: 2.8 | AK74: 9345.7601 | AL74: 2842.9896 | AM74: 6502.7705 | AN74: 3414.2291 | AQ74: =AG74-AH74 -> 692.4148
A75: 43160 | B75: 105.29719 | C75: 249.28262 | D75: =SUM(Data!C222:C224) -> 746.412 | E75: =SUM(Data!D222:D224) -> 9376.631 | F75: =SUM(Data!E222:E224) -> 9236.901 | G75: =E75/F75 -> 1.0151274 | H75: =E75/O75 -> 0.36812358 | I75: 9614.1673 | J75: -1032.8459 | K75: 5325.6169 | L75: 5236.4948 | M75: 93.118595 | N75: 64.078803 | O75: 25471.422 | P75: 91.330727 | Q75: =AVERAGE(Data!L222:L224) -> 66.338728 | R75: =AVERAGE(Data!M222:M224) -> 113.51635 | S75: =Q75/R75 -> 0.584398 | T75: 25251451 | U75: =AB75+AE75+AG75 -> 6972.6098 | V75: =AC75+AF75+AH75 -> 6989.463 | W75: =U75/V75 -> 0.99758877 | X75: 5320.0389 | Y75: 5068.9235 | Z75: 778.0337 | AA75: 889.6462 | AB75: =X75+Z75 -> 6098.0726 | AC75: =Y75+AA75 -> 5958.5697 | AD75: =AB75/AC75 -> 1.0234121 | AE75: 59.677742 | AF75: 695.04375 | AG75: 814.85948 | AH75: 335.84957 | AI75: 21.918 | AJ75: 2.8 | AK75: 9452.273 | AL75: 2834.4895 | AM75: 6617.7835 | AN75: 3539.4024 | AQ75: =AG75-AH75 -> 479.00992
A76: 43252 | B76: 104.88569 | C76: 250.74785 | D76: =SUM(Data!C225:C227) -> 754.123 | E76: =SUM(Data!D225:D227) -> 10455.525 | F76: =SUM(Data!E225:E227) -> 10509.415 | G76: =E76/F76 -> 0.99487222 | H76: =E76/O76 -> 0.39749168 | I76: 9820.4175 | J76: -872.82189 | K76: 5386.6537 | L76: 5558.5971 | M76: -122.96783 | N76: 66.656089 | O76: 26303.758 | P76: 90.973806 | Q76: =AVERAGE(Data!L225:L227) -> 66.167289 | R76: =AVERAGE(Data!M225:M227) -> 114.68906 | S76: =Q76/R76 -> 0.57692764 | T76: 26416799 | U76: =AB76+AE76+AG76 -> 7385.9379 | V76: =AC76+AF76+AH76 -> 7486.4389 | W76: =U76/V76 -> 0.98657559 | X76: 5656.7648 | Y76: 5572.3758 | Z76: 783.69727 | AA76: 882.65419 | AB76: =X76+Z76 -> 6440.4621 | AC76: =Y76+AA76 -> 6455.0299 | AD76: =AB76/AC76 -> 0.99774318 | AE76: 61.138069 | AF76: 763.95194 | AG76: 884.33777 | AH76: 267.45705 | AI76: 25.345 | AJ76: 264.8309 | AK76: 10529.814 | AL76: 3074.0987 | AM76: 7455.7155 | AN76: 4017.2892 | AQ76: =AG76-AH76 -> 616.88072
A77: 43344 | B77: 105.15351 | C77: 251.76403 | D77: =SUM(Data!C228:C230) -> 756.591 | E77: =SUM(Data!D228:D230) -> 10842.241 | F77: =SUM(Data!E228:E230) -> 10080.671 | G77: =E77/F77 -> 1.0755476 | H77: =E77/O77 -> 0.40539932 | I77: 10167.792 | J77: -867.04175 | K77: 5580.7794 | L77: 5647.8646 | M77: -102.08177 | N77: 68.776823 | O77: 26744.596 | P77: 91.206106 | Q77: =AVERAGE(Data!L228:L230) -> 66.20824 | R77: =AVERAGE(Data!M228:M230) -> 115.0644 | S77: =Q77/R77 -> 0.5754016 | T77: 26612319 | U77: =AB77+AE77+AG77 -> 7476.4764 | V77: =AC77+AF77+AH77 -> 7788.6299 | W77: =U77/V77 -> 0.95992189 | X77: 5706.6866 | Y77: 5817.5519 | Z77: 826.99173 | AA77: 1014.2026 | AB77: =X77+Z77 -> 6533.6783 | AC77: =Y77+AA77 -> 6831.7545 | AD77: =AB77/AC77 -> 0.95636901 | AE77: 59.415948 | AF77: 765.78931 | AG77: 883.38214 | AH77: 191.08612 | AI77: 22.624 | AJ77: 2.8 | AK77: 10166.708 | AL77: 3488.1519 | AM77: 6678.5565 | AN77: 3615.805 | AQ77: =AG77-AH77 -> 692.29602
A78: 43435 | B78: 105.47779 | C78: 252.63411 | D78: =SUM(Data!C231:C233) -> 756.156 | E78: =SUM(Data!D231:D233) -> 13388.878 | F78: =SUM(Data!E231:E233) -> 10867.308 | G78: =E78/F78 -> 1.2320326 | H78: =E78/O78 -> 0.46233616 | I78: 10960.59 | J78: -625.73563 | K78: 5334.5617 | L78: 5674.6856 | M78: -360.90028 | N78: 60.110765 | O78: 28959.184 | P78: 91.487371 | Q78: =AVERAGE(Data!L231:L233) -> 66.319162 | R78: =AVERAGE(Data!M231:M233) -> 114.99824 | S78: =Q78/R78 -> 0.57669717 | T78: 29198392 | U78: =AB78+AE78+AG78 -> 7295.6114 | V78: =AC78+AF78+AH78 -> 8178.2291 | W78: =U78/V78 -> 0.89207716 | X78: 5473.6892 | Y78: 5901.5873 | Z78: 860.42067 | AA78: 1149.2063 | AB78: =X78+Z78 -> 6334.1098 | AC78: =Y78+AA78 -> 7050.7936 | AD78: =AB78/AC78 -> 0.89835417 | AE78: 55.610789 | AF78: 842.21984 | AG78: 905.89078 | AH78: 285.21573 | AI78: 28.192004 | AJ78: 2.8 | AK78: 10852.35 | AL78: 3428.2824 | AM78: 7424.0678 | AN78: 4244.957 | AQ78: =AG78-AH78 -> 620.67505
A79: 43525 | B79: 105.5132 | C79: 253.36114 | D79: =SUM(Data!C234:C236) -> 758.69 | E79: =SUM(Data!D234:D236) -> 9547.617 | F79: =SUM(Data!E234:E236) -> 9311.537 | G79: =E79/F79 -> 1.0253535 | H79: =E79/O79 -> 0.37715467 | I79: 9969.6724 | J79: -1148.8538 | K79: 5342.737 | L79: 5522.5965 | M79: -150.88577 | N79: 55.374882 | O79: 25314.858 | P79: 91.518083 | Q79: =AVERAGE(Data!L234:L236) -> 66.466923 | R79: =AVERAGE(Data!M234:M236) -> 115.38362 | S79: =Q79/R79 -> 0.57605163 | T79: 25195116 | U79: =AB79+AE79+AG79 -> 7022.5894 | V79: =AC79+AF79+AH79 -> 7306.4729 | W79: =U79/V79 -> 0.9611463 | X79: 5362.7209 | Y79: 5347.8812 | Z79: 763.8061 | AA79: 950.39133 | AB79: =X79+Z79 -> 6126.527 | AC79: =Y79+AA79 -> 6298.2725 | AD79: =AB79/AC79 -> 0.97273133 | AE79: 54.022659 | AF79: 807.64832 | AG79: 842.03979 | AH79: 200.5521 | AI79: 19.7 | AJ79: 2.8 | AK79: 9487.2672 | AL79: 2866.5051 | AM79: 6620.7621 | AN79: 3489.7361 | AQ79: =AG79-AH79 -> 641.48769
A80: 43617 | B80: 105.31132 | C80: 255.33189 | D80: =SUM(Data!C237:C239) -> 767.783 | E80: =SUM(Data!D237:D239) -> 10569.675 | F80: =SUM(Data!E237:E239) -> 10721.285 | G80: =E80/F80 -> 0.98585897 | H80: =E80/O80 -> 0.39878084 | I80: 10005.114 | J80: -781.21996 | K80: 5623.1682 | L80: 5631.2445 | M80: 24.575602 | N80: 58.765087 | O80: 26504.972 | P80: 91.342983 | Q80: =AVERAGE(Data!L237:L239) -> 66.426302 | R80: =AVERAGE(Data!M237:M239) -> 116.76651 | S80: =Q80/R80 -> 0.56888146 | T80: 26520566 | U80: =AB80+AE80+AG80 -> 7658.3968 | V80: =AC80+AF80+AH80 -> 7633.6813 | W80: =U80/V80 -> 1.0032377 | X80: 5877.4057 | Y80: 5662.9712 | Z80: 810.66011 | AA80: 999.61727 | AB80: =X80+Z80 -> 6688.0658 | AC80: =Y80+AA80 -> 6662.5884 | AD80: =AB80/AC80 -> 1.003824 | AE80: 50.074935 | AF80: 721.2892 | AG80: 920.25599 | AH80: 249.80362 | AI80: 24.423 | AJ80: 2.8 | AK80: 10609.719 | AL80: 3164.8242 | AM80: 7444.8952 | AN80: 4230.7736 | AQ80: =AG80-AH80 -> 670.45237
A81: 43709 | B81: 105.47583 | C81: 256.15358 | D81: =SUM(Data!C240:C242) -> 769.888 | E81: =SUM(Data!D240:D242) -> 10542.904 | F81: =SUM(Data!E240:E242) -> 9741.384 | G81: =E81/F81 -> 1.0822799 | H81: =E81/O81 -> 0.3966247 | I81: 9552.2065 | J81: -835.11982 | K81: 5705.6482 | L81: 5286.7065 | M81: 387.90603 | N81: 55.636824 | O81: 26581.562 | P81: 91.48567 | Q81: =AVERAGE(Data!L240:L242) -> 66.42138 | R81: =AVERAGE(Data!M240:M242) -> 117.08664 | S81: =Q81/R81 -> 0.56728401 | T81: 26709303 | U81: =AB81+AE81+AG81 -> 7641.733 | V81: =AC81+AF81+AH81 -> 7650.4735 | W81: =U81/V81 -> 0.99885751 | X81: 5801.2345 | Y81: 5464.1733 | Z81: 838.75096 | AA81: 1093.9901 | AB81: =X81+Z81 -> 6639.9855 | AC81: =Y81+AA81 -> 6558.1634 | AD81: =AB81/AC81 -> 1.0124764 | AE81: 46.810207 | AF81: 830.11503 | AG81: 954.93728 | AH81: 262.19507 | AI81: 22.85 | AJ81: 2.8 | AK81: 9850.4615 | AL81: 3348.7602 | AM81: 6501.7013 | AN81: 3494.139 | AQ81: =AG81-AH81 -> 692.74221
A82: 43800 | B82: 105.62058 | C82: 257.77668 | D82: =SUM(Data!C243:C245) -> 771.528 | E82: =SUM(Data!D243:D245) -> 12182.21 | F82: =SUM(Data!E243:E245) -> 9616.38 | G82: =E82/F82 -> 1.2668187 | H82: =E82/O82 -> 0.41727846 | I82: 10065.055 | J82: -708.51587 | K82: 5653.6395 | L82: 5058.6695 | M82: 580.0704 | N82: 58.590314 | O82: 29194.438 | P82: 91.611228 | Q82: =AVERAGE(Data!L243:L245) -> 66.423836 | R82: =AVERAGE(Data!M243:M245) -> 117.33606 | S82: =Q82/R82 -> 0.56609909 | T82: 29231751 | U82: =AB82+AE82+AG82 -> 7579.033 | V82: =AC82+AF82+AH82 -> 7467.0294 | W82: =U82/V82 -> 1.0149997 | X82: 5732.4883 | Y82: 5271.5944 | Z82: 838.72482 | AA82: 1098.8635 | AB82: =X82+Z82 -> 6571.2131 | AC82: =Y82+AA82 -> 6370.4579 | AD82: =AB82/AC82 -> 1.0315135 | AE82: 44.132977 | AF82: 866.93233 | AG82: 963.68685 | AH82: 229.63917 | AI82: 27.822124 | AJ82: 2.8 | AK82: 9110.0697 | AL82: 2871.4647 | AM82: 6238.605 | AN82: 3270.9901 | AQ82: =AG82-AH82 -> 734.04768
A83: 43891 | B83: 105.41835 | C83: 258.76857 | D83: =SUM(Data!C246:C248) -> 774.764 | E83: =SUM(Data!D246:D248) -> 9428.373 | F83: =SUM(Data!E246:E248) -> 10089.973 | G83: =E83/F83 -> 0.93442995 | I83: 10447.036 | J83: -266.49226 | K83: 5574.9643 | L83: 4847.932 | M83: 619.11141 | N83: 46.167611 | P83: 91.435815 | Q83: =AVERAGE(Data!L246:L248) -> 66.389371 | R83: =AVERAGE(Data!M246:M248) -> 117.8282 | S83: =Q83/R83 -> 0.56344213 | T83: 25297756 | U83: =AB83+AE83+AG83 -> 7143.4849 | V83: =AC83+AF83+AH83 -> 6791.0466 | W83: =U83/V83 -> 1.0518975 | X83: 5537.2513 | Y83: 4754.5528 | Z83: 758.4949 | AA83: 968.49019 | AB83: =X83+Z83 -> 6295.7461 | AC83: =Y83+AA83 -> 5723.043 | AD83: =AB83/AC83 -> 1.1000697 | AE83: 28.73777 | AF83: 885.02718 | AG83: 819.00097 | AH83: 182.97646 | AI83: 20.21832 | AJ83: 2.8 | AK83: 9742.0753 | AL83: 2749.1028 | AM83: 6992.9725 | AN83: 3517.2909 | AQ83: =AG83-AH83 -> 636.02451
A84: 43983 | B84: 106.01962 | C84: 256.22172 | D84: =SUM(Data!C249:C251) -> 770.58 | E84: =SUM(Data!D249:D251) -> 8567.676 | F84: =SUM(Data!E249:E251) -> 6470.296 | G84: =E84/F84 -> 1.3241552 | I84: 6032.0508 | J84: -3026.3229 | K84: 4087.8691 | L84: 3522.9298 | M84: 523.88724 | N84: 26.564467 | P84: 91.957339 | Q84: =AVERAGE(Data!L249:L251) -> 66.854034 | R84: =AVERAGE(Data!M249:M251) -> 117.19188 | S84: =Q84/R84 -> 0.57046642 | T84: 21335355 | U84: =AB84+AE84+AG84 -> 5308.023 | V84: =AC84+AF84+AH84 -> 5028.7919 | W84: =U84/V84 -> 1.0555265 | X84: 4224.5612 | Y84: 3528.9226 | Z84: 247.73069 | AA84: 478.33563 | AB84: =X84+Z84 -> 4472.2919 | AC84: =Y84+AA84 -> 4007.2583 | AD84: =AB84/AC84 -> 1.1160478 | AE84: 18.403946 | AF84: 889.28993 | AG84: 817.32715 | AH84: 132.24371 | AI84: 36.422136 | AJ84: 2.8 | AK84: 6224.9715 | AL84: 990.34233 | AM84: 5234.6292 | AN84: 2831.7977 | AQ84: =AG84-AH84 -> 685.08344
A85: 44075 | B85: 104.6605 | C85: 259.22659 | D85: =SUM(Data!C252:C254) -> 779.299 | E85: =SUM(Data!D252:D254) -> 9025.835 | F85: =SUM(Data!E252:E254) -> 7629.595 | G85: =E85/F85 -> 1.1830032 | I85: 7532.2591 | J85: -1406.8571 | K85: 5186.6451 | L85: 3942.4479 | M85: 1279.8315 | N85: 40.393708 | P85: 90.778489 | Q85: =AVERAGE(Data!L252:L254) -> 65.934644 | R85: =AVERAGE(Data!M252:M254) -> 118.51789 | S85: =Q85/R85 -> 0.5563265 | T85: 23764365 | U85: =AB85+AE85+AG85 -> 6629.9071 | V85: =AC85+AF85+AH85 -> 5983.8171 | W85: =U85/V85 -> 1.1079729 | X85: 5187.7216 | Y85: 4081.1073 | Z85: 333.38804 | AA85: 537.85743 | AB85: =X85+Z85 -> 5521.1096 | AC85: =Y85+AA85 -> 4618.9648 | AD85: =AB85/AC85 -> 1.1953132 | AE85: 16.760457 | AF85: 1125.3891 | AG85: 1092.037 | AH85: 239.46325 | AI85: 222.17673 | AJ85: 2.8 | AK85: 7653.5111 | AL85: 1824.2909 | AM85: 5829.2203 | AN85: 3063.8842 | AQ85: =AG85-AH85 -> 852.57376
A86: 44166 | B86: 104.38348 | C86: 261.03714 | D86: =SUM(Data!C255:C257) -> 781.091 | E86: =SUM(Data!D255:D257) -> 11601.031 | F86: =SUM(Data!E255:E257) -> 8902.201 | G86: =E86/F86 -> 1.3031644 | I86: 9114.3888 | J86: -840.98243 | K86: 5574.6547 | L86: 4567.3888 | M86: 1033.5762 | N86: 44.188584 | P86: 90.53821 | Q86: =AVERAGE(Data!L255:L257) -> 65.659877 | R86: =AVERAGE(Data!M255:M257) -> 118.79043 | S86: =Q86/R86 -> 0.55273712 | T86: 27306291 | U86: =AB86+AE86+AG86 -> 7218.4048 | V86: =AC86+AF86+AH86 -> 6288.2069 | W86: =U86/V86 -> 1.1479274 | X86: 5619.9947 | Y86: 4727.2715 | Z86: 464.20156 | AA86: 797.38576 | AB86: =X86+Z86 -> 6084.1963 | AC86: =Y86+AA86 -> 5524.6572 | AD86: =AB86/AC86 -> 1.1012803 | AE86: 22.031504 | AF86: 470.63042 | AG86: 1112.177 | AH86: 292.9193 | AI86: 38.492275 | AJ86: 2.8 | AK86: 7910.0999 | AL86: 2357.7934 | AM86: 5552.3065 | AN86: 2953.0258 | AQ86: =AG86-AH86 -> 819.25772
A87: 44256 | B87: 104.51972 | C87: 263.72122 | D87: =SUM(Data!C258:C260) -> 789.473 | E87: =SUM(Data!D258:D260) -> 8670.4716 | F87: =SUM(Data!E258:E260) -> 5411.218 | G87: =E87/F87 -> 1.6023142 | I87: 6078.5322 | J87: -489.62731 | K87: 5963.7305 | L87: 5307.192 | M87: 684.43708 | N87: 58.123818 | P87: 90.656378 | Q87: =AVERAGE(Data!L258:L260) -> 65.797102 | R87: =AVERAGE(Data!M258:M260) -> 120.06518 | S87: =Q87/R87 -> 0.54801151 | T87: 23965889 | U87: =AB87+AE87+AG87 -> 7360.0609 | V87: =AC87+AF87+AH87 -> 6517.7751 | W87: =U87/V87 -> 1.129229 | X87: 5918.8716 | Y87: 5067.756 | Z87: 388.90763 | AA87: 790.76962 | AB87: =X87+Z87 -> 6307.7793 | AC87: =Y87+AA87 -> 5858.5256 | AD87: =AB87/AC87 -> 1.0766837 | AE87: 21.8188 | AF87: 429.49022 | AG87: 1030.4628 | AH87: 229.75925 | AI87: 20.413803 | AJ87: 2.8 | AK87: 8781.2108 | AL87: 2593.4083 | AM87: 6187.8025 | AN87: 3365.3356 | AQ87: =AG87-AH87 -> 800.70358
A88: 44348 | B88: 104.88721 | C88: 268.60554 | D88: =SUM(Data!C261:C263) -> 807.945 | E88: =SUM(Data!D261:D263) -> 9551.1923 | F88: =SUM(Data!E261:E263) -> 0 | I88: 0 | J88: 0 | K88: 6538.5285 | L88: 5556.3883 | M88: 1003.1302 | N88: 64.499289 | P88: 90.975128 | Q88: =AVERAGE(Data!L261:L263) -> 66.120584 | R88: =AVERAGE(Data!M261:M263) -> 122.87445 | S88: =Q88/R88 -> 0.53811497 | T88: 26091223 | U88: =AB88+AE88+AG88 -> 8476.726 | V88: =AC88+AF88+AH88 -> 7149.3357 | W88: =U88/V88 -> 1.1856662 | X88: 6788.8395 | Y88: 5555.5715 | Z88: 462.67802 | AA88: 907.55776 | AB88: =X88+Z88 -> 7251.5175 | AC88: =Y88+AA88 -> 6463.1293 | AD88: =AB88/AC88 -> 1.1219824 | AE88: 21.347282 | AF88: 434.654 | AG88: 1203.8612 | AH88: 251.55242 | AI88: 32.73044 | AJ88: 2.8 | AK88: 9600.3858 | AL88: 3247.5674 | AM88: 6352.8183 | AN88: 3451.8072 | AQ88: =AG88-AH88 -> 952.30878
A89: 44440 | B89: 105.44545 | C89: 273.01486 | D89: =SUM(Data!C264:C266) -> 820.88 | E89: =SUM(Data!D264:D266) -> 9782.455 | F89: =SUM(Data!E264:E266) -> 0 | I89: 0 | J89: 0 | K89: 6876.1579 | L89: 6298.1116 | M89: 494.28914 | N89: 70.231317 | P89: 91.459325 | Q89: =AVERAGE(Data!L264:L266) -> 66.463702 | R89: =AVERAGE(Data!M264:M266) -> 124.84164 | S89: =Q89/R89 -> 0.53238407 | T89: 26970737 | U89: =AB89+AE89+AG89 -> 8760.7077 | V89: =AC89+AF89+AH89 -> 8394.0315 | W89: =U89/V89 -> 1.043683 | X89: 6897.6976 | Y89: 6567.7722 | Z89: 570.13792 | AA89: 1106.3438 | AB89: =X89+Z89 -> 7467.8355 | AC89: =Y89+AA89 -> 7674.116 | AD89: =AB89/AC89 -> 0.97311996 | AE89: 20.932485 | AF89: 466.22232 | AG89: 1271.9397 | AH89: 253.69311 | AI89: 64.0143 | AJ89: 3.77053 | AK89: 9945.1268 | AL89: 3807.1219 | AM89: 6138.0049 | AN89: 3319.5861 | AQ89: =AG89-AH89 -> 1018.2466
A90: 44531 | B90: 106.18264 | C90: 278.55884 | D90: =SUM(Data!C267:C269) -> 833.339 | E90: =SUM(Data!D267:D269) -> 12240.598 | F90: =SUM(Data!E267:E269) -> 0 | I90: 0 | J90: 0 | K90: 7312.7473 | L90: 6573.7877 | M90: 724.30009 | N90: 79.030567 | P90: 92.098733 | Q90: =AVERAGE(Data!L267:L269) -> 66.809439 | R90: =AVERAGE(Data!M267:M269) -> 126.73644 | S90: =Q90/R90 -> 0.52715255 | T90: 30268882 | U90: =AB90+AE90+AG90 -> 9348.7674 | V90: =AC90+AF90+AH90 -> 8787.3867 | W90: =U90/V90 -> 1.0638848 | X90: 7362.1528 | Y90: 6783.8621 | Z90: 648.00611 | AA90: 1348.0397 | AB90: =X90+Z90 -> 8010.1589 | AC90: =Y90+AA90 -> 8131.9018 | AD90: =AB90/AC90 -> 0.98502898 | AE90: 24.723115 | AF90: 427.96394 | AG90: 1313.8854 | AH90: 227.521 | AI90: 45.774746 | AJ90: 377.17 | AK90: 10135.681 | AL90: 3458.2895 | AM90: 6677.3912 | AN90: 3412.6725 | AQ90: =AG90-AH90 -> 1086.3644
A91: 44621 | B91: 107.32453 | C91: 284.73773 | D91: =SUM(Data!C270:C272) -> 852.368 | E91: =SUM(Data!D270:D272) -> 9658.5421 | F91: =SUM(Data!E270:E272) -> 0 | I91: 0 | J91: 0 | K91: 8219.5865 | L91: 7518.6279 | M91: 797.79131 | N91: 94.883803 | P91: 93.089164 | Q91: =AVERAGE(Data!L270:L272) -> 67.531907 | R91: =AVERAGE(Data!M270:M272) -> 129.63042 | S91: =Q91/R91 -> 0.52095723 | T91: 26469576 | U91: =AB91+AE91+AG91 -> 10026.693 | V91: =AC91+AF91+AH91 -> 9210.2895 | W91: =U91/V91 -> 1.0886404 | X91: 8171.3253 | Y91: 7188.0107 | Z91: 607.50005 | AA91: 1314.6446 | AB91: =X91+Z91 -> 8778.8254 | AC91: =Y91+AA91 -> 8502.6553 | AD91: =AB91/AC91 -> 1.0324805 | AE91: 32.828786 | AF91: 511.80322 | AG91: 1215.0388 | AH91: 195.83099 | AI91: 19.164707 | AJ91: 2.8 | AK91: 10516.096 | AL91: 3529.585 | AM91: 6986.5114 | AN91: 4091.0186 | AQ91: =AG91-AH91 -> 1019.2078
A92: 44713 | B92: 108.60043 | C92: 291.76193 | D92: =SUM(Data!C273:C275) -> 877.716 | E92: =SUM(Data!D273:D275) -> 10732.611 | F92: =SUM(Data!E273:E275) -> 0 | I92: 0 | J92: 0 | K92: 8522.4537 | L92: 7786.5244 | M92: 818.53153 | N92: 106.74142 | P92: 94.195833 | Q92: =AVERAGE(Data!L273:L275) -> 68.436952 | R92: =AVERAGE(Data!M273:M275) -> 133.48542 | S92: =Q92/R92 -> 0.51269235 | T92: 27624458 | U92: =AB92+AE92+AG92 -> 10974.965 | V92: =AC92+AF92+AH92 -> 9760.5162 | W92: =U92/V92 -> 1.1244247 | X92: 8891.8272 | Y92: 7751.8908 | Z92: 702.42506 | AA92: 1317.6857 | AB92: =X92+Z92 -> 9594.2523 | AC92: =Y92+AA92 -> 9069.5765 | AD92: =AB92/AC92 -> 1.0578501 | AE92: 99.007986 | AF92: 450.75944 | AG92: 1281.705 | AH92: 240.18027 | AI92: 21.924597 | AJ92: 2.8 | AK92: 11699.203 | AL92: 4356.8527 | AM92: 7342.3505 | AN92: 3985.3372 | AQ92: =AG92-AH92 -> 1041.5247
A93: 44805 | B93: 109.51461 | C93: 295.75898 | D93: =SUM(Data!C276:C278) -> 889.255 | E93: =SUM(Data!D276:D278) -> 11083.57 | F93: =SUM(Data!E276:E278) -> 0 | I93: 0 | J93: 0 | K93: 8055.8637 | L93: 7600.1331 | M93: 339.01276 | N93: 91.622337 | P93: 94.988756 | Q93: =AVERAGE(Data!L276:L278) -> 69.064587 | R93: =AVERAGE(Data!M276:M278) -> 135.2403 | S93: =Q93/R93 -> 0.51068053 | T93: 28796599 | U93: =AB93+AE93+AG93 -> 10254.569 | V93: =AC93+AF93+AH93 -> 10292.808 | W93: =U93/V93 -> 0.99628486 | X93: 8082.2733 | Y93: 7900.9192 | Z93: 777.11614 | AA93: 1478.4062 | AB93: =X93+Z93 -> 8859.3895 | AC93: =Y93+AA93 -> 9379.3255 | AD93: =AB93/AC93 -> 0.94456574 | AE93: 54.451619 | AF93: 575.87363 | AG93: 1340.7281 | AH93: 337.60928 | AI93: 30.068557 | AJ93: 2.8 | AK93: 11706.166 | AL93: 4734.8264 | AM93: 6971.3399 | AN93: 3525.4644 | AQ93: =AG93-AH93 -> 1003.1188
A94: 44896 | B94: 110.19751 | C94: 298.39294 | D94: =SUM(Data!C279:C281) -> 892.52 | E94: =SUM(Data!D279:D281) -> 13747.24 | F94: =SUM(Data!E279:E281) -> 0 | I94: 0 | J94: 0 | K94: 7839.4489 | L94: 7453.5783 | M94: 364.65626 | N94: 84.397998 | P94: 95.581075 | Q94: =AVERAGE(Data!L279:L281) -> 69.349346 | R94: =AVERAGE(Data!M279:M281) -> 135.73685 | S94: =Q94/R94 -> 0.51091024 | T94: 31043623 | U94: =AB94+AE94+AG94 -> 10178.962 | V94: =AC94+AF94+AH94 -> 10049.445 | W94: =U94/V94 -> 1.0128879 | X94: 7887.8711 | Y94: 7648.2936 | Z94: 822.46909 | AA94: 1451.5653 | AB94: =X94+Z94 -> 8710.3402 | AC94: =Y94+AA94 -> 9099.8589 | AD94: =AB94/AC94 -> 0.95719508 | AE94: 46.530595 | AF94: 573.36697 | AG94: 1422.0908 | AH94: 376.21927 | AI94: 25.579353 | AJ94: 2.8 | AK94: 11277.85 | AL94: 4232.5419 | AM94: 7045.308 | AN94: 3497.9324 | AQ94: =AG94-AH94 -> 1045.8715
A95: 44986 | B95: 110.53267 | C95: 301.24767 | D95: =SUM(Data!C282:C284) -> 901.846 | E95: =SUM(Data!D282:D284) -> 10765.527 | F95: =SUM(Data!E282:E284) -> 0 | I95: 0 | J95: 0 | K95: 7593.5891 | L95: 7377.8742 | M95: 319.45447 | N95: 76.827484 | P95: 95.871781 | Q95: =AVERAGE(Data!L282:L284) -> 69.52732 | R95: =AVERAGE(Data!M282:M284) -> 137.15517 | S95: =Q95/R95 -> 0.50692453 | T95: 27778476 | U95: =AB95+AE95+AG95 -> 9687.8049 | V95: =AC95+AF95+AH95 -> 9295.765 | W95: =U95/V95 -> 1.042174 | X95: 7551.3179 | Y95: 7057.9512 | Z95: 786.527 | AA95: 1224.6336 | AB95: =X95+Z95 -> 8337.8449 | AC95: =Y95+AA95 -> 8282.5848 | AD95: =AB95/AC95 -> 1.0066718 | AE95: 56.002378 | AF95: 740.94896 | AG95: 1293.9577 | AH95: 272.23128 | AI95: 19.355051 | AJ95: 2.8 | AK95: 10918.907 | AL95: 3468.767 | AM95: 7450.1398 | AN95: 3792.2888 | AQ95: =AG95-AH95 -> 1021.7264
A96: 45078 | B96: 110.83555 | C96: 303.30898 | D96: =SUM(Data!C285:C287) -> 912.599 | E96: =SUM(Data!D285:D287) -> 11269.373 | F96: =SUM(Data!E285:E287) -> 0 | I96: 0 | J96: 0 | K96: 7463.5554 | L96: 7093.1545 | M96: 415.58513 | N96: 71.527533 | P96: 96.134488 | Q96: =AVERAGE(Data!L285:L287) -> 69.827053 | R96: =AVERAGE(Data!M285:M287) -> 138.79052 | S96: =Q96/R96 -> 0.50311112 | T96: 29098381 | U96: =AB96+AE96+AG96 -> 10050.375 | V96: =AC96+AF96+AH96 -> 9274.7702 | W96: =U96/V96 -> 1.0836252 | X96: 7769.6157 | Y96: 7046.9436 | Z96: 755.56527 | AA96: 1251.6654 | AB96: =X96+Z96 -> 8525.181 | AC96: =Y96+AA96 -> 8298.609 | AD96: =AB96/AC96 -> 1.0273024 | AE96: 56.728812 | AF96: 700.72364 | AG96: 1468.4653 | AH96: 275.43754 | AI96: 22.483954 | AJ96: 2.8 | AK96: 11471.938 | AL96: 3384.1686 | AM96: 8087.7691 | AN96: 4077.1254 | AQ96: =AG96-AH96 -> 1193.0278
A97: 45170 | B97: 111.97739 | C97: 306.16168 | D97: =SUM(Data!C288:C290) -> 920.506 | E97: =SUM(Data!D288:D290) -> 11824.43 | F97: =SUM(Data!E288:E290) -> 0 | I97: 0 | J97: 0 | K97: 8324.7518 | L97: 7401.5789 | M97: 825.98047 | N97: 82.388887 | P97: 97.124872 | Q97: =AVERAGE(Data!L288:L290) -> 70.644012 | R97: =AVERAGE(Data!M288:M290) -> 139.99303 | S97: =Q97/R97 -> 0.50462519 | T97: 29064059 | U97: =AB97+AE97+AG97 -> 10761.308 | V97: =AC97+AF97+AH97 -> 10206.544 | W97: =U97/V97 -> 1.0543537 | X97: 8370.8417 | Y97: 7641.8164 | Z97: 800.99604 | AA97: 1410.8536 | AB97: =X97+Z97 -> 9171.8378 | AC97: =Y97+AA97 -> 9052.67 | AD97: =AB97/AC97 -> 1.0131638 | AE97: 63.508157 | AF97: 841.65158 | AG97: 1525.9617 | AH97: 312.22263 | AI97: 26.115557 | AJ97: 2.8 | AK97: 10341.32 | AL97: 3693.5596 | AM97: 6647.7605 | AN97: 3229.8809 | AQ97: =AG97-AH97 -> 1213.739
A98: 45261 | B98: 111.95095 | C98: 308.11116 | D98: =SUM(Data!C291:C293) -> 921.468 | E98: =SUM(Data!D291:D293) -> 14024.138 | F98: =SUM(Data!E291:E293) -> 0 | I98: 0 | J98: 0 | K98: 2609.7386 | L98: 7277.9504 | M98: -4664.9205 | N98: 79.858249 | P98: 97.101946 | Q98: =AVERAGE(Data!L291:L293) -> 70.46253 | R98: =AVERAGE(Data!M291:M293) -> 140.13934 | S98: =Q98/R98 -> 0.50280336 | T98: 30676739 | U98: =AB98+AE98+AG98 -> 10343.653 | V98: =AC98+AF98+AH98 -> 9989.7547 | W98: =U98/V98 -> 1.0354261 | X98: 7792.2415 | Y98: 7530.502 | Z98: 845.12492 | AA98: 1398.0582 | AB98: =X98+Z98 -> 8637.3664 | AC98: =Y98+AA98 -> 8928.5603 | AD98: =AB98/AC98 -> 0.96738625 | AE98: 60.272001 | AF98: 753.54553 | AG98: 1646.0147 | AH98: 307.64893 | AI98: 25.157311 | AJ98: 2.8 | AK98: 10874.415 | AL98: 3960.2734 | AM98: 6914.1414 | AN98: 3251.5906 | AQ98: =AG98-AH98 -> 1338.3658
A99: 45352 | D99: =SUM(Data!C294:C296) -> 618.743 | E99: =SUM(Data!D294:D296) -> 3367.0705 | F99: =SUM(Data!E294:E296) -> 0 | Q99: =AVERAGE(Data!L294:L296) -> 70.478497 | R99: =AVERAGE(Data!M294:M296) -> 141.15016 | T99: 28232504
A100: 45444 | T100: 28648035 | AD100: =AVERAGE(AD15:AD82) -> 0.9630669
...

Sheet Data trim_sa
A1: fecha | B1: v_1 | C1: v_2 | D1: v_3 | E1: v_4 | F1: v_5 | G1: v_6 | H1: v_7 | I1: v_8 | J1: v_9 | K1: v_10 | L1: v_11 | M1: v_12 | N1: v_13 | O1: v_14 | P1: v_15 | Q1: v_16 | R1: v_17 | S1: v_18 | T1: v_19 | U1: v_20 | V1: v_21 | W1: v_22 | X1: v_23 | Y1: v_24 | Z1: v_25 | AA1: v_26 | AB1: v_27 | AC1: v_28 | AD1: v_29 | AE1: v_30 | AF1: v_31 | AG1: v_32 | AH1: v_33 | AI1: v_34 | AJ1: v_35 | AK1: v_36 | AL1: v_37 | AM1: v_38 | AO1: gasto_2 | AP1: gasto_3 | AQ1: log1 | AR1: log2
A2: 37316 | B2: 58.202395 | C2: 178.16415 | D2: 1414.1844 | E2: 1548.5792 | F2: 49.457657 | G2: 1129.7825 | H2: 1408.6698 | I2: -248.95186 | J2: 21.502171 | K2: 6336.7849 | L2: 50.482517 | M2: 73.97726 | N2: 45.21796 | O2: 24.750528 | P2: 31.477672 | Q2: 75.211587 | R2: 24.224298 | S2: 28.967689 | T2: 69.689063 | V2: 26.536006 | W2: 73.63796 | X2: 1179.2513 | Y2: 1456.0294 | Z2: 215.34727 | AA2: 379.0215 | AB2: 1393.178 | AC2: 1813.8378 | AD2: 24.61169 | AE2: 302.42962 | AF2: 401.31316 | AG2: 14.023082 | AH2: 7.023 | AI2: 2 | AJ2: 1511.1507 | AK2: 390.52837 | AL2: 1160.9608 | AM2: 713.45522 | AO2: =D2/K2 -> 0.22317065 | AP2: =(1+D2/K2) -> 1.2231706 | AQ2: =LN(AO2) -> -1.4998186 | AR2: =LN(AP2) -> 0.20144638
A3: 37408 | B3: 59.724141 | C3: 179.32914 | D3: 1565.4094 | E3: 1601.0718 | F3: -19.173077 | G3: 1267.9003 | H3: 1653.0197 | I3: -370.96169 | J3: 26.497936 | K3: 6670.1135 | L3: 51.80242 | M3: 74.2356 | N3: 46.723576 | O3: 25.574643 | P3: 32.300679 | Q3: 75.703387 | R3: 25.030891 | S3: 29.725071 | T3: 70.144752 | V3: 26.802516 | W3: 74.18355 | X3: 1297.6771 | Y3: 1644.0435 | Z3: 216.9664 | AA3: 403.59948 | AB3: 1523.5768 | AC3: 2067.6361 | AD3: 23.096082 | AE3: 306.30429 | AF3: 416.38117 | AG3: 14.426365 | AH3: 11.68 | AI3: 2 | AJ3: 1623.2508 | AK3: 337.39943 | AL3: 1233.2325 | AM3: 711.71497 | AO3: =D3/K3 -> 0.23469008 | AP3: =(1+D3/K3) -> 1.2346901 | AQ3: =LN(AO3) -> -1.4494895 | AR3: =LN(AP3) -> 0.21081999
A4: 37500 | B4: 60.818873 | C4: 180.33218 | D4: 1513.0327 | E4: 1585.7014 | F4: 78.904321 | G4: 1295.0109 | H4: 1605.6532 | I4: -348.04417 | J4: 26.953621 | K4: 6961.5879 | L4: 52.751949 | M4: 74.59155 | N4: 48.377983 | O4: 26.480201 | P4: 32.892745 | Q4: 76.126815 | R4: 25.917195 | S4: 30.269926 | T4: 70.53709 | V4: 27.087363 | W4: 74.56645 | X4: 1356.3242 | Y4: 1601.6549 | Z4: 223.14556 | AA4: 415.96034 | AB4: 1578.6512 | AC4: 2009.645 | AD4: 19.198398 | AE4: 359.97354 | AF4: 432.04703 | AG4: 14.72421 | AH4: 7.9061 | AI4: 2 | AJ4: 1591.4063 | AK4: 345.79246 | AL4: 1194.6855 | AM4: 722.11408 | AO4: =D4/K4 -> 0.21734017 | AP4: =(1+D4/K4) -> 1.2173402 | AQ4: =LN(AO4) -> -1.5262916 | AR4: =LN(AP4) -> 0.19666829
A5: 37591 | B5: 61.804461 | C5: 181.65563 | D5: 1657.1315 | E5: 1656.6535 | F5: 94.427915 | G5: 1340.8122 | H5: 1504.7116 | I5: -150.36159 | J5: 29.342274 | K5: 7085.7114 | L5: 53.606809 | M5: 75.0244 | N5: 49.376779 | O5: 27.026902 | P5: 33.425781 | Q5: 76.685508 | R5: 26.452273 | S5: 30.760459 | T5: 71.05476 | V5: 27.229797 | W5: 74.91426 | X5: 1425.8254 | Y5: 1455.0367 | Z5: 228.54611 | AA5: 400.95839 | AB5: 1646.9559 | AC5: 1863.9348 | AD5: 16.271345 | AE5: 368.90923 | AF5: 457.10469 | AG5: 14.648272 | AH5: 8.0124 | AI5: 2 | AJ5: 1629.1947 | AK5: 423.03555 | AL5: 1185.4496 | AM5: 761.00683 | AO5: =D5/K5 -> 0.23386947 | AP5: =(1+D5/K5) -> 1.2338695 | AQ5: =LN(AO5) -> -1.4529922 | AR5: =LN(AP5) -> 0.21015514
A6: 37681 | B6: 63.828736 | C6: 183.32684 | D6: 1522.4655 | E6: 1660.0542 | F6: 129.03939 | G6: 1578.2739 | H6: 1558.141 | I6: 23.470858 | J6: 34.220287 | K6: 7561.4756 | L6: 55.362587 | M6: 75.3912 | N6: 51.79348 | O6: 28.349709 | P6: 34.520572 | Q6: 77.391007 | R6: 27.746955 | S6: 31.767953 | T6: 71.708457 | V6: 27.707482 | W6: 75.48714 | X6: 1631.4501 | Y6: 1614.1472 | Z6: 217.88613 | AA6: 412.94038 | AB6: 1847.2704 | AC6: 2006.5339 | AD6: 15.508245 | AE6: 379.03435 | AF6: 436.56627 | AG6: 0.73162719 | AH6: 38.481306 | AI6: 2.25 | AJ6: 1693.95 | AK6: 547.11031 | AL6: 1246.9423 | AM6: 788.47813 | AO6: =D6/K6 -> 0.20134502 | AP6: =(1+D6/K6) -> 1.201345 | AQ6: =LN(AO6) -> -1.6027353 | AR6: =LN(AP6) -> 0.18344178
A7: 37773 | B7: 64.633307 | C7: 183.12823 | D7: 1582.5311 | E7: 1629.4442 | F7: -22.178987 | G7: 1398.0534 | H7: 1518.0399 | I7: -124.02211 | J7: 29.11772 | K7: 7533.3393 | L7: 56.060442 | M7: 75.65644 | N7: 52.102928 | O7: 28.519089 | P7: 34.95571 | Q7: 77.307161 | R7: 27.912733 | S7: 32.168393 | T7: 71.630767 | V7: 28.702062 | W7: 75.56216 | X7: 1431.2782 | Y7: 1530.5191 | Z7: 216.92626 | AA7: 405.98938 | AB7: 1657.8018 | AC7: 1954.276 | AD7: 14.860808 | AE7: 400.46388 | AF7: 432.55878 | AG7: 1.227534 | AH7: 17.331481 | AI7: 2.25 | AJ7: 1651.7481 | AK7: 319.3399 | AL7: 1254.653 | AM7: 762.04478 | AO7: =D7/K7 -> 0.21007033 | AP7: =(1+D7/K7) -> 1.2100703 | AQ7: =LN(AO7) -> -1.5603129 | AR7: =LN(AP7) -> 0.19067848
A8: 37865 | B8: 65.371558 | C8: 184.23369 | D8: 1809.8389 | E8: 1823.3319 | F8: -15.561742 | G8: 1518.8011 | H8: 1563.724 | I8: -69.908429 | J8: 28.445305 | K8: 7821.0842 | L8: 56.700773 | M8: 76.08929 | N8: 53.342082 | O8: 29.197353 | P8: 35.354979 | Q8: 77.773829 | R8: 28.576576 | S8: 32.535825 | T8: 72.06317 | V8: 29.747351 | W8: 76.06002 | X8: 1574.0716 | Y8: 1610.9109 | Z8: 219.73084 | AA8: 409.19512 | AB8: 1792.6438 | AC8: 2009.5818 | AD8: 15.372044 | AE8: 380.67936 | AF8: 445.04945 | AG8: 18.865925 | AH8: 6.0976031 | AI8: 2.25 | AJ8: 1761.0996 | AK8: 421.08759 | AL8: 1307.4951 | AM8: 788.78491 | AO8: =D8/K8 -> 0.23140512 | AP8: =(1+D8/K8) -> 1.2314051 | AQ8: =LN(AO8) -> -1.4635853 | AR8: =LN(AP8) -> 0.20815589
A9: 37956 | B9: 65.786431 | C9: 185.11683 | D9: 1689.6627 | E9: 1772.9298 | F9: 250.49875 | G9: 1741.3533 | H9: 1603.9148 | I9: 180.88873 | J9: 32.500919 | K9: 8049.3086 | L9: 57.060617 | M9: 76.55272 | N9: 53.823933 | O9: 29.461099 | P9: 35.579355 | Q9: 78.146646 | R9: 28.834715 | S9: 32.74231 | T9: 72.408612 | V9: 30.45627 | W9: 76.43316 | X9: 1822.1877 | Y9: 1611.7988 | Z9: 226.88412 | AA9: 395.31807 | AB9: 2040.2929 | AC9: 2017.4775 | AD9: 16.769305 | AE9: 391.51653 | AF9: 475.56415 | AG9: 1.0263901 | AH9: 7.6914874 | AI9: 2.25 | AJ9: 1804.5495 | AK9: 312.22498 | AL9: 1343.9552 | AM9: 829.7208 | AO9: =D9/K9 -> 0.20991401 | AP9: =(1+D9/K9) -> 1.209914 | AQ9: =LN(AO9) -> -1.5610573 | AR9: =LN(AP9) -> 0.19054929
A10: 38047 | B10: 66.326534 | C10: 186.71285 | D10: 1787.5273 | E10: 1918.7608 | F10: 118.21221 | G10: 1739.4882 | H10: 1660.7248 | I10: 67.673952 | J10: 36.038825 | K10: 8396.4922 | L10: 57.529081 | M10: 77.09897 | N10: 55.006476 | O10: 30.108376 | P10: 35.87146 | Q10: 78.820404 | R10: 29.46823 | S10: 33.011122 | T10: 73.032897 | V10: 31.513628 | W10: 77.0226 | X10: 1783.1462 | Y10: 1688.9404 | Z10: 241.62166 | AA10: 465.17851 | AB10: 2023.4921 | AC10: 2139.5873 | AD10: 17.697735 | AE10: 435.57134 | AF10: 486.65567 | AG10: 1.1218982 | AH10: 5.3967888 | AI10: 2.5 | AJ10: 1950.5287 | AK10: 291.08009 | AL10: 1410.3901 | AM10: 862.9658 | AO10: =D10/K10 -> 0.21288977 | AP10: =(1+D10/K10) -> 1.2128898 | AQ10: =LN(AO10) -> -1.5469808 | AR10: =LN(AP10) -> 0.19300575
A11: 38139 | B11: 66.716009 | C11: 188.31622 | D11: 1925.2305 | E11: 1936.3442 | F11: -74.062393 | G11: 1932.1572 | H11: 1832.0244 | I11: 93.511676 | J11: 38.115748 | K11: 8671.4562 | L11: 57.866897 | M11: 77.72114 | N11: 55.754118 | O11: 30.517606 | P11: 36.0821 | Q11: 79.497261 | R11: 29.868759 | S11: 33.204967 | T11: 73.660056 | V11: 32.495652 | W11: 77.53995 | X11: 1964.8603 | Y11: 1819.0634 | Z11: 255.45685 | AA11: 481.24755 | AB11: 2231.006 | AC11: 2317.3202 | AD11: 22.391707 | AE11: 476.60544 | AF11: 498.31622 | AG11: 2.7709221 | AH11: 5.6165501 | AI11: 2.5 | AJ11: 1951.2135 | AK11: 492.01619 | AL11: 1381.0871 | AM11: 860.7288 | AO11: =D11/K11 -> 0.22201928 | AP11: =(1+D11/K11) -> 1.2220193 | AQ11: =LN(AO11) -> -1.504991 | AR11: =LN(AP11) -> 0.20050464
A12: 38231 | B12: 66.640867 | C12: 189.16226 | D12: 1870.2364 | E12: 2135.4849 | F12: 282.15273 | G12: 2002.3963 | H12: 1896.6952 | I12: 92.091342 | J12: 41.482443 | K12: 8973.9161 | L12: 57.801722 | M12: 78.21414 | N12: 56.778815 | O12: 31.078485 | P12: 36.041461 | Q12: 79.854415 | R12: 30.417713 | S12: 33.167568 | T12: 73.990985 | V12: 32.567124 | W12: 77.92186 | X12: 2063.5735 | Y12: 1953.242 | Z12: 257.6071 | AA12: 506.9841 | AB12: 2319.0541 | AC12: 2445.9801 | AD12: 26.824274 | AE12: 443.53895 | AF12: 509.14782 | AG12: 13.879282 | AH12: 6.0145196 | AI12: 2.5 | AJ12: 2089.4257 | AK12: 488.89313 | AL12: 1492.9999 | AM12: 900.56095 | AO12: =D12/K12 -> 0.20840806 | AP12: =(1+D12/K12) -> 1.2084081 | AQ12: =LN(AO12) -> -1.5682573 | AR12: =LN(AP12) -> 0.18930384
A13: 38322 | B13: 67.057985 | C13: 191.29958 | D13: 1875.7386 | E13: 2197.4753 | F13: 399.84056 | G13: 2071.6994 | H13: 2113.538 | I13: -14.101187 | J13: 49.827548 | K13: 9153.0831 | L13: 58.163514 | M13: 78.82054 | N13: 56.989001 | O13: 31.193532 | P13: 36.267051 | Q13: 80.756677 | R13: 30.530314 | S13: 33.37517 | T13: 74.826997 | V13: 33.142584 | W13: 78.5873 | X13: 2150.9195 | Y13: 2192.0791 | Z13: 259.33953 | AA13: 512.07888 | AB13: 2402.2826 | AC13: 2716.7852 | AD13: 32.454478 | AE13: 580.09802 | AF13: 552.95648 | AG13: 0.70515148 | AH13: 6.8226907 | AI13: 2.5 | AJ13: 2190.6819 | AK13: 651.373 | AL13: 1539.2459 | AM13: 978.503 | AO13: =D13/K13 -> 0.20492971 | AP13: =(1+D13/K13) -> 1.2049297 | AQ13: =LN(AO13) -> -1.5850883 | AR13: =LN(AP13) -> 0.18642123
... A41: 40878 | B41: 90.625336 | C41: 226.96056 | D41: 8110.1595 | E41: 8600.8229 | F41: 330.89367 | G41: 5842.7195 | H41: 6147.2152 | I41: -406.61436 | J41: 97.085138 | K41: 20641.679 | L41: 78.604927 | M41: 90.698 | N41: 94.645896 | O41: 51.805432 | P41: 49.01301 | Q41: 95.810882 | R41: 50.703976 | S41: 45.104785 | T41: 88.775824 | V41: 46.956041 | W41: 91.06976 | X41: 5988.1553 | Y41: 6164.7857 | Z41: 419.32662 | AA41: 783.69366 | AB41: 6411.556 | AC41: 6935.8545 | AD41: 25.343071 | AE41: 352.49587 | AF41: 698.31152 | AG41: 74.05274 | AH41: 20.668547 | AI41: 2.6 | AJ41: 8466.1925 | AK41: 3529.4884 | AL41: 4549.3472 | AM41: 2698.9453 | AO41: =D41/K41 -> 0.39290213 | AP41: =(1+D41/K41) -> 1.3929021 | AQ41: =LN(AO41) -> -0.93419474 | AR41: =LN(AP41) -> 0.33138943
A42: 40969 | B42: 91.850408 | C42: 228.49762 | D42: 9212.6493 | E42: 9411.3895 | F42: 153.40068 | G42: 6284.5909 | H42: 6103.3399 | I42: 111.72184 | J42: 103.58711 | K42: 21539.846 | L42: 79.667508 | M42: 91.23044 | N42: 97.084869 | O42: 53.14043 | P42: 49.675568 | Q42: 96.459747 | R42: 52.01059 | S42: 45.714511 | T42: 89.377045 | U42: 4560.4937 | V42: 48.326801 | W42: 91.67284 | X42: 6377.6228 | Y42: 6163.7585 | Z42: 434.71078 | AA42: 787.47921 | AB42: 6790.5582 | AC42: 6971.0956 | AD42: 25.033592 | AE42: 356.87222 | AF42: 734.23905 | AG42: 63.057308 | AH42: 36.547 | AI42: 2.7 | AJ42: 9027.0023 | AK42: 3988.2254 | AL42: 4890.183 | AM42: 2919.3108 | AO42: =D42/K42 -> 0.42770266 | AP42: =(1+D42/K42) -> 1.4277027 | AQ42: =LN(AO42) -> -0.84932705 | AR42: =LN(AP42) -> 0.35606662
A43: 41061 | B43: 92.674622 | C43: 229.02298 | D43: 9398.9108 | E43: 9058.0983 | F43: 93.631265 | G43: 5909.4331 | H43: 6084.6098 | I43: -118.93256 | J43: 91.796453 | K43: 21799.688 | L43: 80.382399 | M43: 91.6071 | N43: 97.257812 | O43: 53.235091 | P43: 50.121328 | Q43: 96.681524 | R43: 52.103239 | S43: 46.124728 | T43: 89.582538 | U43: 4013.875 | V43: 48.94164 | W43: 91.894 | X43: 6157.3317 | Y43: 6164.3727 | Z43: 455.92507 | AA43: 820.96045 | AB43: 6626.0122 | AC43: 6972.0545 | AD43: 26.632214 | AE43: 348.29469 | AF43: 703.40063 | AG43: 72.292247 | AH43: 29.538 | AI43: 2.7 | AJ43: 9034.1802 | AK43: 4026.1706 | AL43: 5016.4841 | AM43: 3011.0165 | AO43: =D43/K43 -> 0.43114887 | AP43: =(1+D43/K43) -> 1.4311489 | AQ43: =LN(AO43) -> -0.84130183 | AR43: =LN(AP43) -> 0.35847753
A44: 41153 | B44: 93.894779 | C44: 229.653 | D44: 9715.1594 | E44: 9281.2757 | F44: -404.50712 | G44: 5850.4068 | H44: 6233.7954 | I44: -363.89327 | J44: 90.19678 | K44: 22184.419 | L44: 81.440716 | M44: 92.10996 | N44: 97.386899 | O44: 53.305749 | P44: 50.781227 | Q44: 96.947489 | R44: 52.172394 | S44: 46.732007 | T44: 89.828974 | U44: 3509.019 | V44: 48.984097 | W44: 92.16095 | X44: 6089.7535 | Y44: 6294.5167 | Z44: 454.66437 | AA44: 804.87036 | AB44: 6547.3333 | AC44: 7106.9861 | AD44: 25.793884 | AE44: 345.21536 | AF44: 659.43937 | AG44: 67.119688 | AH44: 19.512 | AI44: 2.7 | AJ44: 8823.5805 | AK44: 3472.9432 | AL44: 5256.0849 | AM44: 3061.6365 | AO44: =D44/K44 -> 0.43792715 | AP44: =(1+D44/K44) -> 1.4379271 | AQ44: =LN(AO44) -> -0.82570272 | AR44: =LN(AP44) -> 0.36320259
A45: 41244 | B45: 94.77018 | C45: 231.19506 | D45: 9679.7748 | E45: 9247.579 | F45: -521.65824 | G45: 5731.5079 | H45: 5790.9932 | I45: -132.52794 | J45: 90.790325 | K45: 22211.095 | L45: 82.200005 | M45: 92.57141 | N45: 96.737176 | O45: 52.950116 | P45: 51.254671 | Q45: 97.598463 | R45: 51.824323 | S45: 47.1677 | T45: 90.43215 | U45: 2998.2883 | V45: 49.070474 | W45: 92.67732 | X45: 5925.7256 | Y45: 5925.1247 | Z45: 457.92578 | AA45: 784.33726 | AB45: 6394.0752 | AC45: 6695.6975 | AD45: 27.434982 | AE45: 341.86443 | AF45: 663.25748 | AG45: 73.922122 | AH45: 63.10864 | AI45: 2.7 | AJ45: 8374.6156 | AK45: 3222.5256 | AL45: 5189.9974 | AM45: 3188.8173 | AO45: =D45/K45 -> 0.43580809 | AP45: =(1+D45/K45) -> 1.4358081 | AQ45: =LN(AO45) -> -0.8305533 | AR45: =LN(AP45) -> 0.36172782
A46: 41334 | B46: 95.109464 | C46: 232.33447 | D46: 10556.451 | E46: 9781.3321 | F46: -979.90261 | G46: 6254.4999 | H46: 6648.5752 | I46: -317.09263 | J46: 95.369949 | K46: 23286.55 | L46: 82.494287 | M46: 92.93919 | N46: 98.965814 | O46: 54.169984 | P46: 51.438167 | Q46: 98.079462 | R46: 53.018255 | S46: 47.336563 | T46: 90.877831 | U46: 3650.9217 | V46: 49.512956 | W46: 93.00273 | X46: 6373.7387 | Y46: 6711.5868 | Z46: 482.92 | AA46: 844.68473 | AB46: 6829.6971 | AC46: 7579.2875 | AD46: 28.255886 | AE46: 348.29008 | AF46: 667.92171 | AG46: 57.538148 | AH46: 31.8252 | AI46: 2.7 | AJ46: 8876.6741 | AK46: 3480.773 | AL46: 5471.3128 | AM46: 3330.5747 | AO46: =D46/K46 -> 0.45332823 | AP46: =(1+D46/K46) -> 1.4533282 | AQ46: =LN(AO46) -> -0.79113885 | AR46: =LN(AP46) -> 0.37385626
A47: 41426 | B47: 95.408489 | C47: 232.22025 | D47: 10868.415 | E47: 9430.6178 | F47: -950.90153 | G47: 5815.3691 | H47: 6655.9651 | I47: -784.16292 | J47: 92.746275 | K47: 23615.576 | L47: 82.75365 | M47: 93.13935 | N47: 98.433936 | O47: 53.878856 | P47: 51.599889 | Q47: 98.031248 | R47: 52.733316 | S47: 47.48539 | T47: 90.833157 | U47: 3221.587 | V47: 49.697402 | W47: 93.04949 | X47: 6019.7241 | Y47: 6702.8407 | Z47: 496.49894 | AA47: 866.65221 | AB47: 6525.6729 | AC47: 7556.643 | AD47: 27.967979 | AE47: 365.11895 | AF47: 674.91508 | AG47: 79.239373 | AH47: 27.863 | AI47: 2.7 | AJ47: 9045.3116 | AK47: 3179.5201 | AL47: 5819.5911 | AM47: 3412.2709 | AO47: =D47/K47 -> 0.46022229 | AP47: =(1+D47/K47) -> 1.4602223 | AQ47: =LN(AO47) -> -0.77604567 | AR47: =LN(AP47) -> 0.37858868
A48: 41518 | B48: 95.853023 | C48: 233.25068 | D48: 11523.239 | E48: 10403.118 | F48: -733.10553 | G48: 6358.4941 | H48: 6498.2122 | I48: -108.76904 | J48: 103.50745 | K48: 24806.339 | L48: 83.139221 | M48: 93.59587 | N48: 100.75875 | O48: 55.151366 | P48: 51.840307 | Q48: 98.466241 | R48: 53.978771 | S48: 47.706637 | T48: 91.23621 | U48: 3725.5725 | V48: 50.450789 | W48: 93.43239 | X48: 6561.8854 | Y48: 6533.1803 | Z48: 521.32803 | AA48: 855.95023 | AB48: 7086.4031 | AC48: 7396.5112 | AD48: 28.071003 | AE48: 367.18652 | AF48: 681.78477 | AG48: 87.437265 | AH48: 18.582 | AI48: 2.7 | AJ48: 9539.8059 | AK48: 3818.0414 | AL48: 5764.1155 | AM48: 3462.4839 | AO48: =D48/K48 -> 0.46452801 | AP48: =(1+D48/K48) -> 1.464528 | AQ48: =LN(AO48) -> -0.76673343 | AR48: =LN(AP48) -> 0.38153301
A49: 41609 | B49: 96.977249 | C49: 234.00483 | D49: 11982.163 | E49: 11431.494 | F49: -1611.3284 | G49: 6417.6544 | H49: 6028.1215 | I49: 230.50055 | J49: 99.743949 | K49: 24861.869 | L49: 84.114332 | M49: 94.09085 | N49: 100.59493 | O49: 55.061696 | P49: 52.448323 | Q49: 98.784602 | R49: 53.891008 | S49: 48.266171 | T49: 91.531195 | U49: 3805.3494 | V49: 51.184089 | W49: 93.77631 | X49: 6614.1841 | Y49: 6191.058 | Z49: 538.29436 | AA49: 888.72858 | AB49: 7170.6759 | AC49: 7061.4893 | AD49: 28.355515 | AE49: 394.65964 | AF49: 677.17765 | AG49: 102.41611 | AH49: 17.444399 | AI49: 2.7 | AJ49: 9816.7131 | AK49: 3956.0692 | AL49: 5853.553 | AM49: 3454.4338 | AO49: =D49/K49 -> 0.48194941 | AP49: =(1+D49/K49) -> 1.4819494 | AQ49: =LN(AO49) -> -0.72991614 | AR49: =LN(AP49) -> 0.39335839
A50: 41699 | B50: 97.963578 | C50: 235.61578 | D50: 11325.558 | E50: 10023.632 | F50: -965.56663 | G50: 6745.8263 | H50: 6535.5065 | I50: 286.66348 | J50: 100.52994 | K50: 25249.782 | L50: 84.969836 | M50: 94.44779 | N50: 101.9135 | O50: 55.783432 | P50: 52.981761 | Q50: 99.46466 | R50: 54.597398 | S50: 48.757074 | T50: 92.161318 | U50: 3820.9151 | V50: 51.643614 | W50: 94.20694 | X50: 6920.2864 | Y50: 6521.0228 | Z50: 554.16949 | AA50: 883.67819 | AB50: 7438.7819 | AC50: 7430.7445 | AD50: 29.717491 | AE50: 423.81815 | AF50: 727.41531 | AG50: 144.73647 | AH50: 35.0736 | AI50: 2.7 | AJ50: 9596.5343 | AK50: 3732.3368 | AL50: 5929.6602 | AM50: 3461.2201 | AO50: =D50/K50 -> 0.44854084 | AP50: =(1+D50/K50) -> 1.4485408 | AQ50: =LN(AO50) -> -0.80175555 | AR50: =LN(AP50) -> 0.37055673
A51: 41791 | B51: 98.703415 | C51: 236.98945 | D51: 11774.004 | E51: 11006.365 | F51: -187.28018 | G51: 6590.9195 | H51: 6635.5497 | I51: 70.975111 | J51: 101.43838 | K51: 25809.369 | L51: 85.611542 | M51: 94.9822 | N51: 102.78689 | O51: 56.261489 | P51: 53.381888 | Q51: 100.04455 | R51: 55.065291 | S51: 49.125295 | T51: 92.698632 | U51: 3674.8668 | V51: 51.633083 | W51: 94.62783 | X51: 6887.9862 | Y51: 6684.9983 | Z51: 585.85423 | AA51: 870.45035 | AB51: 7487.3597 | AC51: 7542.5265 | AD51: 31.120591 | AE51: 396.58834 | AF51: 686.95236 | AG51: 125.15717 | AH51: 26.436 | AI51: 2.7 | AJ51: 9865.4361 | AK51: 3682.3312 | AL51: 6180.9884 | AM51: 3564.6512 | AO51: =D51/K51 -> 0.45619109 | AP51: =(1+D51/K51) -> 1.4561911 | AQ51: =LN(AO51) -> -0.7848435 | AR51: =LN(AP51) -> 0.37582419
A52: 41883 | B52: 99.782648 | C52: 237.4447 | D52: 12063.603 | E52: 10352.404 | F52: -1680.3627 | G52: 6489.104 | H52: 6533.0023 | I52: -36.930715 | J52: 95.079707 | K52: 26278.331 | L52: 86.547627 | M52: 95.37266 | N52: 102.86318 | O52: 56.303249 | P52: 53.965571 | Q52: 100.23674 | R52: 55.106164 | S52: 49.662436 | T52: 92.876705 | U52: 3205.7899 | V52: 51.449589 | W52: 94.88698 | X52: 6702.8103 | Y52: 6610.8815 | Z52: 595.75703 | AA52: 885.62532 | AB52: 7299.703 | AC52: 7503.1206 | AD52: 35.257232 | AE52: 362.16185 | AF52: 669.996 | AG52: 198.15013 | AH52: 18.7252 | AI52: 2.7 | AJ52: 9430.475 | AK52: 3286.8712 | AL52: 6198.5512 | AM52: 3655.6989 | AO52: =D52/K52 -> 0.45907037 | AP52: =(1+D52/K52) -> 1.4590704 | AQ52: =LN(AO52) -> -0.77855177 | AR52: =LN(AP52) -> 0.3777995
A53: 41974 | B53: 100.66683 | C53: 236.88391 | D53: 12063.429 | E53: 10330.11 | F53: -2452.2043 | G53: 5844.2515 | H53: 6735.8924 | I53: -1024.0911 | J53: 75.027241 | K53: 25380.312 | L53: 87.314534 | M53: 95.46732 | N53: 99.465996 | O53: 54.443765 | P53: 54.443765 | Q53: 100 | R53: 53.286214 | S53: 50.102499 | T53: 92.65735 | U53: 3271.9907 | V53: 50.699486 | W53: 94.7613 | X53: 6042.5199 | Y53: 6825.4354 | Z53: 607.66735 | AA53: 867.30042 | AB53: 6671.3933 | AC53: 7677.9042 | AD53: 24.854375 | AE53: 477.19706 | AF53: 641.77967 | AG53: 150.46483 | AH53: 17.351849 | AI53: 2.7 | AJ53: 9935.549 | AK53: 3151.9155 | AL53: 6619.5863 | AM53: 3780.7771 | AO53: =D53/K53 -> 0.47530658 | AP53: =(1+D53/K53) -> 1.4753066 | AQ53: =LN(AO53) -> -0.74379525 | AR53: =LN(AP53) -> 0.38886582
... A89: 45261 | B89: 111.95095 | C89: 308.11116 | D89: 12018.655 | E89: 0 | F89: 0 | G89: 2609.7386 | H89: 7277.9504 | I89: -4664.9205 | J89: 79.858249 | K89: 29167.529 | L89: 97.101946 | M89: 121.54626 | N89: 102.20865 | O89: 55.944987 | P89: 60.54657 | Q89: 130.06842 | R89: 54.755519 | S89: 55.718676 | T89: 120.51795 | U89: 3849.2331 | V89: 54.548717 | W89: 118.22876 | X89: 7919.3241 | Y89: 7398.0903 | Z89: 813.4812 | AA89: 1331.9868 | AB89: 8730.6301 | AC89: 8679.2516 | AD89: 62.22192 | AE89: 806.22853 | AF89: 1572.3943 | AG89: 307.64893 | AH89: 25.157311 | AI89: 2.8 | AJ89: 11106.129 | AK89: 3806.8701 | AL89: 7135.2808 | AM89: 3492.8517 | AO89: =D89/K89 -> 0.41205597 | AP89: =(1+D89/K89) -> 1.412056 | AQ89: =LN(AO89) -> -0.88659608 | AR89: =LN(AP89) -> 0.34504678

Sheet Hoja1
B2: Balanza comercial | C2: x -m (bienes+servicios)
B3: Balanza de servicios | C3: x-m (servicios
B4: Ingreso primario (rentas) | C4: recibida - pagada, credito - debito
B5: Ingreso secundario (TRANSFERENCIAS CORRIENTES) | C5: trans recibida - trans pagada, credito - debito
B6: Cuenta corriente | C6: balanza comercial + ing. Prim + ing. Secun
B7: Cuenta de capital | C7: Crédito (Transferencias de capital recibidas) - Debito (Transferencias de capital enviadas)
B8: Cuenta financiera | C8: (cambio de manual, valores negativos en cuentas)
